Workbook

Sheet effect_quant_by_period
A1: id | B1: time | C1: policy details | D1: policy effects and effect duration | E1: policy_group_name | F1: cumulative_policy_effect_mw | G1: observed cumulative MW deployed | H1: estimated cumulative MW deployed | I1: error-adjusted total policy effect in MW | J1: error-adjusted non-policy & unidentified policy effect in MW | K1: cumulative error-adjusted total policy mix effect in MW
A2: AUT | B2: 1991 | D2: - | E2: {=_xlfn.IFS(D2=policy_name_clustering!$A$2,policy_name_clustering!$C$2,D2=policy_name_clustering!$A$3,policy_name_clustering!$C$3,D2=policy_name_clustering!$A$5,policy_name_clustering!$C$5,D2=policy_name_clustering!$A$6,policy_name_clustering!$C$6,D2=policy_name_clustering!$A$7,policy_name_clustering!$C$7,D2=policy_name_clustering!$A$8,policy_name_clustering!$C$8,D2=policy_name_clustering!$A$9,policy_name_clustering!$C$9,D2=policy_name_clustering!$A$10,policy_name_clustering!$C$10,D2=policy_name_clustering!$A$11,policy_name_clustering!$C$11,D2=policy_name_clustering!$A$12,policy_name_clustering!$C$12,D2=policy_name_clustering!$A$13,policy_name_clustering!$C$13,D2=policy_name_clustering!$A$14,policy_name_clustering!$C$14,D2=policy_name_clustering!$A$15,policy_name_clustering!$C$15,D2=policy_name_clustering!$A$16,policy_name_clustering!$C$16,D2="-","",D2=policy_name_clustering!$A$4,policy_name_clustering!$C$4)} | G2: =wind_cump_cap!C3 -> 0 | H2: =estimated_capacity!C2 -> -8.2265578 | I2: {=_xlfn.IFS(D2= ""," ",D2<> " ",F2*(G2/H2))} -> 0 | J2: {=_xlfn.IFS(D2= ""," ",D2<> " ",(H2-F2)*(G2/H2))} -> 0 | K2: {=IF(ISNUMBER(H2),_xlfn.IFS(D2= ""," ",D2<> " ",F2*(G2/H2)),"")} -> 0
A3: AUT | B3: 1992 | D3: - | E3: {=_xlfn.IFS(D3=policy_name_clustering!$A$2,policy_name_clustering!$C$2,D3=policy_name_clustering!$A$3,policy_name_clustering!$C$3,D3=policy_name_clustering!$A$5,policy_name_clustering!$C$5,D3=policy_name_clustering!$A$6,policy_name_clustering!$C$6,D3=policy_name_clustering!$A$7,policy_name_clustering!$C$7,D3=policy_name_clustering!$A$8,policy_name_clustering!$C$8,D3=policy_name_clustering!$A$9,policy_name_clustering!$C$9,D3=policy_name_clustering!$A$10,policy_name_clustering!$C$10,D3=policy_name_clustering!$A$11,policy_name_clustering!$C$11,D3=policy_name_clustering!$A$12,policy_name_clustering!$C$12,D3=policy_name_clustering!$A$13,policy_name_clustering!$C$13,D3=policy_name_clustering!$A$14,policy_name_clustering!$C$14,D3=policy_name_clustering!$A$15,policy_name_clustering!$C$15,D3=policy_name_clustering!$A$16,policy_name_clustering!$C$16,D3="-","",D3=policy_name_clustering!$A$4,policy_name_clustering!$C$4)} | G3: =wind_cump_cap!C4 -> 0 | H3: =estimated_capacity!C3 -> -12.430992 | I3: {=_xlfn.IFS(D3= ""," ",D3<> " ",F3*(G3/H3))} -> 0 | J3: {=_xlfn.IFS(D3= ""," ",D3<> " ",(H3-F3)*(G3/H3))} -> 0 | K3: {=IF(ISNUMBER(H3),_xlfn.IFS(D3= ""," ",D3<> " ",F3*(G3/H3)),"")} -> 0
A4: AUT | B4: 1993 | D4: - | E4: {=_xlfn.IFS(D4=policy_name_clustering!$A$2,policy_name_clustering!$C$2,D4=policy_name_clustering!$A$3,policy_name_clustering!$C$3,D4=policy_name_clustering!$A$5,policy_name_clustering!$C$5,D4=policy_name_clustering!$A$6,policy_name_clustering!$C$6,D4=policy_name_clustering!$A$7,policy_name_clustering!$C$7,D4=policy_name_clustering!$A$8,policy_name_clustering!$C$8,D4=policy_name_clustering!$A$9,policy_name_clustering!$C$9,D4=policy_name_clustering!$A$10,policy_name_clustering!$C$10,D4=policy_name_clustering!$A$11,policy_name_clustering!$C$11,D4=policy_name_clustering!$A$12,policy_name_clustering!$C$12,D4=policy_name_clustering!$A$13,policy_name_clustering!$C$13,D4=policy_name_clustering!$A$14,policy_name_clustering!$C$14,D4=policy_name_clustering!$A$15,policy_name_clustering!$C$15,D4=policy_name_clustering!$A$16,policy_name_clustering!$C$16,D4="-","",D4=policy_name_clustering!$A$4,policy_name_clustering!$C$4)} | G4: =wind_cump_cap!C5 -> 1 | H4: =estimated_capacity!C4 -> -10.517072 | I4: {=_xlfn.IFS(D4= ""," ",D4<> " ",F4*(G4/H4))} -> 0 | J4: {=_xlfn.IFS(D4= ""," ",D4<> " ",(H4-F4)*(G4/H4))} -> 1 | K4: {=IF(ISNUMBER(H4),_xlfn.IFS(D4= ""," ",D4<> " ",F4*(G4/H4)),"")} -> 0
A5: AUT | B5: 1994 | D5: - | E5: {=_xlfn.IFS(D5=policy_name_clustering!$A$2,policy_name_clustering!$C$2,D5=policy_name_clustering!$A$3,policy_name_clustering!$C$3,D5=policy_name_clustering!$A$5,policy_name_clustering!$C$5,D5=policy_name_clustering!$A$6,policy_name_clustering!$C$6,D5=policy_name_clustering!$A$7,policy_name_clustering!$C$7,D5=policy_name_clustering!$A$8,policy_name_clustering!$C$8,D5=policy_name_clustering!$A$9,policy_name_clustering!$C$9,D5=policy_name_clustering!$A$10,policy_name_clustering!$C$10,D5=policy_name_clustering!$A$11,policy_name_clustering!$C$11,D5=policy_name_clustering!$A$12,policy_name_clustering!$C$12,D5=policy_name_clustering!$A$13,policy_name_clustering!$C$13,D5=policy_name_clustering!$A$14,policy_name_clustering!$C$14,D5=policy_name_clustering!$A$15,policy_name_clustering!$C$15,D5=policy_name_clustering!$A$16,policy_name_clustering!$C$16,D5="-","",D5=policy_name_clustering!$A$4,policy_name_clustering!$C$4)} | G5: =wind_cump_cap!C6 -> 1 | H5: =estimated_capacity!C5 -> -4.4677335 | I5: {=_xlfn.IFS(D5= ""," ",D5<> " ",F5*(G5/H5))} -> 0 | J5: {=_xlfn.IFS(D5= ""," ",D5<> " ",(H5-F5)*(G5/H5))} -> 1 | K5: {=IF(ISNUMBER(H5),_xlfn.IFS(D5= ""," ",D5<> " ",F5*(G5/H5)),"")} -> 0
A6: AUT | B6: 1995 | D6: - | E6: {=_xlfn.IFS(D6=policy_name_clustering!$A$2,policy_name_clustering!$C$2,D6=policy_name_clustering!$A$3,policy_name_clustering!$C$3,D6=policy_name_clustering!$A$5,policy_name_clustering!$C$5,D6=policy_name_clustering!$A$6,policy_name_clustering!$C$6,D6=policy_name_clustering!$A$7,policy_name_clustering!$C$7,D6=policy_name_clustering!$A$8,policy_name_clustering!$C$8,D6=policy_name_clustering!$A$9,policy_name_clustering!$C$9,D6=policy_name_clustering!$A$10,policy_name_clustering!$C$10,D6=policy_name_clustering!$A$11,policy_name_clustering!$C$11,D6=policy_name_clustering!$A$12,policy_name_clustering!$C$12,D6=policy_name_clustering!$A$13,policy_name_clustering!$C$13,D6=policy_name_clustering!$A$14,policy_name_clustering!$C$14,D6=policy_name_clustering!$A$15,policy_name_clustering!$C$15,D6=policy_name_clustering!$A$16,policy_name_clustering!$C$16,D6="-","",D6=policy_name_clustering!$A$4,policy_name_clustering!$C$4)} | G6: =wind_cump_cap!C7 -> 1 | H6: =estimated_capacity!C6 -> 13.625984 | I6: {=_xlfn.IFS(D6= ""," ",D6<> " ",F6*(G6/H6))} -> 0 | J6: {=_xlfn.IFS(D6= ""," ",D6<> " ",(H6-F6)*(G6/H6))} -> 1 | K6: {=IF(ISNUMBER(H6),_xlfn.IFS(D6= ""," ",D6<> " ",F6*(G6/H6)),"")} -> 0
A7: AUT | B7: 1996 | D7: - | E7: {=_xlfn.IFS(D7=policy_name_clustering!$A$2,policy_name_clustering!$C$2,D7=policy_name_clustering!$A$3,policy_name_clustering!$C$3,D7=policy_name_clustering!$A$5,policy_name_clustering!$C$5,D7=policy_name_clustering!$A$6,policy_name_clustering!$C$6,D7=policy_name_clustering!$A$7,policy_name_clustering!$C$7,D7=policy_name_clustering!$A$8,policy_name_clustering!$C$8,D7=policy_name_clustering!$A$9,policy_name_clustering!$C$9,D7=policy_name_clustering!$A$10,policy_name_clustering!$C$10,D7=policy_name_clustering!$A$11,policy_name_clustering!$C$11,D7=policy_name_clustering!$A$12,policy_name_clustering!$C$12,D7=policy_name_clustering!$A$13,policy_name_clustering!$C$13,D7=policy_name_clustering!$A$14,policy_name_clustering!$C$14,D7=policy_name_clustering!$A$15,policy_name_clustering!$C$15,D7=policy_name_clustering!$A$16,policy_name_clustering!$C$16,D7="-","",D7=policy_name_clustering!$A$4,policy_name_clustering!$C$4)} | G7: =wind_cump_cap!C8 -> 3 | H7: =estimated_capacity!C7 -> 41.36612 | I7: {=_xlfn.IFS(D7= ""," ",D7<> " ",F7*(G7/H7))} -> 0 | J7: {=_xlfn.IFS(D7= ""," ",D7<> " ",(H7-F7)*(G7/H7))} -> 3 | K7: {=IF(ISNUMBER(H7),_xlfn.IFS(D7= ""," ",D7<> " ",F7*(G7/H7)),"")} -> 0
A8: AUT | B8: 1997 | D8: - | E8: {=_xlfn.IFS(D8=policy_name_clustering!$A$2,policy_name_clustering!$C$2,D8=policy_name_clustering!$A$3,policy_name_clustering!$C$3,D8=policy_name_clustering!$A$5,policy_name_clustering!$C$5,D8=policy_name_clustering!$A$6,policy_name_clustering!$C$6,D8=policy_name_clustering!$A$7,policy_name_clustering!$C$7,D8=policy_name_clustering!$A$8,policy_name_clustering!$C$8,D8=policy_name_clustering!$A$9,policy_name_clustering!$C$9,D8=policy_name_clustering!$A$10,policy_name_clustering!$C$10,D8=policy_name_clustering!$A$11,policy_name_clustering!$C$11,D8=policy_name_clustering!$A$12,policy_name_clustering!$C$12,D8=policy_name_clustering!$A$13,policy_name_clustering!$C$13,D8=policy_name_clustering!$A$14,policy_name_clustering!$C$14,D8=policy_name_clustering!$A$15,policy_name_clustering!$C$15,D8=policy_name_clustering!$A$16,policy_name_clustering!$C$16,D8="-","",D8=policy_name_clustering!$A$4,policy_name_clustering!$C$4)} | G8: =wind_cump_cap!C9 -> 15 | H8: =estimated_capacity!C8 -> 81.797647 | I8: {=_xlfn.IFS(D8= ""," ",D8<> " ",F8*(G8/H8))} -> 0 | J8: {=_xlfn.IFS(D8= ""," ",D8<> " ",(H8-F8)*(G8/H8))} -> 15 | K8: {=IF(ISNUMBER(H8),_xlfn.IFS(D8= ""," ",D8<> " ",F8*(G8/H8)),"")} -> 0
A9: AUT | B9: 1998 | D9: - | E9: {=_xlfn.IFS(D9=policy_name_clustering!$A$2,policy_name_clustering!$C$2,D9=policy_name_clustering!$A$3,policy_name_clustering!$C$3,D9=policy_name_clustering!$A$5,policy_name_clustering!$C$5,D9=policy_name_clustering!$A$6,policy_name_clustering!$C$6,D9=policy_name_clustering!$A$7,policy_name_clustering!$C$7,D9=policy_name_clustering!$A$8,policy_name_clustering!$C$8,D9=policy_name_clustering!$A$9,policy_name_clustering!$C$9,D9=policy_name_clustering!$A$10,policy_name_clustering!$C$10,D9=policy_name_clustering!$A$11,policy_name_clustering!$C$11,D9=policy_name_clustering!$A$12,policy_name_clustering!$C$12,D9=policy_name_clustering!$A$13,policy_name_clustering!$C$13,D9=policy_name_clustering!$A$14,policy_name_clustering!$C$14,D9=policy_name_clustering!$A$15,policy_name_clustering!$C$15,D9=policy_name_clustering!$A$16,policy_name_clustering!$C$16,D9="-","",D9=policy_name_clustering!$A$4,policy_name_clustering!$C$4)} | G9: =wind_cump_cap!C10 -> 34 | H9: =estimated_capacity!C9 -> 125.66332 | I9: {=_xlfn.IFS(D9= ""," ",D9<> " ",F9*(G9/H9))} -> 0 | J9: {=_xlfn.IFS(D9= ""," ",D9<> " ",(H9-F9)*(G9/H9))} -> 34 | K9: {=IF(ISNUMBER(H9),_xlfn.IFS(D9= ""," ",D9<> " ",F9*(G9/H9)),"")} -> 0
A10: AUT | B10: 1999 | D10: - | E10: {=_xlfn.IFS(D10=policy_name_clustering!$A$2,policy_name_clustering!$C$2,D10=policy_name_clustering!$A$3,policy_name_clustering!$C$3,D10=policy_name_clustering!$A$5,policy_name_clustering!$C$5,D10=policy_name_clustering!$A$6,policy_name_clustering!$C$6,D10=policy_name_clustering!$A$7,policy_name_clustering!$C$7,D10=policy_name_clustering!$A$8,policy_name_clustering!$C$8,D10=policy_name_clustering!$A$9,policy_name_clustering!$C$9,D10=policy_name_clustering!$A$10,policy_name_clustering!$C$10,D10=policy_name_clustering!$A$11,policy_name_clustering!$C$11,D10=policy_name_clustering!$A$12,policy_name_clustering!$C$12,D10=policy_name_clustering!$A$13,policy_name_clustering!$C$13,D10=policy_name_clustering!$A$14,policy_name_clustering!$C$14,D10=policy_name_clustering!$A$15,policy_name_clustering!$C$15,D10=policy_name_clustering!$A$16,policy_name_clustering!$C$16,D10="-","",D10=policy_name_clustering!$A$4,policy_name_clustering!$C$4)} | G10: =wind_cump_cap!C11 -> 38 | H10: =estimated_capacity!C10 -> 181.79522 | I10: {=_xlfn.IFS(D10= ""," ",D10<> " ",F10*(G10/H10))} -> 0 | J10: {=_xlfn.IFS(D10= ""," ",D10<> " ",(H10-F10)*(G10/H10))} -> 38 | K10: {=IF(ISNUMBER(H10),_xlfn.IFS(D10= ""," ",D10<> " ",F10*(G10/H10)),"")} -> 0
A11: AUT | B11: 2000 | D11: - | E11: {=_xlfn.IFS(D11=policy_name_clustering!$A$2,policy_name_clustering!$C$2,D11=policy_name_clustering!$A$3,policy_name_clustering!$C$3,D11=policy_name_clustering!$A$5,policy_name_clustering!$C$5,D11=policy_name_clustering!$A$6,policy_name_clustering!$C$6,D11=policy_name_clustering!$A$7,policy_name_clustering!$C$7,D11=policy_name_clustering!$A$8,policy_name_clustering!$C$8,D11=policy_name_clustering!$A$9,policy_name_clustering!$C$9,D11=policy_name_clustering!$A$10,policy_name_clustering!$C$10,D11=policy_name_clustering!$A$11,policy_name_clustering!$C$11,D11=policy_name_clustering!$A$12,policy_name_clustering!$C$12,D11=policy_name_clustering!$A$13,policy_name_clustering!$C$13,D11=policy_name_clustering!$A$14,policy_name_clustering!$C$14,D11=policy_name_clustering!$A$15,policy_name_clustering!$C$15,D11=policy_name_clustering!$A$16,policy_name_clustering!$C$16,D11="-","",D11=policy_name_clustering!$A$4,policy_name_clustering!$C$4)} | G11: =wind_cump_cap!C12 -> 50 | H11: =estimated_capacity!C11 -> 239.55534 | I11: {=_xlfn.IFS(D11= ""," ",D11<> " ",F11*(G11/H11))} -> 0 | J11: {=_xlfn.IFS(D11= ""," ",D11<> " ",(H11-F11)*(G11/H11))} -> 50 | K11: {=IF(ISNUMBER(H11),_xlfn.IFS(D11= ""," ",D11<> " ",F11*(G11/H11)),"")} -> 0
A12: AUT | B12: 2001 | D12: - | E12: {=_xlfn.IFS(D12=policy_name_clustering!$A$2,policy_name_clustering!$C$2,D12=policy_name_clustering!$A$3,policy_name_clustering!$C$3,D12=policy_name_clustering!$A$5,policy_name_clustering!$C$5,D12=policy_name_clustering!$A$6,policy_name_clustering!$C$6,D12=policy_name_clustering!$A$7,policy_name_clustering!$C$7,D12=policy_name_clustering!$A$8,policy_name_clustering!$C$8,D12=policy_name_clustering!$A$9,policy_name_clustering!$C$9,D12=policy_name_clustering!$A$10,policy_name_clustering!$C$10,D12=policy_name_clustering!$A$11,policy_name_clustering!$C$11,D12=policy_name_clustering!$A$12,policy_name_clustering!$C$12,D12=policy_name_clustering!$A$13,policy_name_clustering!$C$13,D12=policy_name_clustering!$A$14,policy_name_clustering!$C$14,D12=policy_name_clustering!$A$15,policy_name_clustering!$C$15,D12=policy_name_clustering!$A$16,policy_name_clustering!$C$16,D12="-","",D12=policy_name_clustering!$A$4,policy_name_clustering!$C$4)} | G12: =wind_cump_cap!C13 -> 67 | H12: =estimated_capacity!C12 -> 311.97932 | I12: {=_xlfn.IFS(D12= ""," ",D12<> " ",F12*(G12/H12))} -> 0 | J12: {=_xlfn.IFS(D12= ""," ",D12<> " ",(H12-F12)*(G12/H12))} -> 67 | K12: {=IF(ISNUMBER(H12),_xlfn.IFS(D12= ""," ",D12<> " ",F12*(G12/H12)),"")} -> 0
A13: AUT | B13: 2002 | D13: - | E13: {=_xlfn.IFS(D13=policy_name_clustering!$A$2,policy_name_clustering!$C$2,D13=policy_name_clustering!$A$3,policy_name_clustering!$C$3,D13=policy_name_clustering!$A$5,policy_name_clustering!$C$5,D13=policy_name_clustering!$A$6,policy_name_clustering!$C$6,D13=policy_name_clustering!$A$7,policy_name_clustering!$C$7,D13=policy_name_clustering!$A$8,policy_name_clustering!$C$8,D13=policy_name_clustering!$A$9,policy_name_clustering!$C$9,D13=policy_name_clustering!$A$10,policy_name_clustering!$C$10,D13=policy_name_clustering!$A$11,policy_name_clustering!$C$11,D13=policy_name_clustering!$A$12,policy_name_clustering!$C$12,D13=policy_name_clustering!$A$13,policy_name_clustering!$C$13,D13=policy_name_clustering!$A$14,policy_name_clustering!$C$14,D13=policy_name_clustering!$A$15,policy_name_clustering!$C$15,D13=policy_name_clustering!$A$16,policy_name_clustering!$C$16,D13="-","",D13=policy_name_clustering!$A$4,policy_name_clustering!$C$4)} | G13: =wind_cump_cap!C14 -> 109 | H13: =estimated_capacity!C13 -> 386.63779 | I13: {=_xlfn.IFS(D13= ""," ",D13<> " ",F13*(G13/H13))} -> 0 | J13: {=_xlfn.IFS(D13= ""," ",D13<> " ",(H13-F13)*(G13/H13))} -> 109 | K13: {=IF(ISNUMBER(H13),_xlfn.IFS(D13= ""," ",D13<> " ",F13*(G13/H13)),"")} -> 0
... A34: AUT | B34: 2023 | D34: - | E34: {=_xlfn.IFS(D34=policy_name_clustering!$A$2,policy_name_clustering!$C$2,D34=policy_name_clustering!$A$3,policy_name_clustering!$C$3,D34=policy_name_clustering!$A$5,policy_name_clustering!$C$5,D34=policy_name_clustering!$A$6,policy_name_clustering!$C$6,D34=policy_name_clustering!$A$7,policy_name_clustering!$C$7,D34=policy_name_clustering!$A$8,policy_name_clustering!$C$8,D34=policy_name_clustering!$A$9,policy_name_clustering!$C$9,D34=policy_name_clustering!$A$10,policy_name_clustering!$C$10,D34=policy_name_clustering!$A$11,policy_name_clustering!$C$11,D34=policy_name_clustering!$A$12,policy_name_clustering!$C$12,D34=policy_name_clustering!$A$13,policy_name_clustering!$C$13,D34=policy_name_clustering!$A$14,policy_name_clustering!$C$14,D34=policy_name_clustering!$A$15,policy_name_clustering!$C$15,D34=policy_name_clustering!$A$16,policy_name_clustering!$C$16,D34="-","",D34=policy_name_clustering!$A$4,policy_name_clustering!$C$4)} | G34: =wind_cump_cap!C35 -> 3896.294 | H34: =estimated_capacity!C34 -> 3836.5655 | I34: {=_xlfn.IFS(D34= ""," ",D34<> " ",F34*(G34/H34))} -> 0 | J34: {=_xlfn.IFS(D34= ""," ",D34<> " ",(H34-F34)*(G34/H34))} -> 3896.294 | K34: {=IF(ISNUMBER(H34),_xlfn.IFS(D34= ""," ",D34<> " ",F34*(G34/H34)),"")} -> 0
A35: BEL | B35: 1991 | D35: - | E35: {=_xlfn.IFS(D35=policy_name_clustering!$A$2,policy_name_clustering!$C$2,D35=policy_name_clustering!$A$3,policy_name_clustering!$C$3,D35=policy_name_clustering!$A$5,policy_name_clustering!$C$5,D35=policy_name_clustering!$A$6,policy_name_clustering!$C$6,D35=policy_name_clustering!$A$7,policy_name_clustering!$C$7,D35=policy_name_clustering!$A$8,policy_name_clustering!$C$8,D35=policy_name_clustering!$A$9,policy_name_clustering!$C$9,D35=policy_name_clustering!$A$10,policy_name_clustering!$C$10,D35=policy_name_clustering!$A$11,policy_name_clustering!$C$11,D35=policy_name_clustering!$A$12,policy_name_clustering!$C$12,D35=policy_name_clustering!$A$13,policy_name_clustering!$C$13,D35=policy_name_clustering!$A$14,policy_name_clustering!$C$14,D35=policy_name_clustering!$A$15,policy_name_clustering!$C$15,D35=policy_name_clustering!$A$16,policy_name_clustering!$C$16,D35="-","",D35=policy_name_clustering!$A$4,policy_name_clustering!$C$4)} | G35: =wind_cump_cap!C37 -> 5 | H35: =estimated_capacity!C35 -> 2.3630401 | I35: {=_xlfn.IFS(D35= ""," ",D35<> " ",F35*(G35/H35))} -> 0 | J35: {=_xlfn.IFS(D35= ""," ",D35<> " ",(H35-F35)*(G35/H35))} -> 5 | K35: {=IF(ISNUMBER(H35),_xlfn.IFS(D35= ""," ",D35<> " ",F35*(G35/H35)),"")} -> 0
A36: BEL | B36: 1992 | D36: - | E36: {=_xlfn.IFS(D36=policy_name_clustering!$A$2,policy_name_clustering!$C$2,D36=policy_name_clustering!$A$3,policy_name_clustering!$C$3,D36=policy_name_clustering!$A$5,policy_name_clustering!$C$5,D36=policy_name_clustering!$A$6,policy_name_clustering!$C$6,D36=policy_name_clustering!$A$7,policy_name_clustering!$C$7,D36=policy_name_clustering!$A$8,policy_name_clustering!$C$8,D36=policy_name_clustering!$A$9,policy_name_clustering!$C$9,D36=policy_name_clustering!$A$10,policy_name_clustering!$C$10,D36=policy_name_clustering!$A$11,policy_name_clustering!$C$11,D36=policy_name_clustering!$A$12,policy_name_clustering!$C$12,D36=policy_name_clustering!$A$13,policy_name_clustering!$C$13,D36=policy_name_clustering!$A$14,policy_name_clustering!$C$14,D36=policy_name_clustering!$A$15,policy_name_clustering!$C$15,D36=policy_name_clustering!$A$16,policy_name_clustering!$C$16,D36="-","",D36=policy_name_clustering!$A$4,policy_name_clustering!$C$4)} | G36: =wind_cump_cap!C38 -> 5 | H36: =estimated_capacity!C36 -> 7.8625886 | I36: {=_xlfn.IFS(D36= ""," ",D36<> " ",F36*(G36/H36))} -> 0 | J36: {=_xlfn.IFS(D36= ""," ",D36<> " ",(H36-F36)*(G36/H36))} -> 5 | K36: {=IF(ISNUMBER(H36),_xlfn.IFS(D36= ""," ",D36<> " ",F36*(G36/H36)),"")} -> 0
A37: BEL | B37: 1993 | D37: - | E37: {=_xlfn.IFS(D37=policy_name_clustering!$A$2,policy_name_clustering!$C$2,D37=policy_name_clustering!$A$3,policy_name_clustering!$C$3,D37=policy_name_clustering!$A$5,policy_name_clustering!$C$5,D37=policy_name_clustering!$A$6,policy_name_clustering!$C$6,D37=policy_name_clustering!$A$7,policy_name_clustering!$C$7,D37=policy_name_clustering!$A$8,policy_name_clustering!$C$8,D37=policy_name_clustering!$A$9,policy_name_clustering!$C$9,D37=policy_name_clustering!$A$10,policy_name_clustering!$C$10,D37=policy_name_clustering!$A$11,policy_name_clustering!$C$11,D37=policy_name_clustering!$A$12,policy_name_clustering!$C$12,D37=policy_name_clustering!$A$13,policy_name_clustering!$C$13,D37=policy_name_clustering!$A$14,policy_name_clustering!$C$14,D37=policy_name_clustering!$A$15,policy_name_clustering!$C$15,D37=policy_name_clustering!$A$16,policy_name_clustering!$C$16,D37="-","",D37=policy_name_clustering!$A$4,policy_name_clustering!$C$4)} | G37: =wind_cump_cap!C39 -> 5 | H37: =estimated_capacity!C37 -> 21.679653 | I37: {=_xlfn.IFS(D37= ""," ",D37<> " ",F37*(G37/H37))} -> 0 | J37: {=_xlfn.IFS(D37= ""," ",D37<> " ",(H37-F37)*(G37/H37))} -> 5 | K37: {=IF(ISNUMBER(H37),_xlfn.IFS(D37= ""," ",D37<> " ",F37*(G37/H37)),"")} -> 0
A38: BEL | B38: 1994 | D38: - | E38: {=_xlfn.IFS(D38=policy_name_clustering!$A$2,policy_name_clustering!$C$2,D38=policy_name_clustering!$A$3,policy_name_clustering!$C$3,D38=policy_name_clustering!$A$5,policy_name_clustering!$C$5,D38=policy_name_clustering!$A$6,policy_name_clustering!$C$6,D38=policy_name_clustering!$A$7,policy_name_clustering!$C$7,D38=policy_name_clustering!$A$8,policy_name_clustering!$C$8,D38=policy_name_clustering!$A$9,policy_name_clustering!$C$9,D38=policy_name_clustering!$A$10,policy_name_clustering!$C$10,D38=policy_name_clustering!$A$11,policy_name_clustering!$C$11,D38=policy_name_clustering!$A$12,policy_name_clustering!$C$12,D38=policy_name_clustering!$A$13,policy_name_clustering!$C$13,D38=policy_name_clustering!$A$14,policy_name_clustering!$C$14,D38=policy_name_clustering!$A$15,policy_name_clustering!$C$15,D38=policy_name_clustering!$A$16,policy_name_clustering!$C$16,D38="-","",D38=policy_name_clustering!$A$4,policy_name_clustering!$C$4)} | G38: =wind_cump_cap!C40 -> 5 | H38: =estimated_capacity!C38 -> 39.446623 | I38: {=_xlfn.IFS(D38= ""," ",D38<> " ",F38*(G38/H38))} -> 0 | J38: {=_xlfn.IFS(D38= ""," ",D38<> " ",(H38-F38)*(G38/H38))} -> 5 | K38: {=IF(ISNUMBER(H38),_xlfn.IFS(D38= ""," ",D38<> " ",F38*(G38/H38)),"")} -> 0
A39: BEL | B39: 1995 | D39: - | E39: {=_xlfn.IFS(D39=policy_name_clustering!$A$2,policy_name_clustering!$C$2,D39=policy_name_clustering!$A$3,policy_name_clustering!$C$3,D39=policy_name_clustering!$A$5,policy_name_clustering!$C$5,D39=policy_name_clustering!$A$6,policy_name_clustering!$C$6,D39=policy_name_clustering!$A$7,policy_name_clustering!$C$7,D39=policy_name_clustering!$A$8,policy_name_clustering!$C$8,D39=policy_name_clustering!$A$9,policy_name_clustering!$C$9,D39=policy_name_clustering!$A$10,policy_name_clustering!$C$10,D39=policy_name_clustering!$A$11,policy_name_clustering!$C$11,D39=policy_name_clustering!$A$12,policy_name_clustering!$C$12,D39=policy_name_clustering!$A$13,policy_name_clustering!$C$13,D39=policy_name_clustering!$A$14,policy_name_clustering!$C$14,D39=policy_name_clustering!$A$15,policy_name_clustering!$C$15,D39=policy_name_clustering!$A$16,policy_name_clustering!$C$16,D39="-","",D39=policy_name_clustering!$A$4,policy_name_clustering!$C$4)} | G39: =wind_cump_cap!C41 -> 5 | H39: =estimated_capacity!C39 -> 71.635675 | I39: {=_xlfn.IFS(D39= ""," ",D39<> " ",F39*(G39/H39))} -> 0 | J39: {=_xlfn.IFS(D39= ""," ",D39<> " ",(H39-F39)*(G39/H39))} -> 5 | K39: {=IF(ISNUMBER(H39),_xlfn.IFS(D39= ""," ",D39<> " ",F39*(G39/H39)),"")} -> 0
A40: BEL | B40: 1996 | D40: - | E40: {=_xlfn.IFS(D40=policy_name_clustering!$A$2,policy_name_clustering!$C$2,D40=policy_name_clustering!$A$3,policy_name_clustering!$C$3,D40=policy_name_clustering!$A$5,policy_name_clustering!$C$5,D40=policy_name_clustering!$A$6,policy_name_clustering!$C$6,D40=policy_name_clustering!$A$7,policy_name_clustering!$C$7,D40=policy_name_clustering!$A$8,policy_name_clustering!$C$8,D40=policy_name_clustering!$A$9,policy_name_clustering!$C$9,D40=policy_name_clustering!$A$10,policy_name_clustering!$C$10,D40=policy_name_clustering!$A$11,policy_name_clustering!$C$11,D40=policy_name_clustering!$A$12,policy_name_clustering!$C$12,D40=policy_name_clustering!$A$13,policy_name_clustering!$C$13,D40=policy_name_clustering!$A$14,policy_name_clustering!$C$14,D40=policy_name_clustering!$A$15,policy_name_clustering!$C$15,D40=policy_name_clustering!$A$16,policy_name_clustering!$C$16,D40="-","",D40=policy_name_clustering!$A$4,policy_name_clustering!$C$4)} | G40: =wind_cump_cap!C42 -> 5 | H40: =estimated_capacity!C40 -> 115.13255 | I40: {=_xlfn.IFS(D40= ""," ",D40<> " ",F40*(G40/H40))} -> 0 | J40: {=_xlfn.IFS(D40= ""," ",D40<> " ",(H40-F40)*(G40/H40))} -> 5 | K40: {=IF(ISNUMBER(H40),_xlfn.IFS(D40= ""," ",D40<> " ",F40*(G40/H40)),"")} -> 0
A41: BEL | B41: 1997 | D41: - | E41: {=_xlfn.IFS(D41=policy_name_clustering!$A$2,policy_name_clustering!$C$2,D41=policy_name_clustering!$A$3,policy_name_clustering!$C$3,D41=policy_name_clustering!$A$5,policy_name_clustering!$C$5,D41=policy_name_clustering!$A$6,policy_name_clustering!$C$6,D41=policy_name_clustering!$A$7,policy_name_clustering!$C$7,D41=policy_name_clustering!$A$8,policy_name_clustering!$C$8,D41=policy_name_clustering!$A$9,policy_name_clustering!$C$9,D41=policy_name_clustering!$A$10,policy_name_clustering!$C$10,D41=policy_name_clustering!$A$11,policy_name_clustering!$C$11,D41=policy_name_clustering!$A$12,policy_name_clustering!$C$12,D41=policy_name_clustering!$A$13,policy_name_clustering!$C$13,D41=policy_name_clustering!$A$14,policy_name_clustering!$C$14,D41=policy_name_clustering!$A$15,policy_name_clustering!$C$15,D41=policy_name_clustering!$A$16,policy_name_clustering!$C$16,D41="-","",D41=policy_name_clustering!$A$4,policy_name_clustering!$C$4)} | G41: =wind_cump_cap!C43 -> 5 | H41: =estimated_capacity!C41 -> 173.19867 | I41: {=_xlfn.IFS(D41= ""," ",D41<> " ",F41*(G41/H41))} -> 0 | J41: {=_xlfn.IFS(D41= ""," ",D41<> " ",(H41-F41)*(G41/H41))} -> 5 | K41: {=IF(ISNUMBER(H41),_xlfn.IFS(D41= ""," ",D41<> " ",F41*(G41/H41)),"")} -> 0
A42: BEL | B42: 1998 | D42: - | E42: {=_xlfn.IFS(D42=policy_name_clustering!$A$2,policy_name_clustering!$C$2,D42=policy_name_clustering!$A$3,policy_name_clustering!$C$3,D42=policy_name_clustering!$A$5,policy_name_clustering!$C$5,D42=policy_name_clustering!$A$6,policy_name_clustering!$C$6,D42=policy_name_clustering!$A$7,policy_name_clustering!$C$7,D42=policy_name_clustering!$A$8,policy_name_clustering!$C$8,D42=policy_name_clustering!$A$9,policy_name_clustering!$C$9,D42=policy_name_clustering!$A$10,policy_name_clustering!$C$10,D42=policy_name_clustering!$A$11,policy_name_clustering!$C$11,D42=policy_name_clustering!$A$12,policy_name_clustering!$C$12,D42=policy_name_clustering!$A$13,policy_name_clustering!$C$13,D42=policy_name_clustering!$A$14,policy_name_clustering!$C$14,D42=policy_name_clustering!$A$15,policy_name_clustering!$C$15,D42=policy_name_clustering!$A$16,policy_name_clustering!$C$16,D42="-","",D42=policy_name_clustering!$A$4,policy_name_clustering!$C$4)} | G42: =wind_cump_cap!C44 -> 6 | H42: =estimated_capacity!C42 -> 235.0608 | I42: {=_xlfn.IFS(D42= ""," ",D42<> " ",F42*(G42/H42))} -> 0 | J42: {=_xlfn.IFS(D42= ""," ",D42<> " ",(H42-F42)*(G42/H42))} -> 6 | K42: {=IF(ISNUMBER(H42),_xlfn.IFS(D42= ""," ",D42<> " ",F42*(G42/H42)),"")} -> 0
A43: BEL | B43: 1999 | D43: - | E43: {=_xlfn.IFS(D43=policy_name_clustering!$A$2,policy_name_clustering!$C$2,D43=policy_name_clustering!$A$3,policy_name_clustering!$C$3,D43=policy_name_clustering!$A$5,policy_name_clustering!$C$5,D43=policy_name_clustering!$A$6,policy_name_clustering!$C$6,D43=policy_name_clustering!$A$7,policy_name_clustering!$C$7,D43=policy_name_clustering!$A$8,policy_name_clustering!$C$8,D43=policy_name_clustering!$A$9,policy_name_clustering!$C$9,D43=policy_name_clustering!$A$10,policy_name_clustering!$C$10,D43=policy_name_clustering!$A$11,policy_name_clustering!$C$11,D43=policy_name_clustering!$A$12,policy_name_clustering!$C$12,D43=policy_name_clustering!$A$13,policy_name_clustering!$C$13,D43=policy_name_clustering!$A$14,policy_name_clustering!$C$14,D43=policy_name_clustering!$A$15,policy_name_clustering!$C$15,D43=policy_name_clustering!$A$16,policy_name_clustering!$C$16,D43="-","",D43=policy_name_clustering!$A$4,policy_name_clustering!$C$4)} | G43: =wind_cump_cap!C45 -> 10 | H43: =estimated_capacity!C43 -> 310.70789 | I43: {=_xlfn.IFS(D43= ""," ",D43<> " ",F43*(G43/H43))} -> 0 | J43: {=_xlfn.IFS(D43= ""," ",D43<> " ",(H43-F43)*(G43/H43))} -> 10 | K43: {=IF(ISNUMBER(H43),_xlfn.IFS(D43= ""," ",D43<> " ",F43*(G43/H43)),"")} -> 0
A44: BEL | B44: 2000 | D44: - | E44: {=_xlfn.IFS(D44=policy_name_clustering!$A$2,policy_name_clustering!$C$2,D44=policy_name_clustering!$A$3,policy_name_clustering!$C$3,D44=policy_name_clustering!$A$5,policy_name_clustering!$C$5,D44=policy_name_clustering!$A$6,policy_name_clustering!$C$6,D44=policy_name_clustering!$A$7,policy_name_clustering!$C$7,D44=policy_name_clustering!$A$8,policy_name_clustering!$C$8,D44=policy_name_clustering!$A$9,policy_name_clustering!$C$9,D44=policy_name_clustering!$A$10,policy_name_clustering!$C$10,D44=policy_name_clustering!$A$11,policy_name_clustering!$C$11,D44=policy_name_clustering!$A$12,policy_name_clustering!$C$12,D44=policy_name_clustering!$A$13,policy_name_clustering!$C$13,D44=policy_name_clustering!$A$14,policy_name_clustering!$C$14,D44=policy_name_clustering!$A$15,policy_name_clustering!$C$15,D44=policy_name_clustering!$A$16,policy_name_clustering!$C$16,D44="-","",D44=policy_name_clustering!$A$4,policy_name_clustering!$C$4)} | G44: =wind_cump_cap!C46 -> 14 | H44: =estimated_capacity!C44 -> 388.70055 | I44: {=_xlfn.IFS(D44= ""," ",D44<> " ",F44*(G44/H44))} -> 0 | J44: {=_xlfn.IFS(D44= ""," ",D44<> " ",(H44-F44)*(G44/H44))} -> 14 | K44: {=IF(ISNUMBER(H44),_xlfn.IFS(D44= ""," ",D44<> " ",F44*(G44/H44)),"")} -> 0
A45: BEL | B45: 2001 | D45: - | E45: {=_xlfn.IFS(D45=policy_name_clustering!$A$2,policy_name_clustering!$C$2,D45=policy_name_clustering!$A$3,policy_name_clustering!$C$3,D45=policy_name_clustering!$A$5,policy_name_clustering!$C$5,D45=policy_name_clustering!$A$6,policy_name_clustering!$C$6,D45=policy_name_clustering!$A$7,policy_name_clustering!$C$7,D45=policy_name_clustering!$A$8,policy_name_clustering!$C$8,D45=policy_name_clustering!$A$9,policy_name_clustering!$C$9,D45=policy_name_clustering!$A$10,policy_name_clustering!$C$10,D45=policy_name_clustering!$A$11,policy_name_clustering!$C$11,D45=policy_name_clustering!$A$12,policy_name_clustering!$C$12,D45=policy_name_clustering!$A$13,policy_name_clustering!$C$13,D45=policy_name_clustering!$A$14,policy_name_clustering!$C$14,D45=policy_name_clustering!$A$15,policy_name_clustering!$C$15,D45=policy_name_clustering!$A$16,policy_name_clustering!$C$16,D45="-","",D45=policy_name_clustering!$A$4,policy_name_clustering!$C$4)} | G45: =wind_cump_cap!C47 -> 26 | H45: =estimated_capacity!C45 -> 483.22013 | I45: {=_xlfn.IFS(D45= ""," ",D45<> " ",F45*(G45/H45))} -> 0 | J45: {=_xlfn.IFS(D45= ""," ",D45<> " ",(H45-F45)*(G45/H45))} -> 26 | K45: {=IF(ISNUMBER(H45),_xlfn.IFS(D45= ""," ",D45<> " ",F45*(G45/H45)),"")} -> 0
A46: BEL | B46: 2002 | D46: - | E46: {=_xlfn.IFS(D46=policy_name_clustering!$A$2,policy_name_clustering!$C$2,D46=policy_name_clustering!$A$3,policy_name_clustering!$C$3,D46=policy_name_clustering!$A$5,policy_name_clustering!$C$5,D46=policy_name_clustering!$A$6,policy_name_clustering!$C$6,D46=policy_name_clustering!$A$7,policy_name_clustering!$C$7,D46=policy_name_clustering!$A$8,policy_name_clustering!$C$8,D46=policy_name_clustering!$A$9,policy_name_clustering!$C$9,D46=policy_name_clustering!$A$10,policy_name_clustering!$C$10,D46=policy_name_clustering!$A$11,policy_name_clustering!$C$11,D46=policy_name_clustering!$A$12,policy_name_clustering!$C$12,D46=policy_name_clustering!$A$13,policy_name_clustering!$C$13,D46=policy_name_clustering!$A$14,policy_name_clustering!$C$14,D46=policy_name_clustering!$A$15,policy_name_clustering!$C$15,D46=policy_name_clustering!$A$16,policy_name_clustering!$C$16,D46="-","",D46=policy_name_clustering!$A$4,policy_name_clustering!$C$4)} | G46: =wind_cump_cap!C48 -> 31 | H46: =estimated_capacity!C46 -> 580.25811 | I46: {=_xlfn.IFS(D46= ""," ",D46<> " ",F46*(G46/H46))} -> 0 | J46: {=_xlfn.IFS(D46= ""," ",D46<> " ",(H46-F46)*(G46/H46))} -> 31 | K46: {=IF(ISNUMBER(H46),_xlfn.IFS(D46= ""," ",D46<> " ",F46*(G46/H46)),"")} -> 0
... A66: BEL | B66: 2022 | D66: - | E66: {=_xlfn.IFS(D66=policy_name_clustering!$A$2,policy_name_clustering!$C$2,D66=policy_name_clustering!$A$3,policy_name_clustering!$C$3,D66=policy_name_clustering!$A$5,policy_name_clustering!$C$5,D66=policy_name_clustering!$A$6,policy_name_clustering!$C$6,D66=policy_name_clustering!$A$7,policy_name_clustering!$C$7,D66=policy_name_clustering!$A$8,policy_name_clustering!$C$8,D66=policy_name_clustering!$A$9,policy_name_clustering!$C$9,D66=policy_name_clustering!$A$10,policy_name_clustering!$C$10,D66=policy_name_clustering!$A$11,policy_name_clustering!$C$11,D66=policy_name_clustering!$A$12,policy_name_clustering!$C$12,D66=policy_name_clustering!$A$13,policy_name_clustering!$C$13,D66=policy_name_clustering!$A$14,policy_name_clustering!$C$14,D66=policy_name_clustering!$A$15,policy_name_clustering!$C$15,D66=policy_name_clustering!$A$16,policy_name_clustering!$C$16,D66="-","",D66=policy_name_clustering!$A$4,policy_name_clustering!$C$4)} | G66: =wind_cump_cap!C68 -> 5303.4 | H66: =estimated_capacity!C66 -> 4287.8509 | I66: {=_xlfn.IFS(D66= ""," ",D66<> " ",F66*(G66/H66))} -> 0 | J66: {=_xlfn.IFS(D66= ""," ",D66<> " ",(H66-F66)*(G66/H66))} -> 5303.4 | K66: {=IF(ISNUMBER(H66),_xlfn.IFS(D66= ""," ",D66<> " ",F66*(G66/H66)),"")} -> 0
A67: BEL | B67: 2023 | D67: - | E67: {=_xlfn.IFS(D67=policy_name_clustering!$A$2,policy_name_clustering!$C$2,D67=policy_name_clustering!$A$3,policy_name_clustering!$C$3,D67=policy_name_clustering!$A$5,policy_name_clustering!$C$5,D67=policy_name_clustering!$A$6,policy_name_clustering!$C$6,D67=policy_name_clustering!$A$7,policy_name_clustering!$C$7,D67=policy_name_clustering!$A$8,policy_name_clustering!$C$8,D67=policy_name_clustering!$A$9,policy_name_clustering!$C$9,D67=policy_name_clustering!$A$10,policy_name_clustering!$C$10,D67=policy_name_clustering!$A$11,policy_name_clustering!$C$11,D67=policy_name_clustering!$A$12,policy_name_clustering!$C$12,D67=policy_name_clustering!$A$13,policy_name_clustering!$C$13,D67=policy_name_clustering!$A$14,policy_name_clustering!$C$14,D67=policy_name_clustering!$A$15,policy_name_clustering!$C$15,D67=policy_name_clustering!$A$16,policy_name_clustering!$C$16,D67="-","",D67=policy_name_clustering!$A$4,policy_name_clustering!$C$4)} | G67: =wind_cump_cap!C69 -> 5454.1 | H67: =estimated_capacity!C67 -> 4690.244 | I67: {=_xlfn.IFS(D67= ""," ",D67<> " ",F67*(G67/H67))} -> 0 | J67: {=_xlfn.IFS(D67= ""," ",D67<> " ",(H67-F67)*(G67/H67))} -> 5454.1 | K67: {=IF(ISNUMBER(H67),_xlfn.IFS(D67= ""," ",D67<> " ",F67*(G67/H67)),"")} -> 0 | N67: =SUM(G34,G67,G105,G138,G184,G217,G255,G346,G315,G379,G420,G442,G475,G503,G536,G589)-SUM(H589,H536,H503,H475,H442,H420,H379,H346,H315,H255,H217,H184,H138,H105,H67,H34) -> 1191.1217
A68: DEU | B68: 1991 | D68: - | E68: {=_xlfn.IFS(D68=policy_name_clustering!$A$2,policy_name_clustering!$C$2,D68=policy_name_clustering!$A$3,policy_name_clustering!$C$3,D68=policy_name_clustering!$A$5,policy_name_clustering!$C$5,D68=policy_name_clustering!$A$6,policy_name_clustering!$C$6,D68=policy_name_clustering!$A$7,policy_name_clustering!$C$7,D68=policy_name_clustering!$A$8,policy_name_clustering!$C$8,D68=policy_name_clustering!$A$9,policy_name_clustering!$C$9,D68=policy_name_clustering!$A$10,policy_name_clustering!$C$10,D68=policy_name_clustering!$A$11,policy_name_clustering!$C$11,D68=policy_name_clustering!$A$12,policy_name_clustering!$C$12,D68=policy_name_clustering!$A$13,policy_name_clustering!$C$13,D68=policy_name_clustering!$A$14,policy_name_clustering!$C$14,D68=policy_name_clustering!$A$15,policy_name_clustering!$C$15,D68=policy_name_clustering!$A$16,policy_name_clustering!$C$16,D68="-","",D68=policy_name_clustering!$A$4,policy_name_clustering!$C$4)} | G68: =wind_cump_cap!C71 -> 110 | H68: =estimated_capacity!C68 -> 88.425538 | I68: {=_xlfn.IFS(D68= ""," ",D68<> " ",F68*(G68/H68))} -> 0 | J68: {=_xlfn.IFS(D68= ""," ",D68<> " ",(H68-F68)*(G68/H68))} -> 110 | K68: {=IF(ISNUMBER(H68),_xlfn.IFS(D68= ""," ",D68<> " ",F68*(G68/H68)),"")} -> 0
A69: DEU | B69: 1992 | D69: - | E69: {=_xlfn.IFS(D69=policy_name_clustering!$A$2,policy_name_clustering!$C$2,D69=policy_name_clustering!$A$3,policy_name_clustering!$C$3,D69=policy_name_clustering!$A$5,policy_name_clustering!$C$5,D69=policy_name_clustering!$A$6,policy_name_clustering!$C$6,D69=policy_name_clustering!$A$7,policy_name_clustering!$C$7,D69=policy_name_clustering!$A$8,policy_name_clustering!$C$8,D69=policy_name_clustering!$A$9,policy_name_clustering!$C$9,D69=policy_name_clustering!$A$10,policy_name_clustering!$C$10,D69=policy_name_clustering!$A$11,policy_name_clustering!$C$11,D69=policy_name_clustering!$A$12,policy_name_clustering!$C$12,D69=policy_name_clustering!$A$13,policy_name_clustering!$C$13,D69=policy_name_clustering!$A$14,policy_name_clustering!$C$14,D69=policy_name_clustering!$A$15,policy_name_clustering!$C$15,D69=policy_name_clustering!$A$16,policy_name_clustering!$C$16,D69="-","",D69=policy_name_clustering!$A$4,policy_name_clustering!$C$4)} | G69: =wind_cump_cap!C72 -> 183 | H69: =estimated_capacity!C69 -> 182.77566 | I69: {=_xlfn.IFS(D69= ""," ",D69<> " ",F69*(G69/H69))} -> 0 | J69: {=_xlfn.IFS(D69= ""," ",D69<> " ",(H69-F69)*(G69/H69))} -> 183 | K69: {=IF(ISNUMBER(H69),_xlfn.IFS(D69= ""," ",D69<> " ",F69*(G69/H69)),"")} -> 0
A70: DEU | B70: 1993 | C70: FiT intro -1991 | D70: FiT | E70: {=_xlfn.IFS(D70=policy_name_clustering!$A$2,policy_name_clustering!$C$2,D70=policy_name_clustering!$A$3,policy_name_clustering!$C$3,D70=policy_name_clustering!$A$5,policy_name_clustering!$C$5,D70=policy_name_clustering!$A$6,policy_name_clustering!$C$6,D70=policy_name_clustering!$A$7,policy_name_clustering!$C$7,D70=policy_name_clustering!$A$8,policy_name_clustering!$C$8,D70=policy_name_clustering!$A$9,policy_name_clustering!$C$9,D70=policy_name_clustering!$A$10,policy_name_clustering!$C$10,D70=policy_name_clustering!$A$11,policy_name_clustering!$C$11,D70=policy_name_clustering!$A$12,policy_name_clustering!$C$12,D70=policy_name_clustering!$A$13,policy_name_clustering!$C$13,D70=policy_name_clustering!$A$14,policy_name_clustering!$C$14,D70=policy_name_clustering!$A$15,policy_name_clustering!$C$15,D70=policy_name_clustering!$A$16,policy_name_clustering!$C$16,D70="-","",D70=policy_name_clustering!$A$4,policy_name_clustering!$C$4)} -> FiT/FiP-based | F70: =policy_contributions_cum!F2 -> 51.921175 | G70: =wind_cump_cap!C73 -> 334 | H70: =estimated_capacity!C70 -> 343.94999 | I70: {=_xlfn.IFS(D70= ""," ",D70<> " ",F70*(G70/H70))} -> 50.419168 | J70: {=_xlfn.IFS(D70= ""," ",D70<> " ",(H70-F70)*(G70/H70))} -> 283.58083 | K70: {=IF(ISNUMBER(H70),_xlfn.IFS(D70= ""," ",D70<> " ",F70*(G70/H70)),"")} -> 50.419168
A71: DEU | B71: 1994 | C71: FiT intro -1991 | D71: FiT | E71: {=_xlfn.IFS(D71=policy_name_clustering!$A$2,policy_name_clustering!$C$2,D71=policy_name_clustering!$A$3,policy_name_clustering!$C$3,D71=policy_name_clustering!$A$5,policy_name_clustering!$C$5,D71=policy_name_clustering!$A$6,policy_name_clustering!$C$6,D71=policy_name_clustering!$A$7,policy_name_clustering!$C$7,D71=policy_name_clustering!$A$8,policy_name_clustering!$C$8,D71=policy_name_clustering!$A$9,policy_name_clustering!$C$9,D71=policy_name_clustering!$A$10,policy_name_clustering!$C$10,D71=policy_name_clustering!$A$11,policy_name_clustering!$C$11,D71=policy_name_clustering!$A$12,policy_name_clustering!$C$12,D71=policy_name_clustering!$A$13,policy_name_clustering!$C$13,D71=policy_name_clustering!$A$14,policy_name_clustering!$C$14,D71=policy_name_clustering!$A$15,policy_name_clustering!$C$15,D71=policy_name_clustering!$A$16,policy_name_clustering!$C$16,D71="-","",D71=policy_name_clustering!$A$4,policy_name_clustering!$C$4)} -> FiT/FiP-based | F71: =policy_contributions_cum!F3 -> 172.94021 | G71: =wind_cump_cap!C74 -> 643 | H71: =estimated_capacity!C71 -> 582.1443 | I71: {=_xlfn.IFS(D71= ""," ",D71<> " ",F71*(G71/H71))} -> 191.01889 | J71: {=_xlfn.IFS(D71= ""," ",D71<> " ",(H71-F71)*(G71/H71))} -> 451.98111 | K71: {=IF(ISNUMBER(H71),_xlfn.IFS(D71= ""," ",D71<> " ",F71*(G71/H71)),"")} -> 191.01889
A72: DEU | B72: 1995 | C72: FiT intro -1991 | D72: FiT | E72: {=_xlfn.IFS(D72=policy_name_clustering!$A$2,policy_name_clustering!$C$2,D72=policy_name_clustering!$A$3,policy_name_clustering!$C$3,D72=policy_name_clustering!$A$5,policy_name_clustering!$C$5,D72=policy_name_clustering!$A$6,policy_name_clustering!$C$6,D72=policy_name_clustering!$A$7,policy_name_clustering!$C$7,D72=policy_name_clustering!$A$8,policy_name_clustering!$C$8,D72=policy_name_clustering!$A$9,policy_name_clustering!$C$9,D72=policy_name_clustering!$A$10,policy_name_clustering!$C$10,D72=policy_name_clustering!$A$11,policy_name_clustering!$C$11,D72=policy_name_clustering!$A$12,policy_name_clustering!$C$12,D72=policy_name_clustering!$A$13,policy_name_clustering!$C$13,D72=policy_name_clustering!$A$14,policy_name_clustering!$C$14,D72=policy_name_clustering!$A$15,policy_name_clustering!$C$15,D72=policy_name_clustering!$A$16,policy_name_clustering!$C$16,D72="-","",D72=policy_name_clustering!$A$4,policy_name_clustering!$C$4)} -> FiT/FiP-based | F72: =policy_contributions_cum!F4 -> 401.54788 | G72: =wind_cump_cap!C75 -> 1137 | H72: =estimated_capacity!C72 -> 953.45563 | I72: {=_xlfn.IFS(D72= ""," ",D72<> " ",F72*(G72/H72))} -> 478.84761 | J72: {=_xlfn.IFS(D72= ""," ",D72<> " ",(H72-F72)*(G72/H72))} -> 658.15239 | K72: {=IF(ISNUMBER(H72),_xlfn.IFS(D72= ""," ",D72<> " ",F72*(G72/H72)),"")} -> 478.84761
A73: DEU | B73: 1996 | C73: FiT intro -1991 | D73: FiT | E73: {=_xlfn.IFS(D73=policy_name_clustering!$A$2,policy_name_clustering!$C$2,D73=policy_name_clustering!$A$3,policy_name_clustering!$C$3,D73=policy_name_clustering!$A$5,policy_name_clustering!$C$5,D73=policy_name_clustering!$A$6,policy_name_clustering!$C$6,D73=policy_name_clustering!$A$7,policy_name_clustering!$C$7,D73=policy_name_clustering!$A$8,policy_name_clustering!$C$8,D73=policy_name_clustering!$A$9,policy_name_clustering!$C$9,D73=policy_name_clustering!$A$10,policy_name_clustering!$C$10,D73=policy_name_clustering!$A$11,policy_name_clustering!$C$11,D73=policy_name_clustering!$A$12,policy_name_clustering!$C$12,D73=policy_name_clustering!$A$13,policy_name_clustering!$C$13,D73=policy_name_clustering!$A$14,policy_name_clustering!$C$14,D73=policy_name_clustering!$A$15,policy_name_clustering!$C$15,D73=policy_name_clustering!$A$16,policy_name_clustering!$C$16,D73="-","",D73=policy_name_clustering!$A$4,policy_name_clustering!$C$4)} -> FiT/FiP-based | F73: =policy_contributions_cum!F5 -> 772.96717 | G73: =wind_cump_cap!C76 -> 1564 | H73: =estimated_capacity!C73 -> 1486.2066 | I73: {=_xlfn.IFS(D73= ""," ",D73<> " ",F73*(G73/H73))} -> 813.42707 | J73: {=_xlfn.IFS(D73= ""," ",D73<> " ",(H73-F73)*(G73/H73))} -> 750.57293 | K73: {=IF(ISNUMBER(H73),_xlfn.IFS(D73= ""," ",D73<> " ",F73*(G73/H73)),"")} -> 813.42707
A74: DEU | B74: 1997 | C74: FiT intro -1991 | D74: FiT | E74: {=_xlfn.IFS(D74=policy_name_clustering!$A$2,policy_name_clustering!$C$2,D74=policy_name_clustering!$A$3,policy_name_clustering!$C$3,D74=policy_name_clustering!$A$5,policy_name_clustering!$C$5,D74=policy_name_clustering!$A$6,policy_name_clustering!$C$6,D74=policy_name_clustering!$A$7,policy_name_clustering!$C$7,D74=policy_name_clustering!$A$8,policy_name_clustering!$C$8,D74=policy_name_clustering!$A$9,policy_name_clustering!$C$9,D74=policy_name_clustering!$A$10,policy_name_clustering!$C$10,D74=policy_name_clustering!$A$11,policy_name_clustering!$C$11,D74=policy_name_clustering!$A$12,policy_name_clustering!$C$12,D74=policy_name_clustering!$A$13,policy_name_clustering!$C$13,D74=policy_name_clustering!$A$14,policy_name_clustering!$C$14,D74=policy_name_clustering!$A$15,policy_name_clustering!$C$15,D74=policy_name_clustering!$A$16,policy_name_clustering!$C$16,D74="-","",D74=policy_name_clustering!$A$4,policy_name_clustering!$C$4)} -> FiT/FiP-based | F74: =policy_contributions_cum!F6 -> 1352.5843 | G74: =wind_cump_cap!C77 -> 1966 | H74: =estimated_capacity!C74 -> 2253.023 | I74: {=_xlfn.IFS(D74= ""," ",D74<> " ",F74*(G74/H74))} -> 1180.2723 | J74: {=_xlfn.IFS(D74= ""," ",D74<> " ",(H74-F74)*(G74/H74))} -> 785.7277 | K74: {=IF(ISNUMBER(H74),_xlfn.IFS(D74= ""," ",D74<> " ",F74*(G74/H74)),"")} -> 1180.2723
A75: DEU | B75: 1998 | C75: FiT intro -1991 | D75: FiT | E75: {=_xlfn.IFS(D75=policy_name_clustering!$A$2,policy_name_clustering!$C$2,D75=policy_name_clustering!$A$3,policy_name_clustering!$C$3,D75=policy_name_clustering!$A$5,policy_name_clustering!$C$5,D75=policy_name_clustering!$A$6,policy_name_clustering!$C$6,D75=policy_name_clustering!$A$7,policy_name_clustering!$C$7,D75=policy_name_clustering!$A$8,policy_name_clustering!$C$8,D75=policy_name_clustering!$A$9,policy_name_clustering!$C$9,D75=policy_name_clustering!$A$10,policy_name_clustering!$C$10,D75=policy_name_clustering!$A$11,policy_name_clustering!$C$11,D75=policy_name_clustering!$A$12,policy_name_clustering!$C$12,D75=policy_name_clustering!$A$13,policy_name_clustering!$C$13,D75=policy_name_clustering!$A$14,policy_name_clustering!$C$14,D75=policy_name_clustering!$A$15,policy_name_clustering!$C$15,D75=policy_name_clustering!$A$16,policy_name_clustering!$C$16,D75="-","",D75=policy_name_clustering!$A$4,policy_name_clustering!$C$4)} -> FiT/FiP-based | F75: =policy_contributions_cum!F7 -> 2165.6656 | G75: =wind_cump_cap!C78 -> 2672 | H75: =estimated_capacity!C75 -> 3260.4103 | I75: {=_xlfn.IFS(D75= ""," ",D75<> " ",F75*(G75/H75))} -> 1774.8252 | J75: {=_xlfn.IFS(D75= ""," ",D75<> " ",(H75-F75)*(G75/H75))} -> 897.1748 | K75: {=IF(ISNUMBER(H75),_xlfn.IFS(D75= ""," ",D75<> " ",F75*(G75/H75)),"")} -> 1774.8252
A76: DEU | B76: 1999 | C76: FiT intro -1991 | D76: FiT | E76: {=_xlfn.IFS(D76=policy_name_clustering!$A$2,policy_name_clustering!$C$2,D76=policy_name_clustering!$A$3,policy_name_clustering!$C$3,D76=policy_name_clustering!$A$5,policy_name_clustering!$C$5,D76=policy_name_clustering!$A$6,policy_name_clustering!$C$6,D76=policy_name_clustering!$A$7,policy_name_clustering!$C$7,D76=policy_name_clustering!$A$8,policy_name_clustering!$C$8,D76=policy_name_clustering!$A$9,policy_name_clustering!$C$9,D76=policy_name_clustering!$A$10,policy_name_clustering!$C$10,D76=policy_name_clustering!$A$11,policy_name_clustering!$C$11,D76=policy_name_clustering!$A$12,policy_name_clustering!$C$12,D76=policy_name_clustering!$A$13,policy_name_clustering!$C$13,D76=policy_name_clustering!$A$14,policy_name_clustering!$C$14,D76=policy_name_clustering!$A$15,policy_name_clustering!$C$15,D76=policy_name_clustering!$A$16,policy_name_clustering!$C$16,D76="-","",D76=policy_name_clustering!$A$4,policy_name_clustering!$C$4)} -> FiT/FiP-based | F76: =policy_contributions_cum!F8 -> 3347.1257 | G76: =wind_cump_cap!C79 -> 4138 | H76: =estimated_capacity!C76 -> 4662.0933 | I76: {=_xlfn.IFS(D76= ""," ",D76<> " ",F76*(G76/H76))} -> 2970.8556 | J76: {=_xlfn.IFS(D76= ""," ",D76<> " ",(H76-F76)*(G76/H76))} -> 1167.1444 | K76: {=IF(ISNUMBER(H76),_xlfn.IFS(D76= ""," ",D76<> " ",F76*(G76/H76)),"")} -> 2970.8556
A77: DEU | B77: 2000 | C77: FiT intro -1991 | D77: FiT | E77: {=_xlfn.IFS(D77=policy_name_clustering!$A$2,policy_name_clustering!$C$2,D77=policy_name_clustering!$A$3,policy_name_clustering!$C$3,D77=policy_name_clustering!$A$5,policy_name_clustering!$C$5,D77=policy_name_clustering!$A$6,policy_name_clustering!$C$6,D77=policy_name_clustering!$A$7,policy_name_clustering!$C$7,D77=policy_name_clustering!$A$8,policy_name_clustering!$C$8,D77=policy_name_clustering!$A$9,policy_name_clustering!$C$9,D77=policy_name_clustering!$A$10,policy_name_clustering!$C$10,D77=policy_name_clustering!$A$11,policy_name_clustering!$C$11,D77=policy_name_clustering!$A$12,policy_name_clustering!$C$12,D77=policy_name_clustering!$A$13,policy_name_clustering!$C$13,D77=policy_name_clustering!$A$14,policy_name_clustering!$C$14,D77=policy_name_clustering!$A$15,policy_name_clustering!$C$15,D77=policy_name_clustering!$A$16,policy_name_clustering!$C$16,D77="-","",D77=policy_name_clustering!$A$4,policy_name_clustering!$C$4)} -> FiT/FiP-based | F77: =policy_contributions_cum!F9 -> 4917.8922 | G77: =wind_cump_cap!C80 -> 6095 | H77: =estimated_capacity!C77 -> 6457.0135 | I77: {=_xlfn.IFS(D77= ""," ",D77<> " ",F77*(G77/H77))} -> 4642.1697 | J77: {=_xlfn.IFS(D77= ""," ",D77<> " ",(H77-F77)*(G77/H77))} -> 1452.8303 | K77: {=IF(ISNUMBER(H77),_xlfn.IFS(D77= ""," ",D77<> " ",F77*(G77/H77)),"")} -> 4642.1697
A78: DEU | B78: 2001 | C78: FiT intro -1991 | D78: FiT | E78: {=_xlfn.IFS(D78=policy_name_clustering!$A$2,policy_name_clustering!$C$2,D78=policy_name_clustering!$A$3,policy_name_clustering!$C$3,D78=policy_name_clustering!$A$5,policy_name_clustering!$C$5,D78=policy_name_clustering!$A$6,policy_name_clustering!$C$6,D78=policy_name_clustering!$A$7,policy_name_clustering!$C$7,D78=policy_name_clustering!$A$8,policy_name_clustering!$C$8,D78=policy_name_clustering!$A$9,policy_name_clustering!$C$9,D78=policy_name_clustering!$A$10,policy_name_clustering!$C$10,D78=policy_name_clustering!$A$11,policy_name_clustering!$C$11,D78=policy_name_clustering!$A$12,policy_name_clustering!$C$12,D78=policy_name_clustering!$A$13,policy_name_clustering!$C$13,D78=policy_name_clustering!$A$14,policy_name_clustering!$C$14,D78=policy_name_clustering!$A$15,policy_name_clustering!$C$15,D78=policy_name_clustering!$A$16,policy_name_clustering!$C$16,D78="-","",D78=policy_name_clustering!$A$4,policy_name_clustering!$C$4)} -> FiT/FiP-based | F78: =policy_contributions_cum!F10 -> 7144.8939 | G78: =wind_cump_cap!C81 -> 8754 | H78: =estimated_capacity!C78 -> 8938.369 | I78: {=_xlfn.IFS(D78= ""," ",D78<> " ",F78*(G78/H78))} -> 6997.5183 | J78: {=_xlfn.IFS(D78= ""," ",D78<> " ",(H78-F78)*(G78/H78))} -> 1756.4817 | K78: {=IF(ISNUMBER(H78),_xlfn.IFS(D78= ""," ",D78<> " ",F78*(G78/H78)),"")} -> 6997.5183
A79: DEU | B79: 2002 | C79: negative break here: FiT degression intro - 2000 | D79: FiT | E79: {=_xlfn.IFS(D79=policy_name_clustering!$A$2,policy_name_clustering!$C$2,D79=policy_name_clustering!$A$3,policy_name_clustering!$C$3,D79=policy_name_clustering!$A$5,policy_name_clustering!$C$5,D79=policy_name_clustering!$A$6,policy_name_clustering!$C$6,D79=policy_name_clustering!$A$7,policy_name_clustering!$C$7,D79=policy_name_clustering!$A$8,policy_name_clustering!$C$8,D79=policy_name_clustering!$A$9,policy_name_clustering!$C$9,D79=policy_name_clustering!$A$10,policy_name_clustering!$C$10,D79=policy_name_clustering!$A$11,policy_name_clustering!$C$11,D79=policy_name_clustering!$A$12,policy_name_clustering!$C$12,D79=policy_name_clustering!$A$13,policy_name_clustering!$C$13,D79=policy_name_clustering!$A$14,policy_name_clustering!$C$14,D79=policy_name_clustering!$A$15,policy_name_clustering!$C$15,D79=policy_name_clustering!$A$16,policy_name_clustering!$C$16,D79="-","",D79=policy_name_clustering!$A$4,policy_name_clustering!$C$4)} -> FiT/FiP-based | F79: =policy_contributions_cum!F11 -> 9401.1321 | G79: =wind_cump_cap!C82 -> 12001 | H79: =estimated_capacity!C79 -> 11373.513 | I79: {=_xlfn.IFS(D79= ""," ",D79<> " ",F79*(G79/H79))} -> 9919.8015 | J79: {=_xlfn.IFS(D79= ""," ",D79<> " ",(H79-F79)*(G79/H79))} -> 2081.1985 | K79: {=IF(ISNUMBER(H79),_xlfn.IFS(D79= ""," ",D79<> " ",F79*(G79/H79)),"")} -> 9919.8015
A80: DEU | B80: 2003 | D80: FiT | E80: {=_xlfn.IFS(D80=policy_name_clustering!$A$2,policy_name_clustering!$C$2,D80=policy_name_clustering!$A$3,policy_name_clustering!$C$3,D80=policy_name_clustering!$A$5,policy_name_clustering!$C$5,D80=policy_name_clustering!$A$6,policy_name_clustering!$C$6,D80=policy_name_clustering!$A$7,policy_name_clustering!$C$7,D80=policy_name_clustering!$A$8,policy_name_clustering!$C$8,D80=policy_name_clustering!$A$9,policy_name_clustering!$C$9,D80=policy_name_clustering!$A$10,policy_name_clustering!$C$10,D80=policy_name_clustering!$A$11,policy_name_clustering!$C$11,D80=policy_name_clustering!$A$12,policy_name_clustering!$C$12,D80=policy_name_clustering!$A$13,policy_name_clustering!$C$13,D80=policy_name_clustering!$A$14,policy_name_clustering!$C$14,D80=policy_name_clustering!$A$15,policy_name_clustering!$C$15,D80=policy_name_clustering!$A$16,policy_name_clustering!$C$16,D80="-","",D80=policy_name_clustering!$A$4,policy_name_clustering!$C$4)} -> FiT/FiP-based | F80: =policy_contributions_cum!F12 -> 11859.247 | G80: =wind_cump_cap!C83 -> 14381 | H80: =estimated_capacity!C80 -> 13969.359 | I80: {=_xlfn.IFS(D80= ""," ",D80<> " ",F80*(G80/H80))} -> 12208.709 | J80: {=_xlfn.IFS(D80= ""," ",D80<> " ",(H80-F80)*(G80/H80))} -> 2172.2913 | K80: {=IF(ISNUMBER(H80),_xlfn.IFS(D80= ""," ",D80<> " ",F80*(G80/H80)),"")} -> 12208.709
A81: DEU | B81: 2004 | D81: FiT | E81: {=_xlfn.IFS(D81=policy_name_clustering!$A$2,policy_name_clustering!$C$2,D81=policy_name_clustering!$A$3,policy_name_clustering!$C$3,D81=policy_name_clustering!$A$5,policy_name_clustering!$C$5,D81=policy_name_clustering!$A$6,policy_name_clustering!$C$6,D81=policy_name_clustering!$A$7,policy_name_clustering!$C$7,D81=policy_name_clustering!$A$8,policy_name_clustering!$C$8,D81=policy_name_clustering!$A$9,policy_name_clustering!$C$9,D81=policy_name_clustering!$A$10,policy_name_clustering!$C$10,D81=policy_name_clustering!$A$11,policy_name_clustering!$C$11,D81=policy_name_clustering!$A$12,policy_name_clustering!$C$12,D81=policy_name_clustering!$A$13,policy_name_clustering!$C$13,D81=policy_name_clustering!$A$14,policy_name_clustering!$C$14,D81=policy_name_clustering!$A$15,policy_name_clustering!$C$15,D81=policy_name_clustering!$A$16,policy_name_clustering!$C$16,D81="-","",D81=policy_name_clustering!$A$4,policy_name_clustering!$C$4)} -> FiT/FiP-based | F81: =policy_contributions_cum!F13 -> 14265.98 | G81: =wind_cump_cap!C84 -> 16419 | H81: =estimated_capacity!C81 -> 16458.978 | I81: {=_xlfn.IFS(D81= ""," ",D81<> " ",F81*(G81/H81))} -> 14231.329 | J81: {=_xlfn.IFS(D81= ""," ",D81<> " ",(H81-F81)*(G81/H81))} -> 2187.6707 | K81: {=IF(ISNUMBER(H81),_xlfn.IFS(D81= ""," ",D81<> " ",F81*(G81/H81)),"")} -> 14231.329
A82: DEU | B82: 2005 | D82: FiT | E82: {=_xlfn.IFS(D82=policy_name_clustering!$A$2,policy_name_clustering!$C$2,D82=policy_name_clustering!$A$3,policy_name_clustering!$C$3,D82=policy_name_clustering!$A$5,policy_name_clustering!$C$5,D82=policy_name_clustering!$A$6,policy_name_clustering!$C$6,D82=policy_name_clustering!$A$7,policy_name_clustering!$C$7,D82=policy_name_clustering!$A$8,policy_name_clustering!$C$8,D82=policy_name_clustering!$A$9,policy_name_clustering!$C$9,D82=policy_name_clustering!$A$10,policy_name_clustering!$C$10,D82=policy_name_clustering!$A$11,policy_name_clustering!$C$11,D82=policy_name_clustering!$A$12,policy_name_clustering!$C$12,D82=policy_name_clustering!$A$13,policy_name_clustering!$C$13,D82=policy_name_clustering!$A$14,policy_name_clustering!$C$14,D82=policy_name_clustering!$A$15,policy_name_clustering!$C$15,D82=policy_name_clustering!$A$16,policy_name_clustering!$C$16,D82="-","",D82=policy_name_clustering!$A$4,policy_name_clustering!$C$4)} -> FiT/FiP-based | F82: =policy_contributions_cum!F14 -> 16865.323 | G82: =wind_cump_cap!C85 -> 18248 | H82: =estimated_capacity!C82 -> 19114.216 | I82: {=_xlfn.IFS(D82= ""," ",D82<> " ",F82*(G82/H82))} -> 16101.022 | J82: {=_xlfn.IFS(D82= ""," ",D82<> " ",(H82-F82)*(G82/H82))} -> 2146.9776 | K82: {=IF(ISNUMBER(H82),_xlfn.IFS(D82= ""," ",D82<> " ",F82*(G82/H82)),"")} -> 16101.022
A83: DEU | B83: 2006 | D83: FiT | E83: {=_xlfn.IFS(D83=policy_name_clustering!$A$2,policy_name_clustering!$C$2,D83=policy_name_clustering!$A$3,policy_name_clustering!$C$3,D83=policy_name_clustering!$A$5,policy_name_clustering!$C$5,D83=policy_name_clustering!$A$6,policy_name_clustering!$C$6,D83=policy_name_clustering!$A$7,policy_name_clustering!$C$7,D83=policy_name_clustering!$A$8,policy_name_clustering!$C$8,D83=policy_name_clustering!$A$9,policy_name_clustering!$C$9,D83=policy_name_clustering!$A$10,policy_name_clustering!$C$10,D83=policy_name_clustering!$A$11,policy_name_clustering!$C$11,D83=policy_name_clustering!$A$12,policy_name_clustering!$C$12,D83=policy_name_clustering!$A$13,policy_name_clustering!$C$13,D83=policy_name_clustering!$A$14,policy_name_clustering!$C$14,D83=policy_name_clustering!$A$15,policy_name_clustering!$C$15,D83=policy_name_clustering!$A$16,policy_name_clustering!$C$16,D83="-","",D83=policy_name_clustering!$A$4,policy_name_clustering!$C$4)} -> FiT/FiP-based | F83: =policy_contributions_cum!F15 -> 19323.984 | G83: =wind_cump_cap!C86 -> 20474 | H83: =estimated_capacity!C83 -> 21589.415 | I83: {=_xlfn.IFS(D83= ""," ",D83<> " ",F83*(G83/H83))} -> 18325.612 | J83: {=_xlfn.IFS(D83= ""," ",D83<> " ",(H83-F83)*(G83/H83))} -> 2148.3878 | K83: {=IF(ISNUMBER(H83),_xlfn.IFS(D83= ""," ",D83<> " ",F83*(G83/H83)),"")} -> 18325.612
A84: DEU | B84: 2007 | D84: FiT | E84: {=_xlfn.IFS(D84=policy_name_clustering!$A$2,policy_name_clustering!$C$2,D84=policy_name_clustering!$A$3,policy_name_clustering!$C$3,D84=policy_name_clustering!$A$5,policy_name_clustering!$C$5,D84=policy_name_clustering!$A$6,policy_name_clustering!$C$6,D84=policy_name_clustering!$A$7,policy_name_clustering!$C$7,D84=policy_name_clustering!$A$8,policy_name_clustering!$C$8,D84=policy_name_clustering!$A$9,policy_name_clustering!$C$9,D84=policy_name_clustering!$A$10,policy_name_clustering!$C$10,D84=policy_name_clustering!$A$11,policy_name_clustering!$C$11,D84=policy_name_clustering!$A$12,policy_name_clustering!$C$12,D84=policy_name_clustering!$A$13,policy_name_clustering!$C$13,D84=policy_name_clustering!$A$14,policy_name_clustering!$C$14,D84=policy_name_clustering!$A$15,policy_name_clustering!$C$15,D84=policy_name_clustering!$A$16,policy_name_clustering!$C$16,D84="-","",D84=policy_name_clustering!$A$4,policy_name_clustering!$C$4)} -> FiT/FiP-based | F84: =policy_contributions_cum!F16 -> 21690.393 | G84: =wind_cump_cap!C87 -> 22116 | H84: =estimated_capacity!C84 -> 23944.623 | I84: {=_xlfn.IFS(D84= ""," ",D84<> " ",F84*(G84/H84))} -> 20033.923 | J84: {=_xlfn.IFS(D84= ""," ",D84<> " ",(H84-F84)*(G84/H84))} -> 2082.0765 | K84: {=IF(ISNUMBER(H84),_xlfn.IFS(D84= ""," ",D84<> " ",F84*(G84/H84)),"")} -> 20033.923
A85: DEU | B85: 2008 | D85: FiT | E85: {=_xlfn.IFS(D85=policy_name_clustering!$A$2,policy_name_clustering!$C$2,D85=policy_name_clustering!$A$3,policy_name_clustering!$C$3,D85=policy_name_clustering!$A$5,policy_name_clustering!$C$5,D85=policy_name_clustering!$A$6,policy_name_clustering!$C$6,D85=policy_name_clustering!$A$7,policy_name_clustering!$C$7,D85=policy_name_clustering!$A$8,policy_name_clustering!$C$8,D85=policy_name_clustering!$A$9,policy_name_clustering!$C$9,D85=policy_name_clustering!$A$10,policy_name_clustering!$C$10,D85=policy_name_clustering!$A$11,policy_name_clustering!$C$11,D85=policy_name_clustering!$A$12,policy_name_clustering!$C$12,D85=policy_name_clustering!$A$13,policy_name_clustering!$C$13,D85=policy_name_clustering!$A$14,policy_name_clustering!$C$14,D85=policy_name_clustering!$A$15,policy_name_clustering!$C$15,D85=policy_name_clustering!$A$16,policy_name_clustering!$C$16,D85="-","",D85=policy_name_clustering!$A$4,policy_name_clustering!$C$4)} -> FiT/FiP-based | F85: =policy_contributions_cum!F17 -> 23876.905 | G85: =wind_cump_cap!C88 -> 22794 | H85: =estimated_capacity!C85 -> 26096.078 | I85: {=_xlfn.IFS(D85= ""," ",D85<> " ",F85*(G85/H85))} -> 20855.631 | J85: {=_xlfn.IFS(D85= ""," ",D85<> " ",(H85-F85)*(G85/H85))} -> 1938.369 | K85: {=IF(ISNUMBER(H85),_xlfn.IFS(D85= ""," ",D85<> " ",F85*(G85/H85)),"")} -> 20855.631
A86: DEU | B86: 2009 | D86: FiT | E86: {=_xlfn.IFS(D86=policy_name_clustering!$A$2,policy_name_clustering!$C$2,D86=policy_name_clustering!$A$3,policy_name_clustering!$C$3,D86=policy_name_clustering!$A$5,policy_name_clustering!$C$5,D86=policy_name_clustering!$A$6,policy_name_clustering!$C$6,D86=policy_name_clustering!$A$7,policy_name_clustering!$C$7,D86=policy_name_clustering!$A$8,policy_name_clustering!$C$8,D86=policy_name_clustering!$A$9,policy_name_clustering!$C$9,D86=policy_name_clustering!$A$10,policy_name_clustering!$C$10,D86=policy_name_clustering!$A$11,policy_name_clustering!$C$11,D86=policy_name_clustering!$A$12,policy_name_clustering!$C$12,D86=policy_name_clustering!$A$13,policy_name_clustering!$C$13,D86=policy_name_clustering!$A$14,policy_name_clustering!$C$14,D86=policy_name_clustering!$A$15,policy_name_clustering!$C$15,D86=policy_name_clustering!$A$16,policy_name_clustering!$C$16,D86="-","",D86=policy_name_clustering!$A$4,policy_name_clustering!$C$4)} -> FiT/FiP-based | F86: =policy_contributions_cum!F18 -> 26019.596 | G86: =wind_cump_cap!C89 -> 25732 | H86: =estimated_capacity!C86 -> 28189.201 | I86: {=_xlfn.IFS(D86= ""," ",D86<> " ",F86*(G86/H86))} -> 23751.515 | J86: {=_xlfn.IFS(D86= ""," ",D86<> " ",(H86-F86)*(G86/H86))} -> 1980.4847 | K86: {=IF(ISNUMBER(H86),_xlfn.IFS(D86= ""," ",D86<> " ",F86*(G86/H86)),"")} -> 23751.515
A87: DEU | B87: 2010 | D87: FiT | E87: {=_xlfn.IFS(D87=policy_name_clustering!$A$2,policy_name_clustering!$C$2,D87=policy_name_clustering!$A$3,policy_name_clustering!$C$3,D87=policy_name_clustering!$A$5,policy_name_clustering!$C$5,D87=policy_name_clustering!$A$6,policy_name_clustering!$C$6,D87=policy_name_clustering!$A$7,policy_name_clustering!$C$7,D87=policy_name_clustering!$A$8,policy_name_clustering!$C$8,D87=policy_name_clustering!$A$9,policy_name_clustering!$C$9,D87=policy_name_clustering!$A$10,policy_name_clustering!$C$10,D87=policy_name_clustering!$A$11,policy_name_clustering!$C$11,D87=policy_name_clustering!$A$12,policy_name_clustering!$C$12,D87=policy_name_clustering!$A$13,policy_name_clustering!$C$13,D87=policy_name_clustering!$A$14,policy_name_clustering!$C$14,D87=policy_name_clustering!$A$15,policy_name_clustering!$C$15,D87=policy_name_clustering!$A$16,policy_name_clustering!$C$16,D87="-","",D87=policy_name_clustering!$A$4,policy_name_clustering!$C$4)} -> FiT/FiP-based | F87: =policy_contributions_cum!F19 -> 28292.111 | G87: =wind_cump_cap!C90 -> 26903 | H87: =estimated_capacity!C87 -> 30404.198 | I87: {=_xlfn.IFS(D87= ""," ",D87<> " ",F87*(G87/H87))} -> 25034.13 | J87: {=_xlfn.IFS(D87= ""," ",D87<> " ",(H87-F87)*(G87/H87))} -> 1868.8701 | K87: {=IF(ISNUMBER(H87),_xlfn.IFS(D87= ""," ",D87<> " ",F87*(G87/H87)),"")} -> 25034.13
A88: DEU | B88: 2011 | C88: FiP intro | D88: FiT | E88: {=_xlfn.IFS(D88=policy_name_clustering!$A$2,policy_name_clustering!$C$2,D88=policy_name_clustering!$A$3,policy_name_clustering!$C$3,D88=policy_name_clustering!$A$5,policy_name_clustering!$C$5,D88=policy_name_clustering!$A$6,policy_name_clustering!$C$6,D88=policy_name_clustering!$A$7,policy_name_clustering!$C$7,D88=policy_name_clustering!$A$8,policy_name_clustering!$C$8,D88=policy_name_clustering!$A$9,policy_name_clustering!$C$9,D88=policy_name_clustering!$A$10,policy_name_clustering!$C$10,D88=policy_name_clustering!$A$11,policy_name_clustering!$C$11,D88=policy_name_clustering!$A$12,policy_name_clustering!$C$12,D88=policy_name_clustering!$A$13,policy_name_clustering!$C$13,D88=policy_name_clustering!$A$14,policy_name_clustering!$C$14,D88=policy_name_clustering!$A$15,policy_name_clustering!$C$15,D88=policy_name_clustering!$A$16,policy_name_clustering!$C$16,D88="-","",D88=policy_name_clustering!$A$4,policy_name_clustering!$C$4)} -> FiT/FiP-based | F88: =policy_contributions_cum!F20 -> 30549.635 | G88: =wind_cump_cap!C91 -> 28712 | H88: =estimated_capacity!C88 -> 32595.147 | I88: {=_xlfn.IFS(D88= ""," ",D88<> " ",F88*(G88/H88))} -> 26910.175 | J88: {=_xlfn.IFS(D88= ""," ",D88<> " ",(H88-F88)*(G88/H88))} -> 1801.8253 | K88: {=IF(ISNUMBER(H88),_xlfn.IFS(D88= ""," ",D88<> " ",F88*(G88/H88)),"")} -> 26910.175
A89: DEU | B89: 2012 | C89: soft loan (onshore) intro | D89: FiT | E89: {=_xlfn.IFS(D89=policy_name_clustering!$A$2,policy_name_clustering!$C$2,D89=policy_name_clustering!$A$3,policy_name_clustering!$C$3,D89=policy_name_clustering!$A$5,policy_name_clustering!$C$5,D89=policy_name_clustering!$A$6,policy_name_clustering!$C$6,D89=policy_name_clustering!$A$7,policy_name_clustering!$C$7,D89=policy_name_clustering!$A$8,policy_name_clustering!$C$8,D89=policy_name_clustering!$A$9,policy_name_clustering!$C$9,D89=policy_name_clustering!$A$10,policy_name_clustering!$C$10,D89=policy_name_clustering!$A$11,policy_name_clustering!$C$11,D89=policy_name_clustering!$A$12,policy_name_clustering!$C$12,D89=policy_name_clustering!$A$13,policy_name_clustering!$C$13,D89=policy_name_clustering!$A$14,policy_name_clustering!$C$14,D89=policy_name_clustering!$A$15,policy_name_clustering!$C$15,D89=policy_name_clustering!$A$16,policy_name_clustering!$C$16,D89="-","",D89=policy_name_clustering!$A$4,policy_name_clustering!$C$4)} -> FiT/FiP-based | F89: =policy_contributions_cum!F21 -> 33055.909 | G89: =wind_cump_cap!C92 -> 30979 | H89: =estimated_capacity!C89 -> 35030.937 | I89: {=_xlfn.IFS(D89= ""," ",D89<> " ",F89*(G89/H89))} -> 29232.418 | J89: {=_xlfn.IFS(D89= ""," ",D89<> " ",(H89-F89)*(G89/H89))} -> 1746.5819 | K89: {=IF(ISNUMBER(H89),_xlfn.IFS(D89= ""," ",D89<> " ",F89*(G89/H89)),"")} -> 29232.418
A90: DEU | B90: 2013 | C90: soft loan (offshore) intro | D90: FiT | E90: {=_xlfn.IFS(D90=policy_name_clustering!$A$2,policy_name_clustering!$C$2,D90=policy_name_clustering!$A$3,policy_name_clustering!$C$3,D90=policy_name_clustering!$A$5,policy_name_clustering!$C$5,D90=policy_name_clustering!$A$6,policy_name_clustering!$C$6,D90=policy_name_clustering!$A$7,policy_name_clustering!$C$7,D90=policy_name_clustering!$A$8,policy_name_clustering!$C$8,D90=policy_name_clustering!$A$9,policy_name_clustering!$C$9,D90=policy_name_clustering!$A$10,policy_name_clustering!$C$10,D90=policy_name_clustering!$A$11,policy_name_clustering!$C$11,D90=policy_name_clustering!$A$12,policy_name_clustering!$C$12,D90=policy_name_clustering!$A$13,policy_name_clustering!$C$13,D90=policy_name_clustering!$A$14,policy_name_clustering!$C$14,D90=policy_name_clustering!$A$15,policy_name_clustering!$C$15,D90=policy_name_clustering!$A$16,policy_name_clustering!$C$16,D90="-","",D90=policy_name_clustering!$A$4,policy_name_clustering!$C$4)} -> FiT/FiP-based | F90: =policy_contributions_cum!F22 -> 35392.39 | G90: =wind_cump_cap!C93 -> 33477 | H90: =estimated_capacity!C90 -> 37289.064 | I90: {=_xlfn.IFS(D90= ""," ",D90<> " ",F90*(G90/H90))} -> 31774.223 | J90: {=_xlfn.IFS(D90= ""," ",D90<> " ",(H90-F90)*(G90/H90))} -> 1702.7768 | K90: {=IF(ISNUMBER(H90),_xlfn.IFS(D90= ""," ",D90<> " ",F90*(G90/H90)),"")} -> 31774.223
A91: DEU | B91: 2014 | C91: soft loan (onshore) interest rate increased | D91: FiT | E91: {=_xlfn.IFS(D91=policy_name_clustering!$A$2,policy_name_clustering!$C$2,D91=policy_name_clustering!$A$3,policy_name_clustering!$C$3,D91=policy_name_clustering!$A$5,policy_name_clustering!$C$5,D91=policy_name_clustering!$A$6,policy_name_clustering!$C$6,D91=policy_name_clustering!$A$7,policy_name_clustering!$C$7,D91=policy_name_clustering!$A$8,policy_name_clustering!$C$8,D91=policy_name_clustering!$A$9,policy_name_clustering!$C$9,D91=policy_name_clustering!$A$10,policy_name_clustering!$C$10,D91=policy_name_clustering!$A$11,policy_name_clustering!$C$11,D91=policy_name_clustering!$A$12,policy_name_clustering!$C$12,D91=policy_name_clustering!$A$13,policy_name_clustering!$C$13,D91=policy_name_clustering!$A$14,policy_name_clustering!$C$14,D91=policy_name_clustering!$A$15,policy_name_clustering!$C$15,D91=policy_name_clustering!$A$16,policy_name_clustering!$C$16,D91="-","",D91=policy_name_clustering!$A$4,policy_name_clustering!$C$4)} -> FiT/FiP-based | F91: =policy_contributions_cum!F23 -> 37831.655 | G91: =wind_cump_cap!C94 -> 38614 | H91: =estimated_capacity!C91 -> 39646.181 | I91: {=_xlfn.IFS(D91= ""," ",D91<> " ",F91*(G91/H91))} -> 36846.715 | J91: {=_xlfn.IFS(D91= ""," ",D91<> " ",(H91-F91)*(G91/H91))} -> 1767.2847 | K91: {=IF(ISNUMBER(H91),_xlfn.IFS(D91= ""," ",D91<> " ",F91*(G91/H91)),"")} -> 36846.715
A92: DEU | B92: 2015 | C92: FiP degression removed (offshore) | D92: FiT | E92: {=_xlfn.IFS(D92=policy_name_clustering!$A$2,policy_name_clustering!$C$2,D92=policy_name_clustering!$A$3,policy_name_clustering!$C$3,D92=policy_name_clustering!$A$5,policy_name_clustering!$C$5,D92=policy_name_clustering!$A$6,policy_name_clustering!$C$6,D92=policy_name_clustering!$A$7,policy_name_clustering!$C$7,D92=policy_name_clustering!$A$8,policy_name_clustering!$C$8,D92=policy_name_clustering!$A$9,policy_name_clustering!$C$9,D92=policy_name_clustering!$A$10,policy_name_clustering!$C$10,D92=policy_name_clustering!$A$11,policy_name_clustering!$C$11,D92=policy_name_clustering!$A$12,policy_name_clustering!$C$12,D92=policy_name_clustering!$A$13,policy_name_clustering!$C$13,D92=policy_name_clustering!$A$14,policy_name_clustering!$C$14,D92=policy_name_clustering!$A$15,policy_name_clustering!$C$15,D92=policy_name_clustering!$A$16,policy_name_clustering!$C$16,D92="-","",D92=policy_name_clustering!$A$4,policy_name_clustering!$C$4)} -> FiT/FiP-based | F92: =policy_contributions_cum!F24 -> 40646.366 | G92: =wind_cump_cap!C95 -> 44580 | H92: =estimated_capacity!C92 -> 42377.28 | I92: {=_xlfn.IFS(D92= ""," ",D92<> " ",F92*(G92/H92))} -> 42759.114 | J92: {=_xlfn.IFS(D92= ""," ",D92<> " ",(H92-F92)*(G92/H92))} -> 1820.8856 | K92: {=IF(ISNUMBER(H92),_xlfn.IFS(D92= ""," ",D92<> " ",F92*(G92/H92)),"")} -> 42759.114
A93: DEU | B93: 2016 | C93: FiT degression increased, FiT support level increased (onshore), FiT cancelled | D93: FiT | E93: {=_xlfn.IFS(D93=policy_name_clustering!$A$2,policy_name_clustering!$C$2,D93=policy_name_clustering!$A$3,policy_name_clustering!$C$3,D93=policy_name_clustering!$A$5,policy_name_clustering!$C$5,D93=policy_name_clustering!$A$6,policy_name_clustering!$C$6,D93=policy_name_clustering!$A$7,policy_name_clustering!$C$7,D93=policy_name_clustering!$A$8,policy_name_clustering!$C$8,D93=policy_name_clustering!$A$9,policy_name_clustering!$C$9,D93=policy_name_clustering!$A$10,policy_name_clustering!$C$10,D93=policy_name_clustering!$A$11,policy_name_clustering!$C$11,D93=policy_name_clustering!$A$12,policy_name_clustering!$C$12,D93=policy_name_clustering!$A$13,policy_name_clustering!$C$13,D93=policy_name_clustering!$A$14,policy_name_clustering!$C$14,D93=policy_name_clustering!$A$15,policy_name_clustering!$C$15,D93=policy_name_clustering!$A$16,policy_name_clustering!$C$16,D93="-","",D93=policy_name_clustering!$A$4,policy_name_clustering!$C$4)} -> FiT/FiP-based | F93: =policy_contributions_cum!F25 -> 43491.638 | G93: =wind_cump_cap!C96 -> 49435 | H93: =estimated_capacity!C93 -> 45135.546 | I93: {=_xlfn.IFS(D93= ""," ",D93<> " ",F93*(G93/H93))} -> 47634.499 | J93: {=_xlfn.IFS(D93= ""," ",D93<> " ",(H93-F93)*(G93/H93))} -> 1800.5009 | K93: {=IF(ISNUMBER(H93),_xlfn.IFS(D93= ""," ",D93<> " ",F93*(G93/H93)),"")} -> 47634.499
A94: DEU | B94: 2017 | C94: tender intro (Auction with fixed FIP) | D94: FiT | E94: {=_xlfn.IFS(D94=policy_name_clustering!$A$2,policy_name_clustering!$C$2,D94=policy_name_clustering!$A$3,policy_name_clustering!$C$3,D94=policy_name_clustering!$A$5,policy_name_clustering!$C$5,D94=policy_name_clustering!$A$6,policy_name_clustering!$C$6,D94=policy_name_clustering!$A$7,policy_name_clustering!$C$7,D94=policy_name_clustering!$A$8,policy_name_clustering!$C$8,D94=policy_name_clustering!$A$9,policy_name_clustering!$C$9,D94=policy_name_clustering!$A$10,policy_name_clustering!$C$10,D94=policy_name_clustering!$A$11,policy_name_clustering!$C$11,D94=policy_name_clustering!$A$12,policy_name_clustering!$C$12,D94=policy_name_clustering!$A$13,policy_name_clustering!$C$13,D94=policy_name_clustering!$A$14,policy_name_clustering!$C$14,D94=policy_name_clustering!$A$15,policy_name_clustering!$C$15,D94=policy_name_clustering!$A$16,policy_name_clustering!$C$16,D94="-","",D94=policy_name_clustering!$A$4,policy_name_clustering!$C$4)} -> FiT/FiP-based | F94: =policy_contributions_cum!F26 -> 46199.476 | G94: =wind_cump_cap!C97 -> 55580 | H94: =estimated_capacity!C94 -> 47752.943 | I94: {=_xlfn.IFS(D94= ""," ",D94<> " ",F94*(G94/H94))} -> 53771.909 | J94: {=_xlfn.IFS(D94= ""," ",D94<> " ",(H94-F94)*(G94/H94))} -> 1808.0914 | K94: {=IF(ISNUMBER(H94),_xlfn.IFS(D94= ""," ",D94<> " ",F94*(G94/H94)),"")} -> 53771.909
A95: DEU | B95: 2018 | C95: FiP cancelled | D95: FiT | E95: {=_xlfn.IFS(D95=policy_name_clustering!$A$2,policy_name_clustering!$C$2,D95=policy_name_clustering!$A$3,policy_name_clustering!$C$3,D95=policy_name_clustering!$A$5,policy_name_clustering!$C$5,D95=policy_name_clustering!$A$6,policy_name_clustering!$C$6,D95=policy_name_clustering!$A$7,policy_name_clustering!$C$7,D95=policy_name_clustering!$A$8,policy_name_clustering!$C$8,D95=policy_name_clustering!$A$9,policy_name_clustering!$C$9,D95=policy_name_clustering!$A$10,policy_name_clustering!$C$10,D95=policy_name_clustering!$A$11,policy_name_clustering!$C$11,D95=policy_name_clustering!$A$12,policy_name_clustering!$C$12,D95=policy_name_clustering!$A$13,policy_name_clustering!$C$13,D95=policy_name_clustering!$A$14,policy_name_clustering!$C$14,D95=policy_name_clustering!$A$15,policy_name_clustering!$C$15,D95=policy_name_clustering!$A$16,policy_name_clustering!$C$16,D95="-","",D95=policy_name_clustering!$A$4,policy_name_clustering!$C$4)} -> FiT/FiP-based | F95: =policy_contributions_cum!F27 -> 48978.937 | G95: =wind_cump_cap!C98 -> 58721 | H95: =estimated_capacity!C95 -> 50440.006 | I95: {=_xlfn.IFS(D95= ""," ",D95<> " ",F95*(G95/H95))} -> 57020.059 | J95: {=_xlfn.IFS(D95= ""," ",D95<> " ",(H95-F95)*(G95/H95))} -> 1700.9407 | K95: {=IF(ISNUMBER(H95),_xlfn.IFS(D95= ""," ",D95<> " ",F95*(G95/H95)),"")} -> 57020.059
A96: DEU | B96: 2019 | D96: FiT | E96: {=_xlfn.IFS(D96=policy_name_clustering!$A$2,policy_name_clustering!$C$2,D96=policy_name_clustering!$A$3,policy_name_clustering!$C$3,D96=policy_name_clustering!$A$5,policy_name_clustering!$C$5,D96=policy_name_clustering!$A$6,policy_name_clustering!$C$6,D96=policy_name_clustering!$A$7,policy_name_clustering!$C$7,D96=policy_name_clustering!$A$8,policy_name_clustering!$C$8,D96=policy_name_clustering!$A$9,policy_name_clustering!$C$9,D96=policy_name_clustering!$A$10,policy_name_clustering!$C$10,D96=policy_name_clustering!$A$11,policy_name_clustering!$C$11,D96=policy_name_clustering!$A$12,policy_name_clustering!$C$12,D96=policy_name_clustering!$A$13,policy_name_clustering!$C$13,D96=policy_name_clustering!$A$14,policy_name_clustering!$C$14,D96=policy_name_clustering!$A$15,policy_name_clustering!$C$15,D96=policy_name_clustering!$A$16,policy_name_clustering!$C$16,D96="-","",D96=policy_name_clustering!$A$4,policy_name_clustering!$C$4)} -> FiT/FiP-based | I96: =I95 -> 57020.059 | K96: {=IF(ISNUMBER(H96),_xlfn.IFS(D96= ""," ",D96<> " ",F96*(G96/H96)),"")}
A97: DEU | B97: 2020 | D97: FiT | E97: {=_xlfn.IFS(D97=policy_name_clustering!$A$2,policy_name_clustering!$C$2,D97=policy_name_clustering!$A$3,policy_name_clustering!$C$3,D97=policy_name_clustering!$A$5,policy_name_clustering!$C$5,D97=policy_name_clustering!$A$6,policy_name_clustering!$C$6,D97=policy_name_clustering!$A$7,policy_name_clustering!$C$7,D97=policy_name_clustering!$A$8,policy_name_clustering!$C$8,D97=policy_name_clustering!$A$9,policy_name_clustering!$C$9,D97=policy_name_clustering!$A$10,policy_name_clustering!$C$10,D97=policy_name_clustering!$A$11,policy_name_clustering!$C$11,D97=policy_name_clustering!$A$12,policy_name_clustering!$C$12,D97=policy_name_clustering!$A$13,policy_name_clustering!$C$13,D97=policy_name_clustering!$A$14,policy_name_clustering!$C$14,D97=policy_name_clustering!$A$15,policy_name_clustering!$C$15,D97=policy_name_clustering!$A$16,policy_name_clustering!$C$16,D97="-","",D97=policy_name_clustering!$A$4,policy_name_clustering!$C$4)} -> FiT/FiP-based | I97: =I96 -> 57020.059 | K97: {=IF(ISNUMBER(H97),_xlfn.IFS(D97= ""," ",D97<> " ",F97*(G97/H97)),"")}
A98: DEU | B98: 2021 | D98: FiT | E98: {=_xlfn.IFS(D98=policy_name_clustering!$A$2,policy_name_clustering!$C$2,D98=policy_name_clustering!$A$3,policy_name_clustering!$C$3,D98=policy_name_clustering!$A$5,policy_name_clustering!$C$5,D98=policy_name_clustering!$A$6,policy_name_clustering!$C$6,D98=policy_name_clustering!$A$7,policy_name_clustering!$C$7,D98=policy_name_clustering!$A$8,policy_name_clustering!$C$8,D98=policy_name_clustering!$A$9,policy_name_clustering!$C$9,D98=policy_name_clustering!$A$10,policy_name_clustering!$C$10,D98=policy_name_clustering!$A$11,policy_name_clustering!$C$11,D98=policy_name_clustering!$A$12,policy_name_clustering!$C$12,D98=policy_name_clustering!$A$13,policy_name_clustering!$C$13,D98=policy_name_clustering!$A$14,policy_name_clustering!$C$14,D98=policy_name_clustering!$A$15,policy_name_clustering!$C$15,D98=policy_name_clustering!$A$16,policy_name_clustering!$C$16,D98="-","",D98=policy_name_clustering!$A$4,policy_name_clustering!$C$4)} -> FiT/FiP-based | I98: =I97 -> 57020.059 | K98: {=IF(ISNUMBER(H98),_xlfn.IFS(D98= ""," ",D98<> " ",F98*(G98/H98)),"")}
A99: DEU | B99: 2022 | D99: FiT | E99: {=_xlfn.IFS(D99=policy_name_clustering!$A$2,policy_name_clustering!$C$2,D99=policy_name_clustering!$A$3,policy_name_clustering!$C$3,D99=policy_name_clustering!$A$5,policy_name_clustering!$C$5,D99=policy_name_clustering!$A$6,policy_name_clustering!$C$6,D99=policy_name_clustering!$A$7,policy_name_clustering!$C$7,D99=policy_name_clustering!$A$8,policy_name_clustering!$C$8,D99=policy_name_clustering!$A$9,policy_name_clustering!$C$9,D99=policy_name_clustering!$A$10,policy_name_clustering!$C$10,D99=policy_name_clustering!$A$11,policy_name_clustering!$C$11,D99=policy_name_clustering!$A$12,policy_name_clustering!$C$12,D99=policy_name_clustering!$A$13,policy_name_clustering!$C$13,D99=policy_name_clustering!$A$14,policy_name_clustering!$C$14,D99=policy_name_clustering!$A$15,policy_name_clustering!$C$15,D99=policy_name_clustering!$A$16,policy_name_clustering!$C$16,D99="-","",D99=policy_name_clustering!$A$4,policy_name_clustering!$C$4)} -> FiT/FiP-based | I99: =I98 -> 57020.059 | K99: {=IF(ISNUMBER(H99),_xlfn.IFS(D99= ""," ",D99<> " ",F99*(G99/H99)),"")}
A100: DEU | B100: 2023 | D100: FiT | E100: {=_xlfn.IFS(D100=policy_name_clustering!$A$2,policy_name_clustering!$C$2,D100=policy_name_clustering!$A$3,policy_name_clustering!$C$3,D100=policy_name_clustering!$A$5,policy_name_clustering!$C$5,D100=policy_name_clustering!$A$6,policy_name_clustering!$C$6,D100=policy_name_clustering!$A$7,policy_name_clustering!$C$7,D100=policy_name_clustering!$A$8,policy_name_clustering!$C$8,D100=policy_name_clustering!$A$9,policy_name_clustering!$C$9,D100=policy_name_clustering!$A$10,policy_name_clustering!$C$10,D100=policy_name_clustering!$A$11,policy_name_clustering!$C$11,D100=policy_name_clustering!$A$12,policy_name_clustering!$C$12,D100=policy_name_clustering!$A$13,policy_name_clustering!$C$13,D100=policy_name_clustering!$A$14,policy_name_clustering!$C$14,D100=policy_name_clustering!$A$15,policy_name_clustering!$C$15,D100=policy_name_clustering!$A$16,policy_name_clustering!$C$16,D100="-","",D100=policy_name_clustering!$A$4,policy_name_clustering!$C$4)} -> FiT/FiP-based | I100: =I99 -> 57020.059 | K100: {=IF(ISNUMBER(H100),_xlfn.IFS(D100= ""," ",D100<> " ",F100*(G100/H100)),"")}
A101: DEU | B101: 2019 | D101: Tender | E101: {=_xlfn.IFS(D101=policy_name_clustering!$A$2,policy_name_clustering!$C$2,D101=policy_name_clustering!$A$3,policy_name_clustering!$C$3,D101=policy_name_clustering!$A$5,policy_name_clustering!$C$5,D101=policy_name_clustering!$A$6,policy_name_clustering!$C$6,D101=policy_name_clustering!$A$7,policy_name_clustering!$C$7,D101=policy_name_clustering!$A$8,policy_name_clustering!$C$8,D101=policy_name_clustering!$A$9,policy_name_clustering!$C$9,D101=policy_name_clustering!$A$10,policy_name_clustering!$C$10,D101=policy_name_clustering!$A$11,policy_name_clustering!$C$11,D101=policy_name_clustering!$A$12,policy_name_clustering!$C$12,D101=policy_name_clustering!$A$13,policy_name_clustering!$C$13,D101=policy_name_clustering!$A$14,policy_name_clustering!$C$14,D101=policy_name_clustering!$A$15,policy_name_clustering!$C$15,D101=policy_name_clustering!$A$16,policy_name_clustering!$C$16,D101="-","",D101=policy_name_clustering!$A$4,policy_name_clustering!$C$4)} -> Tender-based | F101: =policy_contributions_cum!F28 -> 52064.968 | G101: =wind_cump_cap!C99 -> 60742 | H101: =estimated_capacity!C96 -> 53432.643 | I101: {=_xlfn.IFS(D101= ""," ",D101<> " ",F101*(G101/H101)-$I$95)} -> 2167.1741 | J101: {=_xlfn.IFS(D101= ""," ",D101<> " ",(H101-F101)*(G101/H101))} -> 1554.7666 | K101: {=IF(ISNUMBER(H101),_xlfn.IFS(D101= ""," ",D101<> " ",F101*(G101/H101)),"")} -> 59187.233
A102: DEU | B102: 2020 | D102: Tender | E102: {=_xlfn.IFS(D102=policy_name_clustering!$A$2,policy_name_clustering!$C$2,D102=policy_name_clustering!$A$3,policy_name_clustering!$C$3,D102=policy_name_clustering!$A$5,policy_name_clustering!$C$5,D102=policy_name_clustering!$A$6,policy_name_clustering!$C$6,D102=policy_name_clustering!$A$7,policy_name_clustering!$C$7,D102=policy_name_clustering!$A$8,policy_name_clustering!$C$8,D102=policy_name_clustering!$A$9,policy_name_clustering!$C$9,D102=policy_name_clustering!$A$10,policy_name_clustering!$C$10,D102=policy_name_clustering!$A$11,policy_name_clustering!$C$11,D102=policy_name_clustering!$A$12,policy_name_clustering!$C$12,D102=policy_name_clustering!$A$13,policy_name_clustering!$C$13,D102=policy_name_clustering!$A$14,policy_name_clustering!$C$14,D102=policy_name_clustering!$A$15,policy_name_clustering!$C$15,D102=policy_name_clustering!$A$16,policy_name_clustering!$C$16,D102="-","",D102=policy_name_clustering!$A$4,policy_name_clustering!$C$4)} -> Tender-based | F102: =policy_contributions_cum!F29 -> 55638.659 | G102: =wind_cump_cap!C100 -> 62201 | H102: =estimated_capacity!C97 -> 56912.361 | I102: {=_xlfn.IFS(D102= ""," ",D102<> " ",F102*(G102/H102)-$I$95)} -> 3788.8785 | J102: {=_xlfn.IFS(D102= ""," ",D102<> " ",(H102-F102)*(G102/H102))} -> 1392.0623 | K102: {=IF(ISNUMBER(H102),_xlfn.IFS(D102= ""," ",D102<> " ",F102*(G102/H102)),"")} -> 60808.938
A103: DEU | B103: 2021 | D103: Tender | E103: {=_xlfn.IFS(D103=policy_name_clustering!$A$2,policy_name_clustering!$C$2,D103=policy_name_clustering!$A$3,policy_name_clustering!$C$3,D103=policy_name_clustering!$A$5,policy_name_clustering!$C$5,D103=policy_name_clustering!$A$6,policy_name_clustering!$C$6,D103=policy_name_clustering!$A$7,policy_name_clustering!$C$7,D103=policy_name_clustering!$A$8,policy_name_clustering!$C$8,D103=policy_name_clustering!$A$9,policy_name_clustering!$C$9,D103=policy_name_clustering!$A$10,policy_name_clustering!$C$10,D103=policy_name_clustering!$A$11,policy_name_clustering!$C$11,D103=policy_name_clustering!$A$12,policy_name_clustering!$C$12,D103=policy_name_clustering!$A$13,policy_name_clustering!$C$13,D103=policy_name_clustering!$A$14,policy_name_clustering!$C$14,D103=policy_name_clustering!$A$15,policy_name_clustering!$C$15,D103=policy_name_clustering!$A$16,policy_name_clustering!$C$16,D103="-","",D103=policy_name_clustering!$A$4,policy_name_clustering!$C$4)} -> Tender-based | F103: =policy_contributions_cum!F30 -> 59283.282 | G103: =wind_cump_cap!C101 -> 63711 | H103: =estimated_capacity!C98 -> 60461.644 | I103: {=_xlfn.IFS(D103= ""," ",D103<> " ",F103*(G103/H103)-$I$95)} -> 5449.251 | J103: {=_xlfn.IFS(D103= ""," ",D103<> " ",(H103-F103)*(G103/H103))} -> 1241.6897 | K103: {=IF(ISNUMBER(H103),_xlfn.IFS(D103= ""," ",D103<> " ",F103*(G103/H103)),"")} -> 62469.31
A104: DEU | B104: 2022 | D104: Tender | E104: {=_xlfn.IFS(D104=policy_name_clustering!$A$2,policy_name_clustering!$C$2,D104=policy_name_clustering!$A$3,policy_name_clustering!$C$3,D104=policy_name_clustering!$A$5,policy_name_clustering!$C$5,D104=policy_name_clustering!$A$6,policy_name_clustering!$C$6,D104=policy_name_clustering!$A$7,policy_name_clustering!$C$7,D104=policy_name_clustering!$A$8,policy_name_clustering!$C$8,D104=policy_name_clustering!$A$9,policy_name_clustering!$C$9,D104=policy_name_clustering!$A$10,policy_name_clustering!$C$10,D104=policy_name_clustering!$A$11,policy_name_clustering!$C$11,D104=policy_name_clustering!$A$12,policy_name_clustering!$C$12,D104=policy_name_clustering!$A$13,policy_name_clustering!$C$13,D104=policy_name_clustering!$A$14,policy_name_clustering!$C$14,D104=policy_name_clustering!$A$15,policy_name_clustering!$C$15,D104=policy_name_clustering!$A$16,policy_name_clustering!$C$16,D104="-","",D104=policy_name_clustering!$A$4,policy_name_clustering!$C$4)} -> Tender-based | F104: =policy_contributions_cum!F31 -> 62736.199 | G104: =wind_cump_cap!C102 -> 66202 | H104: =estimated_capacity!C99 -> 63817.744 | I104: {=_xlfn.IFS(D104= ""," ",D104<> " ",F104*(G104/H104)-$I$95)} -> 8059.9883 | J104: {=_xlfn.IFS(D104= ""," ",D104<> " ",(H104-F104)*(G104/H104))} -> 1121.9524 | K104: {=IF(ISNUMBER(H104),_xlfn.IFS(D104= ""," ",D104<> " ",F104*(G104/H104)),"")} -> 65080.048
A105: DEU | B105: 2023 | D105: Tender | E105: {=_xlfn.IFS(D105=policy_name_clustering!$A$2,policy_name_clustering!$C$2,D105=policy_name_clustering!$A$3,policy_name_clustering!$C$3,D105=policy_name_clustering!$A$5,policy_name_clustering!$C$5,D105=policy_name_clustering!$A$6,policy_name_clustering!$C$6,D105=policy_name_clustering!$A$7,policy_name_clustering!$C$7,D105=policy_name_clustering!$A$8,policy_name_clustering!$C$8,D105=policy_name_clustering!$A$9,policy_name_clustering!$C$9,D105=policy_name_clustering!$A$10,policy_name_clustering!$C$10,D105=policy_name_clustering!$A$11,policy_name_clustering!$C$11,D105=policy_name_clustering!$A$12,policy_name_clustering!$C$12,D105=policy_name_clustering!$A$13,policy_name_clustering!$C$13,D105=policy_name_clustering!$A$14,policy_name_clustering!$C$14,D105=policy_name_clustering!$A$15,policy_name_clustering!$C$15,D105=policy_name_clustering!$A$16,policy_name_clustering!$C$16,D105="-","",D105=policy_name_clustering!$A$4,policy_name_clustering!$C$4)} -> Tender-based | F105: =policy_contributions_cum!F32 -> 66389.683 | G105: =wind_cump_cap!C103 -> 69486 | H105: =estimated_capacity!C100 -> 67373.705 | I105: {=_xlfn.IFS(D105= ""," ",D105<> " ",F105*(G105/H105)-$I$95)} -> 11451.067 | J105: {=_xlfn.IFS(D105= ""," ",D105<> " ",(H105-F105)*(G105/H105))} -> 1014.8737 | K105: {=IF(ISNUMBER(H105),_xlfn.IFS(D105= ""," ",D105<> " ",F105*(G105/H105)),"")} -> 68471.126
A106: DNK | B106: 1991 | D106: - | E106: {=_xlfn.IFS(D106=policy_name_clustering!$A$2,policy_name_clustering!$C$2,D106=policy_name_clustering!$A$3,policy_name_clustering!$C$3,D106=policy_name_clustering!$A$5,policy_name_clustering!$C$5,D106=policy_name_clustering!$A$6,policy_name_clustering!$C$6,D106=policy_name_clustering!$A$7,policy_name_clustering!$C$7,D106=policy_name_clustering!$A$8,policy_name_clustering!$C$8,D106=policy_name_clustering!$A$9,policy_name_clustering!$C$9,D106=policy_name_clustering!$A$10,policy_name_clustering!$C$10,D106=policy_name_clustering!$A$11,policy_name_clustering!$C$11,D106=policy_name_clustering!$A$12,policy_name_clustering!$C$12,D106=policy_name_clustering!$A$13,policy_name_clustering!$C$13,D106=policy_name_clustering!$A$14,policy_name_clustering!$C$14,D106=policy_name_clustering!$A$15,policy_name_clustering!$C$15,D106=policy_name_clustering!$A$16,policy_name_clustering!$C$16,D106="-","",D106=policy_name_clustering!$A$4,policy_name_clustering!$C$4)} | G106: =wind_cump_cap!C105 -> 392.859 | H106: =estimated_capacity!C101 -> 102.89494 | I106: {=_xlfn.IFS(D106= ""," ",D106<> " ",F106*(G106/H106))} -> 0 | J106: {=_xlfn.IFS(D106= ""," ",D106<> " ",(H106-F106)*(G106/H106))} -> 392.859 | K106: {=IF(ISNUMBER(H106),_xlfn.IFS(D106= ""," ",D106<> " ",F106*(G106/H106)),"")} -> 0
A107: DNK | B107: 1992 | D107: - | E107: {=_xlfn.IFS(D107=policy_name_clustering!$A$2,policy_name_clustering!$C$2,D107=policy_name_clustering!$A$3,policy_name_clustering!$C$3,D107=policy_name_clustering!$A$5,policy_name_clustering!$C$5,D107=policy_name_clustering!$A$6,policy_name_clustering!$C$6,D107=policy_name_clustering!$A$7,policy_name_clustering!$C$7,D107=policy_name_clustering!$A$8,policy_name_clustering!$C$8,D107=policy_name_clustering!$A$9,policy_name_clustering!$C$9,D107=policy_name_clustering!$A$10,policy_name_clustering!$C$10,D107=policy_name_clustering!$A$11,policy_name_clustering!$C$11,D107=policy_name_clustering!$A$12,policy_name_clustering!$C$12,D107=policy_name_clustering!$A$13,policy_name_clustering!$C$13,D107=policy_name_clustering!$A$14,policy_name_clustering!$C$14,D107=policy_name_clustering!$A$15,policy_name_clustering!$C$15,D107=policy_name_clustering!$A$16,policy_name_clustering!$C$16,D107="-","",D107=policy_name_clustering!$A$4,policy_name_clustering!$C$4)} | G107: =wind_cump_cap!C106 -> 435.949 | H107: =estimated_capacity!C102 -> 210.86781 | I107: {=_xlfn.IFS(D107= ""," ",D107<> " ",F107*(G107/H107))} -> 0 | J107: {=_xlfn.IFS(D107= ""," ",D107<> " ",(H107-F107)*(G107/H107))} -> 435.949 | K107: {=IF(ISNUMBER(H107),_xlfn.IFS(D107= ""," ",D107<> " ",F107*(G107/H107)),"")} -> 0
A108: DNK | B108: 1993 | D108: - | E108: {=_xlfn.IFS(D108=policy_name_clustering!$A$2,policy_name_clustering!$C$2,D108=policy_name_clustering!$A$3,policy_name_clustering!$C$3,D108=policy_name_clustering!$A$5,policy_name_clustering!$C$5,D108=policy_name_clustering!$A$6,policy_name_clustering!$C$6,D108=policy_name_clustering!$A$7,policy_name_clustering!$C$7,D108=policy_name_clustering!$A$8,policy_name_clustering!$C$8,D108=policy_name_clustering!$A$9,policy_name_clustering!$C$9,D108=policy_name_clustering!$A$10,policy_name_clustering!$C$10,D108=policy_name_clustering!$A$11,policy_name_clustering!$C$11,D108=policy_name_clustering!$A$12,policy_name_clustering!$C$12,D108=policy_name_clustering!$A$13,policy_name_clustering!$C$13,D108=policy_name_clustering!$A$14,policy_name_clustering!$C$14,D108=policy_name_clustering!$A$15,policy_name_clustering!$C$15,D108=policy_name_clustering!$A$16,policy_name_clustering!$C$16,D108="-","",D108=policy_name_clustering!$A$4,policy_name_clustering!$C$4)} | G108: =wind_cump_cap!C107 -> 468.099 | H108: =estimated_capacity!C103 -> 335.83897 | I108: {=_xlfn.IFS(D108= ""," ",D108<> " ",F108*(G108/H108))} -> 0 | J108: {=_xlfn.IFS(D108= ""," ",D108<> " ",(H108-F108)*(G108/H108))} -> 468.099 | K108: {=IF(ISNUMBER(H108),_xlfn.IFS(D108= ""," ",D108<> " ",F108*(G108/H108)),"")} -> 0
A109: DNK | B109: 1994 | D109: - | E109: {=_xlfn.IFS(D109=policy_name_clustering!$A$2,policy_name_clustering!$C$2,D109=policy_name_clustering!$A$3,policy_name_clustering!$C$3,D109=policy_name_clustering!$A$5,policy_name_clustering!$C$5,D109=policy_name_clustering!$A$6,policy_name_clustering!$C$6,D109=policy_name_clustering!$A$7,policy_name_clustering!$C$7,D109=policy_name_clustering!$A$8,policy_name_clustering!$C$8,D109=policy_name_clustering!$A$9,policy_name_clustering!$C$9,D109=policy_name_clustering!$A$10,policy_name_clustering!$C$10,D109=policy_name_clustering!$A$11,policy_name_clustering!$C$11,D109=policy_name_clustering!$A$12,policy_name_clustering!$C$12,D109=policy_name_clustering!$A$13,policy_name_clustering!$C$13,D109=policy_name_clustering!$A$14,policy_name_clustering!$C$14,D109=policy_name_clustering!$A$15,policy_name_clustering!$C$15,D109=policy_name_clustering!$A$16,policy_name_clustering!$C$16,D109="-","",D109=policy_name_clustering!$A$4,policy_name_clustering!$C$4)} | G109: =wind_cump_cap!C108 -> 521.237 | H109: =estimated_capacity!C104 -> 469.04973 | I109: {=_xlfn.IFS(D109= ""," ",D109<> " ",F109*(G109/H109))} -> 0 | J109: {=_xlfn.IFS(D109= ""," ",D109<> " ",(H109-F109)*(G109/H109))} -> 521.237 | K109: {=IF(ISNUMBER(H109),_xlfn.IFS(D109= ""," ",D109<> " ",F109*(G109/H109)),"")} -> 0
A110: DNK | B110: 1995 | D110: - | E110: {=_xlfn.IFS(D110=policy_name_clustering!$A$2,policy_name_clustering!$C$2,D110=policy_name_clustering!$A$3,policy_name_clustering!$C$3,D110=policy_name_clustering!$A$5,policy_name_clustering!$C$5,D110=policy_name_clustering!$A$6,policy_name_clustering!$C$6,D110=policy_name_clustering!$A$7,policy_name_clustering!$C$7,D110=policy_name_clustering!$A$8,policy_name_clustering!$C$8,D110=policy_name_clustering!$A$9,policy_name_clustering!$C$9,D110=policy_name_clustering!$A$10,policy_name_clustering!$C$10,D110=policy_name_clustering!$A$11,policy_name_clustering!$C$11,D110=policy_name_clustering!$A$12,policy_name_clustering!$C$12,D110=policy_name_clustering!$A$13,policy_name_clustering!$C$13,D110=policy_name_clustering!$A$14,policy_name_clustering!$C$14,D110=policy_name_clustering!$A$15,policy_name_clustering!$C$15,D110=policy_name_clustering!$A$16,policy_name_clustering!$C$16,D110="-","",D110=policy_name_clustering!$A$4,policy_name_clustering!$C$4)} | G110: =wind_cump_cap!C109 -> 599.499 | H110: =estimated_capacity!C105 -> 626.64529 | I110: {=_xlfn.IFS(D110= ""," ",D110<> " ",F110*(G110/H110))} -> 0 | J110: {=_xlfn.IFS(D110= ""," ",D110<> " ",(H110-F110)*(G110/H110))} -> 599.499 | K110: {=IF(ISNUMBER(H110),_xlfn.IFS(D110= ""," ",D110<> " ",F110*(G110/H110)),"")} -> 0
A111: DNK | B111: 1996 | D111: - | E111: {=_xlfn.IFS(D111=policy_name_clustering!$A$2,policy_name_clustering!$C$2,D111=policy_name_clustering!$A$3,policy_name_clustering!$C$3,D111=policy_name_clustering!$A$5,policy_name_clustering!$C$5,D111=policy_name_clustering!$A$6,policy_name_clustering!$C$6,D111=policy_name_clustering!$A$7,policy_name_clustering!$C$7,D111=policy_name_clustering!$A$8,policy_name_clustering!$C$8,D111=policy_name_clustering!$A$9,policy_name_clustering!$C$9,D111=policy_name_clustering!$A$10,policy_name_clustering!$C$10,D111=policy_name_clustering!$A$11,policy_name_clustering!$C$11,D111=policy_name_clustering!$A$12,policy_name_clustering!$C$12,D111=policy_name_clustering!$A$13,policy_name_clustering!$C$13,D111=policy_name_clustering!$A$14,policy_name_clustering!$C$14,D111=policy_name_clustering!$A$15,policy_name_clustering!$C$15,D111=policy_name_clustering!$A$16,policy_name_clustering!$C$16,D111="-","",D111=policy_name_clustering!$A$4,policy_name_clustering!$C$4)} | G111: =wind_cump_cap!C110 -> 814.221 | H111: =estimated_capacity!C106 -> 806.22155 | I111: {=_xlfn.IFS(D111= ""," ",D111<> " ",F111*(G111/H111))} -> 0 | J111: {=_xlfn.IFS(D111= ""," ",D111<> " ",(H111-F111)*(G111/H111))} -> 814.221 | K111: {=IF(ISNUMBER(H111),_xlfn.IFS(D111= ""," ",D111<> " ",F111*(G111/H111)),"")} -> 0
A112: DNK | B112: 1997 | D112: - | E112: {=_xlfn.IFS(D112=policy_name_clustering!$A$2,policy_name_clustering!$C$2,D112=policy_name_clustering!$A$3,policy_name_clustering!$C$3,D112=policy_name_clustering!$A$5,policy_name_clustering!$C$5,D112=policy_name_clustering!$A$6,policy_name_clustering!$C$6,D112=policy_name_clustering!$A$7,policy_name_clustering!$C$7,D112=policy_name_clustering!$A$8,policy_name_clustering!$C$8,D112=policy_name_clustering!$A$9,policy_name_clustering!$C$9,D112=policy_name_clustering!$A$10,policy_name_clustering!$C$10,D112=policy_name_clustering!$A$11,policy_name_clustering!$C$11,D112=policy_name_clustering!$A$12,policy_name_clustering!$C$12,D112=policy_name_clustering!$A$13,policy_name_clustering!$C$13,D112=policy_name_clustering!$A$14,policy_name_clustering!$C$14,D112=policy_name_clustering!$A$15,policy_name_clustering!$C$15,D112=policy_name_clustering!$A$16,policy_name_clustering!$C$16,D112="-","",D112=policy_name_clustering!$A$4,policy_name_clustering!$C$4)} | G112: =wind_cump_cap!C111 -> 1123.347 | H112: =estimated_capacity!C107 -> 1015.024 | I112: {=_xlfn.IFS(D112= ""," ",D112<> " ",F112*(G112/H112))} -> 0 | J112: {=_xlfn.IFS(D112= ""," ",D112<> " ",(H112-F112)*(G112/H112))} -> 1123.347 | K112: {=IF(ISNUMBER(H112),_xlfn.IFS(D112= ""," ",D112<> " ",F112*(G112/H112)),"")} -> 0
A113: DNK | B113: 1998 | D113: - | E113: {=_xlfn.IFS(D113=policy_name_clustering!$A$2,policy_name_clustering!$C$2,D113=policy_name_clustering!$A$3,policy_name_clustering!$C$3,D113=policy_name_clustering!$A$5,policy_name_clustering!$C$5,D113=policy_name_clustering!$A$6,policy_name_clustering!$C$6,D113=policy_name_clustering!$A$7,policy_name_clustering!$C$7,D113=policy_name_clustering!$A$8,policy_name_clustering!$C$8,D113=policy_name_clustering!$A$9,policy_name_clustering!$C$9,D113=policy_name_clustering!$A$10,policy_name_clustering!$C$10,D113=policy_name_clustering!$A$11,policy_name_clustering!$C$11,D113=policy_name_clustering!$A$12,policy_name_clustering!$C$12,D113=policy_name_clustering!$A$13,policy_name_clustering!$C$13,D113=policy_name_clustering!$A$14,policy_name_clustering!$C$14,D113=policy_name_clustering!$A$15,policy_name_clustering!$C$15,D113=policy_name_clustering!$A$16,policy_name_clustering!$C$16,D113="-","",D113=policy_name_clustering!$A$4,policy_name_clustering!$C$4)} | G113: =wind_cump_cap!C112 -> 1438.482 | H113: =estimated_capacity!C108 -> 1234.1074 | I113: {=_xlfn.IFS(D113= ""," ",D113<> " ",F113*(G113/H113))} -> 0 | J113: {=_xlfn.IFS(D113= ""," ",D113<> " ",(H113-F113)*(G113/H113))} -> 1438.482 | K113: {=IF(ISNUMBER(H113),_xlfn.IFS(D113= ""," ",D113<> " ",F113*(G113/H113)),"")} -> 0
A114: DNK | B114: 1999 | D114: - | E114: {=_xlfn.IFS(D114=policy_name_clustering!$A$2,policy_name_clustering!$C$2,D114=policy_name_clustering!$A$3,policy_name_clustering!$C$3,D114=policy_name_clustering!$A$5,policy_name_clustering!$C$5,D114=policy_name_clustering!$A$6,policy_name_clustering!$C$6,D114=policy_name_clustering!$A$7,policy_name_clustering!$C$7,D114=policy_name_clustering!$A$8,policy_name_clustering!$C$8,D114=policy_name_clustering!$A$9,policy_name_clustering!$C$9,D114=policy_name_clustering!$A$10,policy_name_clustering!$C$10,D114=policy_name_clustering!$A$11,policy_name_clustering!$C$11,D114=policy_name_clustering!$A$12,policy_name_clustering!$C$12,D114=policy_name_clustering!$A$13,policy_name_clustering!$C$13,D114=policy_name_clustering!$A$14,policy_name_clustering!$C$14,D114=policy_name_clustering!$A$15,policy_name_clustering!$C$15,D114=policy_name_clustering!$A$16,policy_name_clustering!$C$16,D114="-","",D114=policy_name_clustering!$A$4,policy_name_clustering!$C$4)} | G114: =wind_cump_cap!C113 -> 1753.445 | H114: =estimated_capacity!C109 -> 1480.2435 | I114: {=_xlfn.IFS(D114= ""," ",D114<> " ",F114*(G114/H114))} -> 0 | J114: {=_xlfn.IFS(D114= ""," ",D114<> " ",(H114-F114)*(G114/H114))} -> 1753.445 | K114: {=IF(ISNUMBER(H114),_xlfn.IFS(D114= ""," ",D114<> " ",F114*(G114/H114)),"")} -> 0
A115: DNK | B115: 2000 | D115: - | E115: {=_xlfn.IFS(D115=policy_name_clustering!$A$2,policy_name_clustering!$C$2,D115=policy_name_clustering!$A$3,policy_name_clustering!$C$3,D115=policy_name_clustering!$A$5,policy_name_clustering!$C$5,D115=policy_name_clustering!$A$6,policy_name_clustering!$C$6,D115=policy_name_clustering!$A$7,policy_name_clustering!$C$7,D115=policy_name_clustering!$A$8,policy_name_clustering!$C$8,D115=policy_name_clustering!$A$9,policy_name_clustering!$C$9,D115=policy_name_clustering!$A$10,policy_name_clustering!$C$10,D115=policy_name_clustering!$A$11,policy_name_clustering!$C$11,D115=policy_name_clustering!$A$12,policy_name_clustering!$C$12,D115=policy_name_clustering!$A$13,policy_name_clustering!$C$13,D115=policy_name_clustering!$A$14,policy_name_clustering!$C$14,D115=policy_name_clustering!$A$15,policy_name_clustering!$C$15,D115=policy_name_clustering!$A$16,policy_name_clustering!$C$16,D115="-","",D115=policy_name_clustering!$A$4,policy_name_clustering!$C$4)} | G115: =wind_cump_cap!C114 -> 2390.015 | H115: =estimated_capacity!C110 -> 1731.982 | I115: {=_xlfn.IFS(D115= ""," ",D115<> " ",F115*(G115/H115))} -> 0 | J115: {=_xlfn.IFS(D115= ""," ",D115<> " ",(H115-F115)*(G115/H115))} -> 2390.015 | K115: {=IF(ISNUMBER(H115),_xlfn.IFS(D115= ""," ",D115<> " ",F115*(G115/H115)),"")} -> 0
A116: DNK | B116: 2001 | D116: - | E116: {=_xlfn.IFS(D116=policy_name_clustering!$A$2,policy_name_clustering!$C$2,D116=policy_name_clustering!$A$3,policy_name_clustering!$C$3,D116=policy_name_clustering!$A$5,policy_name_clustering!$C$5,D116=policy_name_clustering!$A$6,policy_name_clustering!$C$6,D116=policy_name_clustering!$A$7,policy_name_clustering!$C$7,D116=policy_name_clustering!$A$8,policy_name_clustering!$C$8,D116=policy_name_clustering!$A$9,policy_name_clustering!$C$9,D116=policy_name_clustering!$A$10,policy_name_clustering!$C$10,D116=policy_name_clustering!$A$11,policy_name_clustering!$C$11,D116=policy_name_clustering!$A$12,policy_name_clustering!$C$12,D116=policy_name_clustering!$A$13,policy_name_clustering!$C$13,D116=policy_name_clustering!$A$14,policy_name_clustering!$C$14,D116=policy_name_clustering!$A$15,policy_name_clustering!$C$15,D116=policy_name_clustering!$A$16,policy_name_clustering!$C$16,D116="-","",D116=policy_name_clustering!$A$4,policy_name_clustering!$C$4)} | G116: =wind_cump_cap!C115 -> 2497.153 | H116: =estimated_capacity!C111 -> 2016.2463 | I116: {=_xlfn.IFS(D116= ""," ",D116<> " ",F116*(G116/H116))} -> 0 | J116: {=_xlfn.IFS(D116= ""," ",D116<> " ",(H116-F116)*(G116/H116))} -> 2497.153 | K116: {=IF(ISNUMBER(H116),_xlfn.IFS(D116= ""," ",D116<> " ",F116*(G116/H116)),"")} -> 0
A117: DNK | B117: 2002 | D117: - | E117: {=_xlfn.IFS(D117=policy_name_clustering!$A$2,policy_name_clustering!$C$2,D117=policy_name_clustering!$A$3,policy_name_clustering!$C$3,D117=policy_name_clustering!$A$5,policy_name_clustering!$C$5,D117=policy_name_clustering!$A$6,policy_name_clustering!$C$6,D117=policy_name_clustering!$A$7,policy_name_clustering!$C$7,D117=policy_name_clustering!$A$8,policy_name_clustering!$C$8,D117=policy_name_clustering!$A$9,policy_name_clustering!$C$9,D117=policy_name_clustering!$A$10,policy_name_clustering!$C$10,D117=policy_name_clustering!$A$11,policy_name_clustering!$C$11,D117=policy_name_clustering!$A$12,policy_name_clustering!$C$12,D117=policy_name_clustering!$A$13,policy_name_clustering!$C$13,D117=policy_name_clustering!$A$14,policy_name_clustering!$C$14,D117=policy_name_clustering!$A$15,policy_name_clustering!$C$15,D117=policy_name_clustering!$A$16,policy_name_clustering!$C$16,D117="-","",D117=policy_name_clustering!$A$4,policy_name_clustering!$C$4)} | G117: =wind_cump_cap!C116 -> 2894.531 | H117: =estimated_capacity!C112 -> 2304.3956 | I117: {=_xlfn.IFS(D117= ""," ",D117<> " ",F117*(G117/H117))} -> 0 | J117: {=_xlfn.IFS(D117= ""," ",D117<> " ",(H117-F117)*(G117/H117))} -> 2894.531 | K117: {=IF(ISNUMBER(H117),_xlfn.IFS(D117= ""," ",D117<> " ",F117*(G117/H117)),"")} -> 0
... A122: DNK | B122: 2007 | D122: - | E122: {=_xlfn.IFS(D122=policy_name_clustering!$A$2,policy_name_clustering!$C$2,D122=policy_name_clustering!$A$3,policy_name_clustering!$C$3,D122=policy_name_clustering!$A$5,policy_name_clustering!$C$5,D122=policy_name_clustering!$A$6,policy_name_clustering!$C$6,D122=policy_name_clustering!$A$7,policy_name_clustering!$C$7,D122=policy_name_clustering!$A$8,policy_name_clustering!$C$8,D122=policy_name_clustering!$A$9,policy_name_clustering!$C$9,D122=policy_name_clustering!$A$10,policy_name_clustering!$C$10,D122=policy_name_clustering!$A$11,policy_name_clustering!$C$11,D122=policy_name_clustering!$A$12,policy_name_clustering!$C$12,D122=policy_name_clustering!$A$13,policy_name_clustering!$C$13,D122=policy_name_clustering!$A$14,policy_name_clustering!$C$14,D122=policy_name_clustering!$A$15,policy_name_clustering!$C$15,D122=policy_name_clustering!$A$16,policy_name_clustering!$C$16,D122="-","",D122=policy_name_clustering!$A$4,policy_name_clustering!$C$4)} | G122: =wind_cump_cap!C121 -> 3124.214 | H122: =estimated_capacity!C117 -> 2649.6376 | I122: {=_xlfn.IFS(D122= ""," ",D122<> " ",F122*(G122/H122))} -> 0 | J122: {=_xlfn.IFS(D122= ""," ",D122<> " ",(H122-F122)*(G122/H122))} -> 3124.214 | K122: {=IF(ISNUMBER(H122),_xlfn.IFS(D122= ""," ",D122<> " ",F122*(G122/H122)),"")} -> 0
A123: DNK | B123: 2008 | C123: tender intro - 2005 (Auction with two-sided floating FIP (CfD)), FiP (onshore) intro - 2008, loan guarantee intro - 2008 | D123: Tender, FiP, Loan guarantee | E123: {=_xlfn.IFS(D123=policy_name_clustering!$A$2,policy_name_clustering!$C$2,D123=policy_name_clustering!$A$3,policy_name_clustering!$C$3,D123=policy_name_clustering!$A$5,policy_name_clustering!$C$5,D123=policy_name_clustering!$A$6,policy_name_clustering!$C$6,D123=policy_name_clustering!$A$7,policy_name_clustering!$C$7,D123=policy_name_clustering!$A$8,policy_name_clustering!$C$8,D123=policy_name_clustering!$A$9,policy_name_clustering!$C$9,D123=policy_name_clustering!$A$10,policy_name_clustering!$C$10,D123=policy_name_clustering!$A$11,policy_name_clustering!$C$11,D123=policy_name_clustering!$A$12,policy_name_clustering!$C$12,D123=policy_name_clustering!$A$13,policy_name_clustering!$C$13,D123=policy_name_clustering!$A$14,policy_name_clustering!$C$14,D123=policy_name_clustering!$A$15,policy_name_clustering!$C$15,D123=policy_name_clustering!$A$16,policy_name_clustering!$C$16,D123="-","",D123=policy_name_clustering!$A$4,policy_name_clustering!$C$4)} -> Policy mix | F123: =policy_contributions_cum!F33 -> 97.008855 | G123: =wind_cump_cap!C122 -> 3162.87 | H123: =estimated_capacity!C118 -> 2743.6468 | I123: {=_xlfn.IFS(D123= ""," ",D123<> " ",F123*(G123/H123))} -> 111.8316 | J123: {=_xlfn.IFS(D123= ""," ",D123<> " ",(H123-F123)*(G123/H123))} -> 3051.0384 | K123: {=IF(ISNUMBER(H123),_xlfn.IFS(D123= ""," ",D123<> " ",F123*(G123/H123)),"")} -> 111.8316
A124: DNK | B124: 2009 | C124: tender intro - 2005, FiP (onshore) intro - 2008, loan guarantee intro - 2008, FiP level reduced | D124: Tender, FiP, Loan guarantee | E124: {=_xlfn.IFS(D124=policy_name_clustering!$A$2,policy_name_clustering!$C$2,D124=policy_name_clustering!$A$3,policy_name_clustering!$C$3,D124=policy_name_clustering!$A$5,policy_name_clustering!$C$5,D124=policy_name_clustering!$A$6,policy_name_clustering!$C$6,D124=policy_name_clustering!$A$7,policy_name_clustering!$C$7,D124=policy_name_clustering!$A$8,policy_name_clustering!$C$8,D124=policy_name_clustering!$A$9,policy_name_clustering!$C$9,D124=policy_name_clustering!$A$10,policy_name_clustering!$C$10,D124=policy_name_clustering!$A$11,policy_name_clustering!$C$11,D124=policy_name_clustering!$A$12,policy_name_clustering!$C$12,D124=policy_name_clustering!$A$13,policy_name_clustering!$C$13,D124=policy_name_clustering!$A$14,policy_name_clustering!$C$14,D124=policy_name_clustering!$A$15,policy_name_clustering!$C$15,D124=policy_name_clustering!$A$16,policy_name_clustering!$C$16,D124="-","",D124=policy_name_clustering!$A$4,policy_name_clustering!$C$4)} -> Policy mix | F124: =policy_contributions_cum!F34 -> 385.62718 | G124: =wind_cump_cap!C123 -> 3482.087 | H124: =estimated_capacity!C119 -> 3028.9413 | I124: {=_xlfn.IFS(D124= ""," ",D124<> " ",F124*(G124/H124))} -> 443.31906 | J124: {=_xlfn.IFS(D124= ""," ",D124<> " ",(H124-F124)*(G124/H124))} -> 3038.7679 | K124: {=IF(ISNUMBER(H124),_xlfn.IFS(D124= ""," ",D124<> " ",F124*(G124/H124)),"")} -> 443.31906
A125: DNK | B125: 2010 | C125: negative break here: FiP level reduced - 2009 | D125: Tender, FiP, Loan guarantee | E125: {=_xlfn.IFS(D125=policy_name_clustering!$A$2,policy_name_clustering!$C$2,D125=policy_name_clustering!$A$3,policy_name_clustering!$C$3,D125=policy_name_clustering!$A$5,policy_name_clustering!$C$5,D125=policy_name_clustering!$A$6,policy_name_clustering!$C$6,D125=policy_name_clustering!$A$7,policy_name_clustering!$C$7,D125=policy_name_clustering!$A$8,policy_name_clustering!$C$8,D125=policy_name_clustering!$A$9,policy_name_clustering!$C$9,D125=policy_name_clustering!$A$10,policy_name_clustering!$C$10,D125=policy_name_clustering!$A$11,policy_name_clustering!$C$11,D125=policy_name_clustering!$A$12,policy_name_clustering!$C$12,D125=policy_name_clustering!$A$13,policy_name_clustering!$C$13,D125=policy_name_clustering!$A$14,policy_name_clustering!$C$14,D125=policy_name_clustering!$A$15,policy_name_clustering!$C$15,D125=policy_name_clustering!$A$16,policy_name_clustering!$C$16,D125="-","",D125=policy_name_clustering!$A$4,policy_name_clustering!$C$4)} -> Policy mix | F125: =policy_contributions_cum!F35 -> 725.08373 | G125: =wind_cump_cap!C124 -> 3801.829 | H125: =estimated_capacity!C120 -> 3316.6758 | I125: {=_xlfn.IFS(D125= ""," ",D125<> " ",F125*(G125/H125))} -> 831.14677 | J125: {=_xlfn.IFS(D125= ""," ",D125<> " ",(H125-F125)*(G125/H125))} -> 2970.6822 | K125: {=IF(ISNUMBER(H125),_xlfn.IFS(D125= ""," ",D125<> " ",F125*(G125/H125)),"")} -> 831.14677
A126: DNK | B126: 2011 | C126: FiP support duration reduced | D126: Tender, FiP, Loan guarantee | E126: {=_xlfn.IFS(D126=policy_name_clustering!$A$2,policy_name_clustering!$C$2,D126=policy_name_clustering!$A$3,policy_name_clustering!$C$3,D126=policy_name_clustering!$A$5,policy_name_clustering!$C$5,D126=policy_name_clustering!$A$6,policy_name_clustering!$C$6,D126=policy_name_clustering!$A$7,policy_name_clustering!$C$7,D126=policy_name_clustering!$A$8,policy_name_clustering!$C$8,D126=policy_name_clustering!$A$9,policy_name_clustering!$C$9,D126=policy_name_clustering!$A$10,policy_name_clustering!$C$10,D126=policy_name_clustering!$A$11,policy_name_clustering!$C$11,D126=policy_name_clustering!$A$12,policy_name_clustering!$C$12,D126=policy_name_clustering!$A$13,policy_name_clustering!$C$13,D126=policy_name_clustering!$A$14,policy_name_clustering!$C$14,D126=policy_name_clustering!$A$15,policy_name_clustering!$C$15,D126=policy_name_clustering!$A$16,policy_name_clustering!$C$16,D126="-","",D126=policy_name_clustering!$A$4,policy_name_clustering!$C$4)} -> Policy mix | F126: =policy_contributions_cum!F36 -> 1067.8619 | G126: =wind_cump_cap!C125 -> 3951.981 | H126: =estimated_capacity!C121 -> 3581.5666 | I126: {=_xlfn.IFS(D126= ""," ",D126<> " ",F126*(G126/H126))} -> 1178.3028 | J126: {=_xlfn.IFS(D126= ""," ",D126<> " ",(H126-F126)*(G126/H126))} -> 2773.6782 | K126: {=IF(ISNUMBER(H126),_xlfn.IFS(D126= ""," ",D126<> " ",F126*(G126/H126)),"")} -> 1178.3028
A127: DNK | B127: 2012 | D127: Tender, FiP, Loan guarantee | E127: {=_xlfn.IFS(D127=policy_name_clustering!$A$2,policy_name_clustering!$C$2,D127=policy_name_clustering!$A$3,policy_name_clustering!$C$3,D127=policy_name_clustering!$A$5,policy_name_clustering!$C$5,D127=policy_name_clustering!$A$6,policy_name_clustering!$C$6,D127=policy_name_clustering!$A$7,policy_name_clustering!$C$7,D127=policy_name_clustering!$A$8,policy_name_clustering!$C$8,D127=policy_name_clustering!$A$9,policy_name_clustering!$C$9,D127=policy_name_clustering!$A$10,policy_name_clustering!$C$10,D127=policy_name_clustering!$A$11,policy_name_clustering!$C$11,D127=policy_name_clustering!$A$12,policy_name_clustering!$C$12,D127=policy_name_clustering!$A$13,policy_name_clustering!$C$13,D127=policy_name_clustering!$A$14,policy_name_clustering!$C$14,D127=policy_name_clustering!$A$15,policy_name_clustering!$C$15,D127=policy_name_clustering!$A$16,policy_name_clustering!$C$16,D127="-","",D127=policy_name_clustering!$A$4,policy_name_clustering!$C$4)} -> Policy mix | F127: =policy_contributions_cum!F37 -> 1443.4536 | G127: =wind_cump_cap!C126 -> 4161.941 | H127: =estimated_capacity!C122 -> 3868.2685 | I127: {=_xlfn.IFS(D127= ""," ",D127<> " ",F127*(G127/H127))} -> 1553.0382 | J127: {=_xlfn.IFS(D127= ""," ",D127<> " ",(H127-F127)*(G127/H127))} -> 2608.9028 | K127: {=IF(ISNUMBER(H127),_xlfn.IFS(D127= ""," ",D127<> " ",F127*(G127/H127)),"")} -> 1553.0382
A128: DNK | B128: 2013 | C128: FiP (offshore) intro | D128: Tender, FiP, Loan guarantee | E128: {=_xlfn.IFS(D128=policy_name_clustering!$A$2,policy_name_clustering!$C$2,D128=policy_name_clustering!$A$3,policy_name_clustering!$C$3,D128=policy_name_clustering!$A$5,policy_name_clustering!$C$5,D128=policy_name_clustering!$A$6,policy_name_clustering!$C$6,D128=policy_name_clustering!$A$7,policy_name_clustering!$C$7,D128=policy_name_clustering!$A$8,policy_name_clustering!$C$8,D128=policy_name_clustering!$A$9,policy_name_clustering!$C$9,D128=policy_name_clustering!$A$10,policy_name_clustering!$C$10,D128=policy_name_clustering!$A$11,policy_name_clustering!$C$11,D128=policy_name_clustering!$A$12,policy_name_clustering!$C$12,D128=policy_name_clustering!$A$13,policy_name_clustering!$C$13,D128=policy_name_clustering!$A$14,policy_name_clustering!$C$14,D128=policy_name_clustering!$A$15,policy_name_clustering!$C$15,D128=policy_name_clustering!$A$16,policy_name_clustering!$C$16,D128="-","",D128=policy_name_clustering!$A$4,policy_name_clustering!$C$4)} -> Policy mix | F128: =policy_contributions_cum!F38 -> 1774.0805 | G128: =wind_cump_cap!C127 -> 4818.923 | H128: =estimated_capacity!C123 -> 4102.904 | I128: {=_xlfn.IFS(D128= ""," ",D128<> " ",F128*(G128/H128))} -> 2083.6845 | J128: {=_xlfn.IFS(D128= ""," ",D128<> " ",(H128-F128)*(G128/H128))} -> 2735.2385 | K128: {=IF(ISNUMBER(H128),_xlfn.IFS(D128= ""," ",D128<> " ",F128*(G128/H128)),"")} -> 2083.6845
A129: DNK | B129: 2014 | D129: Tender, FiP, Loan guarantee | E129: {=_xlfn.IFS(D129=policy_name_clustering!$A$2,policy_name_clustering!$C$2,D129=policy_name_clustering!$A$3,policy_name_clustering!$C$3,D129=policy_name_clustering!$A$5,policy_name_clustering!$C$5,D129=policy_name_clustering!$A$6,policy_name_clustering!$C$6,D129=policy_name_clustering!$A$7,policy_name_clustering!$C$7,D129=policy_name_clustering!$A$8,policy_name_clustering!$C$8,D129=policy_name_clustering!$A$9,policy_name_clustering!$C$9,D129=policy_name_clustering!$A$10,policy_name_clustering!$C$10,D129=policy_name_clustering!$A$11,policy_name_clustering!$C$11,D129=policy_name_clustering!$A$12,policy_name_clustering!$C$12,D129=policy_name_clustering!$A$13,policy_name_clustering!$C$13,D129=policy_name_clustering!$A$14,policy_name_clustering!$C$14,D129=policy_name_clustering!$A$15,policy_name_clustering!$C$15,D129=policy_name_clustering!$A$16,policy_name_clustering!$C$16,D129="-","",D129=policy_name_clustering!$A$4,policy_name_clustering!$C$4)} -> Policy mix | F129: =policy_contributions_cum!F39 -> 2104.6848 | G129: =wind_cump_cap!C128 -> 4886.403 | H129: =estimated_capacity!C124 -> 4334.7676 | I129: {=_xlfn.IFS(D129= ""," ",D129<> " ",F129*(G129/H129))} -> 2372.5236 | J129: {=_xlfn.IFS(D129= ""," ",D129<> " ",(H129-F129)*(G129/H129))} -> 2513.8794 | K129: {=IF(ISNUMBER(H129),_xlfn.IFS(D129= ""," ",D129<> " ",F129*(G129/H129)),"")} -> 2372.5236
A130: DNK | B130: 2015 | C130: FiP cancelled for (offshore) wind farms | D130: Tender, FiP, Loan guarantee | E130: {=_xlfn.IFS(D130=policy_name_clustering!$A$2,policy_name_clustering!$C$2,D130=policy_name_clustering!$A$3,policy_name_clustering!$C$3,D130=policy_name_clustering!$A$5,policy_name_clustering!$C$5,D130=policy_name_clustering!$A$6,policy_name_clustering!$C$6,D130=policy_name_clustering!$A$7,policy_name_clustering!$C$7,D130=policy_name_clustering!$A$8,policy_name_clustering!$C$8,D130=policy_name_clustering!$A$9,policy_name_clustering!$C$9,D130=policy_name_clustering!$A$10,policy_name_clustering!$C$10,D130=policy_name_clustering!$A$11,policy_name_clustering!$C$11,D130=policy_name_clustering!$A$12,policy_name_clustering!$C$12,D130=policy_name_clustering!$A$13,policy_name_clustering!$C$13,D130=policy_name_clustering!$A$14,policy_name_clustering!$C$14,D130=policy_name_clustering!$A$15,policy_name_clustering!$C$15,D130=policy_name_clustering!$A$16,policy_name_clustering!$C$16,D130="-","",D130=policy_name_clustering!$A$4,policy_name_clustering!$C$4)} -> Policy mix | F130: =policy_contributions_cum!F40 -> 2463.1919 | G130: =wind_cump_cap!C129 -> 5076.966 | H130: =estimated_capacity!C125 -> 4593.2822 | I130: {=_xlfn.IFS(D130= ""," ",D130<> " ",F130*(G130/H130))} -> 2722.572 | J130: {=_xlfn.IFS(D130= ""," ",D130<> " ",(H130-F130)*(G130/H130))} -> 2354.394 | K130: {=IF(ISNUMBER(H130),_xlfn.IFS(D130= ""," ",D130<> " ",F130*(G130/H130)),"")} -> 2722.572
A131: DNK | B131: 2016 | C131: FiP (onshore) support duration reduced, tender remuneration scheme changed (Auction with fixed FIP) | D131: Tender, FiP, Loan guarantee | E131: {=_xlfn.IFS(D131=policy_name_clustering!$A$2,policy_name_clustering!$C$2,D131=policy_name_clustering!$A$3,policy_name_clustering!$C$3,D131=policy_name_clustering!$A$5,policy_name_clustering!$C$5,D131=policy_name_clustering!$A$6,policy_name_clustering!$C$6,D131=policy_name_clustering!$A$7,policy_name_clustering!$C$7,D131=policy_name_clustering!$A$8,policy_name_clustering!$C$8,D131=policy_name_clustering!$A$9,policy_name_clustering!$C$9,D131=policy_name_clustering!$A$10,policy_name_clustering!$C$10,D131=policy_name_clustering!$A$11,policy_name_clustering!$C$11,D131=policy_name_clustering!$A$12,policy_name_clustering!$C$12,D131=policy_name_clustering!$A$13,policy_name_clustering!$C$13,D131=policy_name_clustering!$A$14,policy_name_clustering!$C$14,D131=policy_name_clustering!$A$15,policy_name_clustering!$C$15,D131=policy_name_clustering!$A$16,policy_name_clustering!$C$16,D131="-","",D131=policy_name_clustering!$A$4,policy_name_clustering!$C$4)} -> Policy mix | F131: =policy_contributions_cum!F41 -> 2805.4058 | G131: =wind_cump_cap!C130 -> 5245.142 | H131: =estimated_capacity!C126 -> 4834.7268 | I131: {=_xlfn.IFS(D131= ""," ",D131<> " ",F131*(G131/H131))} -> 3043.5539 | J131: {=_xlfn.IFS(D131= ""," ",D131<> " ",(H131-F131)*(G131/H131))} -> 2201.5881 | K131: {=IF(ISNUMBER(H131),_xlfn.IFS(D131= ""," ",D131<> " ",F131*(G131/H131)),"")} -> 3043.5539
A132: DNK | B132: 2017 | D132: Tender, FiP, Loan guarantee | E132: {=_xlfn.IFS(D132=policy_name_clustering!$A$2,policy_name_clustering!$C$2,D132=policy_name_clustering!$A$3,policy_name_clustering!$C$3,D132=policy_name_clustering!$A$5,policy_name_clustering!$C$5,D132=policy_name_clustering!$A$6,policy_name_clustering!$C$6,D132=policy_name_clustering!$A$7,policy_name_clustering!$C$7,D132=policy_name_clustering!$A$8,policy_name_clustering!$C$8,D132=policy_name_clustering!$A$9,policy_name_clustering!$C$9,D132=policy_name_clustering!$A$10,policy_name_clustering!$C$10,D132=policy_name_clustering!$A$11,policy_name_clustering!$C$11,D132=policy_name_clustering!$A$12,policy_name_clustering!$C$12,D132=policy_name_clustering!$A$13,policy_name_clustering!$C$13,D132=policy_name_clustering!$A$14,policy_name_clustering!$C$14,D132=policy_name_clustering!$A$15,policy_name_clustering!$C$15,D132=policy_name_clustering!$A$16,policy_name_clustering!$C$16,D132="-","",D132=policy_name_clustering!$A$4,policy_name_clustering!$C$4)} -> Policy mix | F132: =policy_contributions_cum!F42 -> 3114.6446 | G132: =wind_cump_cap!C131 -> 5488.949 | H132: =estimated_capacity!C127 -> 5042.8056 | I132: {=_xlfn.IFS(D132= ""," ",D132<> " ",F132*(G132/H132))} -> 3390.2012 | J132: {=_xlfn.IFS(D132= ""," ",D132<> " ",(H132-F132)*(G132/H132))} -> 2098.7478 | K132: {=IF(ISNUMBER(H132),_xlfn.IFS(D132= ""," ",D132<> " ",F132*(G132/H132)),"")} -> 3390.2012
A133: DNK | B133: 2018 | D133: Tender, FiP, Loan guarantee | E133: {=_xlfn.IFS(D133=policy_name_clustering!$A$2,policy_name_clustering!$C$2,D133=policy_name_clustering!$A$3,policy_name_clustering!$C$3,D133=policy_name_clustering!$A$5,policy_name_clustering!$C$5,D133=policy_name_clustering!$A$6,policy_name_clustering!$C$6,D133=policy_name_clustering!$A$7,policy_name_clustering!$C$7,D133=policy_name_clustering!$A$8,policy_name_clustering!$C$8,D133=policy_name_clustering!$A$9,policy_name_clustering!$C$9,D133=policy_name_clustering!$A$10,policy_name_clustering!$C$10,D133=policy_name_clustering!$A$11,policy_name_clustering!$C$11,D133=policy_name_clustering!$A$12,policy_name_clustering!$C$12,D133=policy_name_clustering!$A$13,policy_name_clustering!$C$13,D133=policy_name_clustering!$A$14,policy_name_clustering!$C$14,D133=policy_name_clustering!$A$15,policy_name_clustering!$C$15,D133=policy_name_clustering!$A$16,policy_name_clustering!$C$16,D133="-","",D133=policy_name_clustering!$A$4,policy_name_clustering!$C$4)} -> Policy mix | F133: =policy_contributions_cum!F43 -> 3418.2052 | G133: =wind_cump_cap!C132 -> 6122.66 | H133: =estimated_capacity!C128 -> 5245.0413 | I133: {=_xlfn.IFS(D133= ""," ",D133<> " ",F133*(G133/H133))} -> 3990.1513 | J133: {=_xlfn.IFS(D133= ""," ",D133<> " ",(H133-F133)*(G133/H133))} -> 2132.5087 | K133: {=IF(ISNUMBER(H133),_xlfn.IFS(D133= ""," ",D133<> " ",F133*(G133/H133)),"")} -> 3990.1513
A134: DNK | B134: 2019 | D134: Tender, FiP, Loan guarantee | E134: {=_xlfn.IFS(D134=policy_name_clustering!$A$2,policy_name_clustering!$C$2,D134=policy_name_clustering!$A$3,policy_name_clustering!$C$3,D134=policy_name_clustering!$A$5,policy_name_clustering!$C$5,D134=policy_name_clustering!$A$6,policy_name_clustering!$C$6,D134=policy_name_clustering!$A$7,policy_name_clustering!$C$7,D134=policy_name_clustering!$A$8,policy_name_clustering!$C$8,D134=policy_name_clustering!$A$9,policy_name_clustering!$C$9,D134=policy_name_clustering!$A$10,policy_name_clustering!$C$10,D134=policy_name_clustering!$A$11,policy_name_clustering!$C$11,D134=policy_name_clustering!$A$12,policy_name_clustering!$C$12,D134=policy_name_clustering!$A$13,policy_name_clustering!$C$13,D134=policy_name_clustering!$A$14,policy_name_clustering!$C$14,D134=policy_name_clustering!$A$15,policy_name_clustering!$C$15,D134=policy_name_clustering!$A$16,policy_name_clustering!$C$16,D134="-","",D134=policy_name_clustering!$A$4,policy_name_clustering!$C$4)} -> Policy mix | F134: =policy_contributions_cum!F44 -> 3740.3405 | G134: =wind_cump_cap!C133 -> 6110.543 | H134: =estimated_capacity!C129 -> 5465.7767 | I134: {=_xlfn.IFS(D134= ""," ",D134<> " ",F134*(G134/H134))} -> 4181.567 | J134: {=_xlfn.IFS(D134= ""," ",D134<> " ",(H134-F134)*(G134/H134))} -> 1928.976 | K134: {=IF(ISNUMBER(H134),_xlfn.IFS(D134= ""," ",D134<> " ",F134*(G134/H134)),"")} -> 4181.567
A135: DNK | B135: 2020 | D135: Tender, FiP, Loan guarantee | E135: {=_xlfn.IFS(D135=policy_name_clustering!$A$2,policy_name_clustering!$C$2,D135=policy_name_clustering!$A$3,policy_name_clustering!$C$3,D135=policy_name_clustering!$A$5,policy_name_clustering!$C$5,D135=policy_name_clustering!$A$6,policy_name_clustering!$C$6,D135=policy_name_clustering!$A$7,policy_name_clustering!$C$7,D135=policy_name_clustering!$A$8,policy_name_clustering!$C$8,D135=policy_name_clustering!$A$9,policy_name_clustering!$C$9,D135=policy_name_clustering!$A$10,policy_name_clustering!$C$10,D135=policy_name_clustering!$A$11,policy_name_clustering!$C$11,D135=policy_name_clustering!$A$12,policy_name_clustering!$C$12,D135=policy_name_clustering!$A$13,policy_name_clustering!$C$13,D135=policy_name_clustering!$A$14,policy_name_clustering!$C$14,D135=policy_name_clustering!$A$15,policy_name_clustering!$C$15,D135=policy_name_clustering!$A$16,policy_name_clustering!$C$16,D135="-","",D135=policy_name_clustering!$A$4,policy_name_clustering!$C$4)} -> Policy mix | F135: =policy_contributions_cum!F45 -> 4087.6013 | G135: =wind_cump_cap!C134 -> 6258.537 | H135: =estimated_capacity!C130 -> 5711.5982 | I135: {=_xlfn.IFS(D135= ""," ",D135<> " ",F135*(G135/H135))} -> 4479.0272 | J135: {=_xlfn.IFS(D135= ""," ",D135<> " ",(H135-F135)*(G135/H135))} -> 1779.5098 | K135: {=IF(ISNUMBER(H135),_xlfn.IFS(D135= ""," ",D135<> " ",F135*(G135/H135)),"")} -> 4479.0272
A136: DNK | B136: 2021 | C136: tender remuneration scheme changed (Auction with two-sided floating FIP (CfD)) | D136: Tender, FiP, Loan guarantee | E136: {=_xlfn.IFS(D136=policy_name_clustering!$A$2,policy_name_clustering!$C$2,D136=policy_name_clustering!$A$3,policy_name_clustering!$C$3,D136=policy_name_clustering!$A$5,policy_name_clustering!$C$5,D136=policy_name_clustering!$A$6,policy_name_clustering!$C$6,D136=policy_name_clustering!$A$7,policy_name_clustering!$C$7,D136=policy_name_clustering!$A$8,policy_name_clustering!$C$8,D136=policy_name_clustering!$A$9,policy_name_clustering!$C$9,D136=policy_name_clustering!$A$10,policy_name_clustering!$C$10,D136=policy_name_clustering!$A$11,policy_name_clustering!$C$11,D136=policy_name_clustering!$A$12,policy_name_clustering!$C$12,D136=policy_name_clustering!$A$13,policy_name_clustering!$C$13,D136=policy_name_clustering!$A$14,policy_name_clustering!$C$14,D136=policy_name_clustering!$A$15,policy_name_clustering!$C$15,D136=policy_name_clustering!$A$16,policy_name_clustering!$C$16,D136="-","",D136=policy_name_clustering!$A$4,policy_name_clustering!$C$4)} -> Policy mix | F136: =policy_contributions_cum!F46 -> 4414.3097 | G136: =wind_cump_cap!C135 -> 7003.948 | H136: =estimated_capacity!C131 -> 5936.8428 | I136: {=_xlfn.IFS(D136= ""," ",D136<> " ",F136*(G136/H136))} -> 5207.7504 | J136: {=_xlfn.IFS(D136= ""," ",D136<> " ",(H136-F136)*(G136/H136))} -> 1796.1976 | K136: {=IF(ISNUMBER(H136),_xlfn.IFS(D136= ""," ",D136<> " ",F136*(G136/H136)),"")} -> 5207.7504
A137: DNK | B137: 2022 | C137: FiP cancelled | D137: Tender, FiP, Loan guarantee | E137: {=_xlfn.IFS(D137=policy_name_clustering!$A$2,policy_name_clustering!$C$2,D137=policy_name_clustering!$A$3,policy_name_clustering!$C$3,D137=policy_name_clustering!$A$5,policy_name_clustering!$C$5,D137=policy_name_clustering!$A$6,policy_name_clustering!$C$6,D137=policy_name_clustering!$A$7,policy_name_clustering!$C$7,D137=policy_name_clustering!$A$8,policy_name_clustering!$C$8,D137=policy_name_clustering!$A$9,policy_name_clustering!$C$9,D137=policy_name_clustering!$A$10,policy_name_clustering!$C$10,D137=policy_name_clustering!$A$11,policy_name_clustering!$C$11,D137=policy_name_clustering!$A$12,policy_name_clustering!$C$12,D137=policy_name_clustering!$A$13,policy_name_clustering!$C$13,D137=policy_name_clustering!$A$14,policy_name_clustering!$C$14,D137=policy_name_clustering!$A$15,policy_name_clustering!$C$15,D137=policy_name_clustering!$A$16,policy_name_clustering!$C$16,D137="-","",D137=policy_name_clustering!$A$4,policy_name_clustering!$C$4)} -> Policy mix | F137: =policy_contributions_cum!F47 -> 4712.6666 | G137: =wind_cump_cap!C136 -> 7083.818 | H137: =estimated_capacity!C132 -> 6133.7239 | I137: {=_xlfn.IFS(D137= ""," ",D137<> " ",F137*(G137/H137))} -> 5442.6435 | J137: {=_xlfn.IFS(D137= ""," ",D137<> " ",(H137-F137)*(G137/H137))} -> 1641.1745 | K137: {=IF(ISNUMBER(H137),_xlfn.IFS(D137= ""," ",D137<> " ",F137*(G137/H137)),"")} -> 5442.6435
A138: DNK | B138: 2023 | D138: Tender, FiP, Loan guarantee | E138: {=_xlfn.IFS(D138=policy_name_clustering!$A$2,policy_name_clustering!$C$2,D138=policy_name_clustering!$A$3,policy_name_clustering!$C$3,D138=policy_name_clustering!$A$5,policy_name_clustering!$C$5,D138=policy_name_clustering!$A$6,policy_name_clustering!$C$6,D138=policy_name_clustering!$A$7,policy_name_clustering!$C$7,D138=policy_name_clustering!$A$8,policy_name_clustering!$C$8,D138=policy_name_clustering!$A$9,policy_name_clustering!$C$9,D138=policy_name_clustering!$A$10,policy_name_clustering!$C$10,D138=policy_name_clustering!$A$11,policy_name_clustering!$C$11,D138=policy_name_clustering!$A$12,policy_name_clustering!$C$12,D138=policy_name_clustering!$A$13,policy_name_clustering!$C$13,D138=policy_name_clustering!$A$14,policy_name_clustering!$C$14,D138=policy_name_clustering!$A$15,policy_name_clustering!$C$15,D138=policy_name_clustering!$A$16,policy_name_clustering!$C$16,D138="-","",D138=policy_name_clustering!$A$4,policy_name_clustering!$C$4)} -> Policy mix | F138: =policy_contributions_cum!F48 -> 5016.7081 | G138: =wind_cump_cap!C137 -> 7277.006 | H138: =estimated_capacity!C133 -> 6336.2847 | I138: {=_xlfn.IFS(D138= ""," ",D138<> " ",F138*(G138/H138))} -> 5761.5175 | J138: {=_xlfn.IFS(D138= ""," ",D138<> " ",(H138-F138)*(G138/H138))} -> 1515.4885 | K138: {=IF(ISNUMBER(H138),_xlfn.IFS(D138= ""," ",D138<> " ",F138*(G138/H138)),"")} -> 5761.5175
A139: ESP | B139: 1991 | D139: - | E139: {=_xlfn.IFS(D139=policy_name_clustering!$A$2,policy_name_clustering!$C$2,D139=policy_name_clustering!$A$3,policy_name_clustering!$C$3,D139=policy_name_clustering!$A$5,policy_name_clustering!$C$5,D139=policy_name_clustering!$A$6,policy_name_clustering!$C$6,D139=policy_name_clustering!$A$7,policy_name_clustering!$C$7,D139=policy_name_clustering!$A$8,policy_name_clustering!$C$8,D139=policy_name_clustering!$A$9,policy_name_clustering!$C$9,D139=policy_name_clustering!$A$10,policy_name_clustering!$C$10,D139=policy_name_clustering!$A$11,policy_name_clustering!$C$11,D139=policy_name_clustering!$A$12,policy_name_clustering!$C$12,D139=policy_name_clustering!$A$13,policy_name_clustering!$C$13,D139=policy_name_clustering!$A$14,policy_name_clustering!$C$14,D139=policy_name_clustering!$A$15,policy_name_clustering!$C$15,D139=policy_name_clustering!$A$16,policy_name_clustering!$C$16,D139="-","",D139=policy_name_clustering!$A$4,policy_name_clustering!$C$4)} | G139: =wind_cump_cap!C139 -> 3 | H139: =estimated_capacity!C134 -> 2.6367979 | I139: {=_xlfn.IFS(D139= ""," ",D139<> " ",F139*(G139/H139))} -> 0 | J139: {=_xlfn.IFS(D139= ""," ",D139<> " ",(H139-F139)*(G139/H139))} -> 3 | K139: {=IF(ISNUMBER(H139),_xlfn.IFS(D139= ""," ",D139<> " ",F139*(G139/H139)),"")} -> 0
A140: ESP | B140: 1992 | D140: - | E140: {=_xlfn.IFS(D140=policy_name_clustering!$A$2,policy_name_clustering!$C$2,D140=policy_name_clustering!$A$3,policy_name_clustering!$C$3,D140=policy_name_clustering!$A$5,policy_name_clustering!$C$5,D140=policy_name_clustering!$A$6,policy_name_clustering!$C$6,D140=policy_name_clustering!$A$7,policy_name_clustering!$C$7,D140=policy_name_clustering!$A$8,policy_name_clustering!$C$8,D140=policy_name_clustering!$A$9,policy_name_clustering!$C$9,D140=policy_name_clustering!$A$10,policy_name_clustering!$C$10,D140=policy_name_clustering!$A$11,policy_name_clustering!$C$11,D140=policy_name_clustering!$A$12,policy_name_clustering!$C$12,D140=policy_name_clustering!$A$13,policy_name_clustering!$C$13,D140=policy_name_clustering!$A$14,policy_name_clustering!$C$14,D140=policy_name_clustering!$A$15,policy_name_clustering!$C$15,D140=policy_name_clustering!$A$16,policy_name_clustering!$C$16,D140="-","",D140=policy_name_clustering!$A$4,policy_name_clustering!$C$4)} | G140: =wind_cump_cap!C140 -> 33 | H140: =estimated_capacity!C135 -> 6.8831811 | I140: {=_xlfn.IFS(D140= ""," ",D140<> " ",F140*(G140/H140))} -> 0 | J140: {=_xlfn.IFS(D140= ""," ",D140<> " ",(H140-F140)*(G140/H140))} -> 33 | K140: {=IF(ISNUMBER(H140),_xlfn.IFS(D140= ""," ",D140<> " ",F140*(G140/H140)),"")} -> 0
A141: ESP | B141: 1993 | D141: - | E141: {=_xlfn.IFS(D141=policy_name_clustering!$A$2,policy_name_clustering!$C$2,D141=policy_name_clustering!$A$3,policy_name_clustering!$C$3,D141=policy_name_clustering!$A$5,policy_name_clustering!$C$5,D141=policy_name_clustering!$A$6,policy_name_clustering!$C$6,D141=policy_name_clustering!$A$7,policy_name_clustering!$C$7,D141=policy_name_clustering!$A$8,policy_name_clustering!$C$8,D141=policy_name_clustering!$A$9,policy_name_clustering!$C$9,D141=policy_name_clustering!$A$10,policy_name_clustering!$C$10,D141=policy_name_clustering!$A$11,policy_name_clustering!$C$11,D141=policy_name_clustering!$A$12,policy_name_clustering!$C$12,D141=policy_name_clustering!$A$13,policy_name_clustering!$C$13,D141=policy_name_clustering!$A$14,policy_name_clustering!$C$14,D141=policy_name_clustering!$A$15,policy_name_clustering!$C$15,D141=policy_name_clustering!$A$16,policy_name_clustering!$C$16,D141="-","",D141=policy_name_clustering!$A$4,policy_name_clustering!$C$4)} | G141: =wind_cump_cap!C141 -> 34 | H141: =estimated_capacity!C136 -> 18.564603 | I141: {=_xlfn.IFS(D141= ""," ",D141<> " ",F141*(G141/H141))} -> 0 | J141: {=_xlfn.IFS(D141= ""," ",D141<> " ",(H141-F141)*(G141/H141))} -> 34 | K141: {=IF(ISNUMBER(H141),_xlfn.IFS(D141= ""," ",D141<> " ",F141*(G141/H141)),"")} -> 0
A142: ESP | B142: 1994 | C142: FiT intro - 1994 | D142: FiT | E142: {=_xlfn.IFS(D142=policy_name_clustering!$A$2,policy_name_clustering!$C$2,D142=policy_name_clustering!$A$3,policy_name_clustering!$C$3,D142=policy_name_clustering!$A$5,policy_name_clustering!$C$5,D142=policy_name_clustering!$A$6,policy_name_clustering!$C$6,D142=policy_name_clustering!$A$7,policy_name_clustering!$C$7,D142=policy_name_clustering!$A$8,policy_name_clustering!$C$8,D142=policy_name_clustering!$A$9,policy_name_clustering!$C$9,D142=policy_name_clustering!$A$10,policy_name_clustering!$C$10,D142=policy_name_clustering!$A$11,policy_name_clustering!$C$11,D142=policy_name_clustering!$A$12,policy_name_clustering!$C$12,D142=policy_name_clustering!$A$13,policy_name_clustering!$C$13,D142=policy_name_clustering!$A$14,policy_name_clustering!$C$14,D142=policy_name_clustering!$A$15,policy_name_clustering!$C$15,D142=policy_name_clustering!$A$16,policy_name_clustering!$C$16,D142="-","",D142=policy_name_clustering!$A$4,policy_name_clustering!$C$4)} -> FiT/FiP-based | F142: =policy_contributions_cum!F54 -> 28.568404 | G142: =wind_cump_cap!C142 -> 41 | H142: =estimated_capacity!C137 -> 64.471477 | I142: {=_xlfn.IFS(D142= ""," ",D142<> " ",F142*(G142/H142))} -> 18.167795 | J142: {=_xlfn.IFS(D142= ""," ",D142<> " ",(H142-F142)*(G142/H142))} -> 22.832205 | K142: {=IF(ISNUMBER(H142),_xlfn.IFS(D142= ""," ",D142<> " ",F142*(G142/H142)),"")} -> 18.167795
A143: ESP | B143: 1995 | C143: FiT intro - 1994 | D143: FiT | E143: {=_xlfn.IFS(D143=policy_name_clustering!$A$2,policy_name_clustering!$C$2,D143=policy_name_clustering!$A$3,policy_name_clustering!$C$3,D143=policy_name_clustering!$A$5,policy_name_clustering!$C$5,D143=policy_name_clustering!$A$6,policy_name_clustering!$C$6,D143=policy_name_clustering!$A$7,policy_name_clustering!$C$7,D143=policy_name_clustering!$A$8,policy_name_clustering!$C$8,D143=policy_name_clustering!$A$9,policy_name_clustering!$C$9,D143=policy_name_clustering!$A$10,policy_name_clustering!$C$10,D143=policy_name_clustering!$A$11,policy_name_clustering!$C$11,D143=policy_name_clustering!$A$12,policy_name_clustering!$C$12,D143=policy_name_clustering!$A$13,policy_name_clustering!$C$13,D143=policy_name_clustering!$A$14,policy_name_clustering!$C$14,D143=policy_name_clustering!$A$15,policy_name_clustering!$C$15,D143=policy_name_clustering!$A$16,policy_name_clustering!$C$16,D143="-","",D143=policy_name_clustering!$A$4,policy_name_clustering!$C$4)} -> FiT/FiP-based | F143: =policy_contributions_cum!F55 -> 98.531787 | G143: =wind_cump_cap!C143 -> 98 | H143: =estimated_capacity!C138 -> 162.83423 | I143: {=_xlfn.IFS(D143= ""," ",D143<> " ",F143*(G143/H143))} -> 59.300277 | J143: {=_xlfn.IFS(D143= ""," ",D143<> " ",(H143-F143)*(G143/H143))} -> 38.699723 | K143: {=IF(ISNUMBER(H143),_xlfn.IFS(D143= ""," ",D143<> " ",F143*(G143/H143)),"")} -> 59.300277
...

Sheet cumulative_effects
A1: policy instrument | B1: error-adjusted Cumulative policy instrument effect in GW
A2: FiT | B2: =SUMIFS(effect_quant_by_period!$I$2:$I$589,effect_quant_by_period!$D$2:$D$589,A2,effect_quant_by_period!$B$2:$B$589,estimated_capacity!$K$1)/1000 -> 85.849186
A3: FiT prolonged, FiT support duration increased | B3: =SUMIFS(effect_quant_by_period!$I$2:$I$589,effect_quant_by_period!$D$2:$D$589,A3,effect_quant_by_period!$B$2:$B$589,estimated_capacity!$K$1)/1000 -> 12.50677
A4: FiP | B4: =SUMIFS(effect_quant_by_period!$I$2:$I$589,effect_quant_by_period!$D$2:$D$589,A4,effect_quant_by_period!$B$2:$B$589,estimated_capacity!$K$1)/1000 -> 6.6995896
A5: Tax incentive, Subsidy, TGC | B5: =SUMIFS(effect_quant_by_period!$I$2:$I$589,effect_quant_by_period!$D$2:$D$589,A5,effect_quant_by_period!$B$2:$B$589,estimated_capacity!$K$1)/1000 -> 0.42229176
A6: Tax incentive, TGC | B6: =SUMIFS(effect_quant_by_period!$I$2:$I$589,effect_quant_by_period!$D$2:$D$589,A6,effect_quant_by_period!$B$2:$B$589,estimated_capacity!$K$1)/1000 -> 16.953336
A7: TGC | B7: =SUMIFS(effect_quant_by_period!$I$2:$I$589,effect_quant_by_period!$D$2:$D$589,A7,effect_quant_by_period!$B$2:$B$589,estimated_capacity!$K$1)/1000 -> 9.5113122
A8: Tax incentive, TGC level increase | B8: =SUMIFS(effect_quant_by_period!$I$2:$I$589,effect_quant_by_period!$D$2:$D$589,A8,effect_quant_by_period!$B$2:$B$589,estimated_capacity!$K$1)/1000 -> 7.5580639
A9: TGC aim increase, Tax incentive | B9: =SUMIFS(effect_quant_by_period!$I$2:$I$589,effect_quant_by_period!$D$2:$D$589,A9,effect_quant_by_period!$B$2:$B$589,estimated_capacity!$K$1)/1000 -> 8.4137234
A10: Tax incentive | B10: =SUMIFS(effect_quant_by_period!$I$2:$I$589,effect_quant_by_period!$D$2:$D$589,A10,effect_quant_by_period!$B$2:$B$589,estimated_capacity!$K$1)/1000 -> 3.9040364
A11: Tax incentive increase, TGC aim increase, Tender | B11: =SUMIFS(effect_quant_by_period!$I$2:$I$589,effect_quant_by_period!$D$2:$D$589,A11,effect_quant_by_period!$B$2:$B$589,estimated_capacity!$K$1)/1000 -> 4.6048161
A12: Subsidy prolonged, Tax incentive level increased | B12: =SUMIFS(effect_quant_by_period!$I$2:$I$589,effect_quant_by_period!$D$2:$D$589,A12,effect_quant_by_period!$B$2:$B$589,estimated_capacity!$K$1)/1000 -> 2.2156931
A13: Tender | B13: =SUMIFS(effect_quant_by_period!$I$2:$I$589,effect_quant_by_period!$D$2:$D$589,A13,effect_quant_by_period!$B$2:$B$589,estimated_capacity!$K$1)/1000 -> 25.08644
... A16: Subsidy prolonged | B16: =SUMIFS(effect_quant_by_period!$I$2:$I$589,effect_quant_by_period!$D$2:$D$589,A16,effect_quant_by_period!$B$2:$B$589,estimated_capacity!$K$1)/1000 -> 1.1515816
A17: Total policy effect | B17: =SUM(B2:B16) -> 197.6152 | C17: =SUMIFS(effect_quant_by_period!$J$2:$J$589,effect_quant_by_period!$B$2:$B$589,2023)/1000 -> 45.272322 | D17: =estimated_capacity!G2-B17 -> 44.0812
A18: Non-policy factors | B18: =SUMIFS(effect_quant_by_period!$J$2:$J$589,effect_quant_by_period!$B$2:$B$589,2023)/1000 -> 45.272322 | C18: =(estimated_capacity!G2-B17)-C17 -> -1.1911217 | D18: difference as model estimated cumulative capacity is not error adjusted!
A19: Policy effect share | B19: =B17/SUM(B17:B18) -> 0.81360787
A21: policy instrument | B21: error-adjusted Cumulative policy instrument effect in GW
A22: FiT/FiP-based | B22: =SUM(B2:B4) -> 105.05555
A23: Tender-based | B23: =SUM(B13) -> 25.08644
A24: TGC-based | B24: =SUM(B7) -> 9.5113122
A25: Tax-based | B25: =SUM(B10) -> 3.9040364
A26: Policy mix | B26: =SUM(B14,B11,B6,B5,B9,B8,B12,B15) -> 52.906285
A27: Other single instrument | B27: =SUM(B16) -> 1.1515816
A28: Total policy effect | B28: =B17 -> 197.6152
A29: Non-policy factors | B29: =B18 -> 45.272322

Sheet policy_contributions_cum
A1: id | B1: time | C1: policy | D1: effect_mw | E1: benchmark_mw | F1: cumulative_effect_mw
A2: DEU | B2: 1993 | C2: effect_tisDEU.1993 | D2: 51.921175 | E2: 161.17433 | F2: 51.921175
A3: DEU | B3: 1994 | C3: effect_tisDEU.1993 | D3: 121.01904 | E3: 238.19431 | F3: 172.94021
A4: DEU | B4: 1995 | C4: effect_tisDEU.1993 | D4: 228.60767 | E4: 371.31132 | F4: 401.54788
A5: DEU | B5: 1996 | C5: effect_tisDEU.1993 | D5: 371.41928 | E5: 532.75093 | F5: 772.96717
A6: DEU | B6: 1997 | C6: effect_tisDEU.1993 | D6: 579.6171 | E6: 766.81647 | F6: 1352.5843
A7: DEU | B7: 1998 | C7: effect_tisDEU.1993 | D7: 813.0813 | E7: 1007.3873 | F7: 2165.6656
A8: DEU | B8: 1999 | C8: effect_tisDEU.1993 | D8: 1181.4601 | E8: 1401.683 | F8: 3347.1257
A9: DEU | B9: 2000 | C9: effect_tisDEU.1993 | D9: 1570.7665 | E9: 1794.9202 | F9: 4917.8922
A10: DEU | B10: 2001 | C10: effect_tisDEU.1993 | D10: 2227.0017 | E10: 2481.3555 | F10: 7144.8939
A11: DEU | B11: 2002 | C11: effect_tisDEU.1993 | D11: 2256.2382 | E11: 2435.1435 | F11: 9401.1321
A12: DEU | B12: 2003 | C12: effect_tisDEU.1993 | D12: 2458.1153 | E12: 2595.8467 | F12: 11859.247
A13: DEU | B13: 2004 | C13: effect_tisDEU.1993 | D13: 2406.7327 | E13: 2489.6182 | F13: 14265.98
... A208: SWE | B208: 2023 | C208: effect_fesisSWE.2008 | D208: 1118.9349 | E208: 1503.0466 | F208: 11223.456

Sheet wind_cump_cap
A1: year | B1: country | C1: wind.cap | E1: Eur_cum_cap_wind_GW | H1: end sample year | I1: 2023
A2: 1990 | B2: AUT | C2: 0 | E2: =SUMIF($A$2:$A$523,$I$1,$C$2:$C$523)/1000 -> 242.88752
A3: 1991 | B3: AUT | C3: 0
A4: 1992 | B4: AUT | C4: 0
A5: 1993 | B5: AUT | C5: 1
A6: 1994 | B6: AUT | C6: 1
A7: 1995 | B7: AUT | C7: 1
A8: 1996 | B8: AUT | C8: 3
A9: 1997 | B9: AUT | C9: 15
A10: 1998 | B10: AUT | C10: 34
A11: 1999 | B11: AUT | C11: 38
A12: 2000 | B12: AUT | C12: 50
A13: 2001 | B13: AUT | C13: 67
A14: 2002 | B14: AUT | C14: 109
... A523: 2023 | B523: SWE | C523: 16224

Sheet estimated_capacity
A1: id | B1: time | C1: estimated_cumulative_wind_cap_MW | G1: Eur_estimated_cum_cap_GW | J1: end sample year | K1: 2023
A2: AUT | B2: 1991 | C2: -8.2265578 | G2: =SUMIF($B$2:$B$507,$K$1,$C$2:$C$507)/1000 -> 241.6964
A3: AUT | B3: 1992 | C3: -12.430992
A4: AUT | B4: 1993 | C4: -10.517072
A5: AUT | B5: 1994 | C5: -4.4677335
A6: AUT | B6: 1995 | C6: 13.625984
A7: AUT | B7: 1996 | C7: 41.36612
A8: AUT | B8: 1997 | C8: 81.797647
A9: AUT | B9: 1998 | C9: 125.66332
A10: AUT | B10: 1999 | C10: 181.79522
A11: AUT | B11: 2000 | C11: 239.55534
A12: AUT | B12: 2001 | C12: 311.97932
A13: AUT | B13: 2002 | C13: 386.63779
A14: AUT | B14: 2003 | C14: 478.8744
... A507: SWE | B507: 2023 | C507: 15456.19

Sheet policy_name_clustering
A1: full name | B1: dominant instrument | C1: cluster name
A2: FiT | B2: FiT | C2: FiT/FiP-based
A3: FiT prolonged, FiT support duration increased | B3: FiT | C3: FiT/FiP-based
A4: FiP | B4: FiP | C4: FiT/FiP-based
A5: Tender | B5: Tender | C5: Tender-based
A6: Tender, FiP, Loan guarantee | B6: FiP | C6: Policy mix
A7: Tax incentive increase, TGC aim increase, Tender | B7: Tender | C7: Policy mix
A8: TGC | B8: TGC | C8: TGC-based
A9: Tax incentive | B9: Tax incentive | C9: Tax-based
A10: Tax incentive, TGC | B10: TGC | C10: Policy mix
A11: Subsidy prolonged | B11: Subsidy | C11: Other single instrument
A12: Tax incentive, Subsidy, TGC | B12: TGC | C12: Policy mix
... A16: Tax incentive extended, Tender | B16: Tender | C16: Policy mix
