Workbook

Sheet effect_quant_by_period
A1: id | B1: time | C1: policy details | D1: policy effects and effect duration | E1: policy_group_name | F1: cumulative_policy_effect_mw | G1: observed cumulative MW deployed | H1: estimated cumulative MW deployed | I1: error-adjusted total policy effect in MW | J1: error-adjusted non-policy & unidentified policy effect in MW | K1: cumulative error-adjusted total policy mix effect in MW
A2: AUT | B2: 2001 | D2: - | E2: {=_xlfn.IFS(D2=policy_name_clustering!$A$2,policy_name_clustering!$C$2,D2=policy_name_clustering!$A$3,policy_name_clustering!$C$3,D2=policy_name_clustering!$A$4,policy_name_clustering!$C$4,D2=policy_name_clustering!$A$5,policy_name_clustering!$C$5,D2=policy_name_clustering!$A$6,policy_name_clustering!$C$6,D2=policy_name_clustering!$A$7,policy_name_clustering!$C$7,D2=policy_name_clustering!$A$8,policy_name_clustering!$C$8,D2=policy_name_clustering!$A$9,policy_name_clustering!$C$9,D2=policy_name_clustering!$A$10,policy_name_clustering!$C$10,D2=policy_name_clustering!$A$11,policy_name_clustering!$C$11,D2=policy_name_clustering!$A$12,policy_name_clustering!$C$12,D2="-","")} | G2: =solar_cum_cap!C3 -> 7 | H2: =estimated_capacity!C2 -> 37.662573 | I2: {=_xlfn.IFS(D2= ""," ",D2<> " ",F2*(G2/H2))} -> 0 | J2: {=_xlfn.IFS(D2= ""," ",D2<> " ",(H2-F2)*(G2/H2))} -> 7 | K2: {=IF(ISNUMBER(H2),_xlfn.IFS(D2= ""," ",D2<> " ",F2*(G2/H2)),"")} -> 0
A3: AUT | B3: 2002 | D3: - | E3: {=_xlfn.IFS(D3=policy_name_clustering!$A$2,policy_name_clustering!$C$2,D3=policy_name_clustering!$A$3,policy_name_clustering!$C$3,D3=policy_name_clustering!$A$4,policy_name_clustering!$C$4,D3=policy_name_clustering!$A$5,policy_name_clustering!$C$5,D3=policy_name_clustering!$A$6,policy_name_clustering!$C$6,D3=policy_name_clustering!$A$7,policy_name_clustering!$C$7,D3=policy_name_clustering!$A$8,policy_name_clustering!$C$8,D3=policy_name_clustering!$A$9,policy_name_clustering!$C$9,D3=policy_name_clustering!$A$10,policy_name_clustering!$C$10,D3=policy_name_clustering!$A$11,policy_name_clustering!$C$11,D3=policy_name_clustering!$A$12,policy_name_clustering!$C$12,D3="-","")} | G3: =solar_cum_cap!C4 -> 9 | H3: =estimated_capacity!C3 -> 67.605946 | I3: {=_xlfn.IFS(D3= ""," ",D3<> " ",F3*(G3/H3))} -> 0 | J3: {=_xlfn.IFS(D3= ""," ",D3<> " ",(H3-F3)*(G3/H3))} -> 9 | K3: {=IF(ISNUMBER(H3),_xlfn.IFS(D3= ""," ",D3<> " ",F3*(G3/H3)),"")} -> 0
A4: AUT | B4: 2003 | D4: - | E4: {=_xlfn.IFS(D4=policy_name_clustering!$A$2,policy_name_clustering!$C$2,D4=policy_name_clustering!$A$3,policy_name_clustering!$C$3,D4=policy_name_clustering!$A$4,policy_name_clustering!$C$4,D4=policy_name_clustering!$A$5,policy_name_clustering!$C$5,D4=policy_name_clustering!$A$6,policy_name_clustering!$C$6,D4=policy_name_clustering!$A$7,policy_name_clustering!$C$7,D4=policy_name_clustering!$A$8,policy_name_clustering!$C$8,D4=policy_name_clustering!$A$9,policy_name_clustering!$C$9,D4=policy_name_clustering!$A$10,policy_name_clustering!$C$10,D4=policy_name_clustering!$A$11,policy_name_clustering!$C$11,D4=policy_name_clustering!$A$12,policy_name_clustering!$C$12,D4="-","")} | G4: =solar_cum_cap!C5 -> 23 | H4: =estimated_capacity!C4 -> 111.45853 | I4: {=_xlfn.IFS(D4= ""," ",D4<> " ",F4*(G4/H4))} -> 0 | J4: {=_xlfn.IFS(D4= ""," ",D4<> " ",(H4-F4)*(G4/H4))} -> 23 | K4: {=IF(ISNUMBER(H4),_xlfn.IFS(D4= ""," ",D4<> " ",F4*(G4/H4)),"")} -> 0
A5: AUT | B5: 2004 | D5: - | E5: {=_xlfn.IFS(D5=policy_name_clustering!$A$2,policy_name_clustering!$C$2,D5=policy_name_clustering!$A$3,policy_name_clustering!$C$3,D5=policy_name_clustering!$A$4,policy_name_clustering!$C$4,D5=policy_name_clustering!$A$5,policy_name_clustering!$C$5,D5=policy_name_clustering!$A$6,policy_name_clustering!$C$6,D5=policy_name_clustering!$A$7,policy_name_clustering!$C$7,D5=policy_name_clustering!$A$8,policy_name_clustering!$C$8,D5=policy_name_clustering!$A$9,policy_name_clustering!$C$9,D5=policy_name_clustering!$A$10,policy_name_clustering!$C$10,D5=policy_name_clustering!$A$11,policy_name_clustering!$C$11,D5=policy_name_clustering!$A$12,policy_name_clustering!$C$12,D5="-","")} | G5: =solar_cum_cap!C6 -> 27 | H5: =estimated_capacity!C5 -> 179.5902 | I5: {=_xlfn.IFS(D5= ""," ",D5<> " ",F5*(G5/H5))} -> 0 | J5: {=_xlfn.IFS(D5= ""," ",D5<> " ",(H5-F5)*(G5/H5))} -> 27 | K5: {=IF(ISNUMBER(H5),_xlfn.IFS(D5= ""," ",D5<> " ",F5*(G5/H5)),"")} -> 0
A6: AUT | B6: 2005 | D6: - | E6: {=_xlfn.IFS(D6=policy_name_clustering!$A$2,policy_name_clustering!$C$2,D6=policy_name_clustering!$A$3,policy_name_clustering!$C$3,D6=policy_name_clustering!$A$4,policy_name_clustering!$C$4,D6=policy_name_clustering!$A$5,policy_name_clustering!$C$5,D6=policy_name_clustering!$A$6,policy_name_clustering!$C$6,D6=policy_name_clustering!$A$7,policy_name_clustering!$C$7,D6=policy_name_clustering!$A$8,policy_name_clustering!$C$8,D6=policy_name_clustering!$A$9,policy_name_clustering!$C$9,D6=policy_name_clustering!$A$10,policy_name_clustering!$C$10,D6=policy_name_clustering!$A$11,policy_name_clustering!$C$11,D6=policy_name_clustering!$A$12,policy_name_clustering!$C$12,D6="-","")} | G6: =solar_cum_cap!C7 -> 21.018 | H6: =estimated_capacity!C6 -> 248.19562 | I6: {=_xlfn.IFS(D6= ""," ",D6<> " ",F6*(G6/H6))} -> 0 | J6: {=_xlfn.IFS(D6= ""," ",D6<> " ",(H6-F6)*(G6/H6))} -> 21.018 | K6: {=IF(ISNUMBER(H6),_xlfn.IFS(D6= ""," ",D6<> " ",F6*(G6/H6)),"")} -> 0
A7: AUT | B7: 2006 | D7: - | E7: {=_xlfn.IFS(D7=policy_name_clustering!$A$2,policy_name_clustering!$C$2,D7=policy_name_clustering!$A$3,policy_name_clustering!$C$3,D7=policy_name_clustering!$A$4,policy_name_clustering!$C$4,D7=policy_name_clustering!$A$5,policy_name_clustering!$C$5,D7=policy_name_clustering!$A$6,policy_name_clustering!$C$6,D7=policy_name_clustering!$A$7,policy_name_clustering!$C$7,D7=policy_name_clustering!$A$8,policy_name_clustering!$C$8,D7=policy_name_clustering!$A$9,policy_name_clustering!$C$9,D7=policy_name_clustering!$A$10,policy_name_clustering!$C$10,D7=policy_name_clustering!$A$11,policy_name_clustering!$C$11,D7=policy_name_clustering!$A$12,policy_name_clustering!$C$12,D7="-","")} | G7: =solar_cum_cap!C8 -> 22.387 | H7: =estimated_capacity!C7 -> 322.68046 | I7: {=_xlfn.IFS(D7= ""," ",D7<> " ",F7*(G7/H7))} -> 0 | J7: {=_xlfn.IFS(D7= ""," ",D7<> " ",(H7-F7)*(G7/H7))} -> 22.387 | K7: {=IF(ISNUMBER(H7),_xlfn.IFS(D7= ""," ",D7<> " ",F7*(G7/H7)),"")} -> 0
A8: AUT | B8: 2007 | D8: - | E8: {=_xlfn.IFS(D8=policy_name_clustering!$A$2,policy_name_clustering!$C$2,D8=policy_name_clustering!$A$3,policy_name_clustering!$C$3,D8=policy_name_clustering!$A$4,policy_name_clustering!$C$4,D8=policy_name_clustering!$A$5,policy_name_clustering!$C$5,D8=policy_name_clustering!$A$6,policy_name_clustering!$C$6,D8=policy_name_clustering!$A$7,policy_name_clustering!$C$7,D8=policy_name_clustering!$A$8,policy_name_clustering!$C$8,D8=policy_name_clustering!$A$9,policy_name_clustering!$C$9,D8=policy_name_clustering!$A$10,policy_name_clustering!$C$10,D8=policy_name_clustering!$A$11,policy_name_clustering!$C$11,D8=policy_name_clustering!$A$12,policy_name_clustering!$C$12,D8="-","")} | G8: =solar_cum_cap!C9 -> 24.238 | H8: =estimated_capacity!C8 -> 402.12565 | I8: {=_xlfn.IFS(D8= ""," ",D8<> " ",F8*(G8/H8))} -> 0 | J8: {=_xlfn.IFS(D8= ""," ",D8<> " ",(H8-F8)*(G8/H8))} -> 24.238 | K8: {=IF(ISNUMBER(H8),_xlfn.IFS(D8= ""," ",D8<> " ",F8*(G8/H8)),"")} -> 0
A9: AUT | B9: 2008 | D9: - | E9: {=_xlfn.IFS(D9=policy_name_clustering!$A$2,policy_name_clustering!$C$2,D9=policy_name_clustering!$A$3,policy_name_clustering!$C$3,D9=policy_name_clustering!$A$4,policy_name_clustering!$C$4,D9=policy_name_clustering!$A$5,policy_name_clustering!$C$5,D9=policy_name_clustering!$A$6,policy_name_clustering!$C$6,D9=policy_name_clustering!$A$7,policy_name_clustering!$C$7,D9=policy_name_clustering!$A$8,policy_name_clustering!$C$8,D9=policy_name_clustering!$A$9,policy_name_clustering!$C$9,D9=policy_name_clustering!$A$10,policy_name_clustering!$C$10,D9=policy_name_clustering!$A$11,policy_name_clustering!$C$11,D9=policy_name_clustering!$A$12,policy_name_clustering!$C$12,D9="-","")} | G9: =solar_cum_cap!C10 -> 30.12 | H9: =estimated_capacity!C9 -> 499.52628 | I9: {=_xlfn.IFS(D9= ""," ",D9<> " ",F9*(G9/H9))} -> 0 | J9: {=_xlfn.IFS(D9= ""," ",D9<> " ",(H9-F9)*(G9/H9))} -> 30.12 | K9: {=IF(ISNUMBER(H9),_xlfn.IFS(D9= ""," ",D9<> " ",F9*(G9/H9)),"")} -> 0
A10: AUT | B10: 2009 | D10: - | E10: {=_xlfn.IFS(D10=policy_name_clustering!$A$2,policy_name_clustering!$C$2,D10=policy_name_clustering!$A$3,policy_name_clustering!$C$3,D10=policy_name_clustering!$A$4,policy_name_clustering!$C$4,D10=policy_name_clustering!$A$5,policy_name_clustering!$C$5,D10=policy_name_clustering!$A$6,policy_name_clustering!$C$6,D10=policy_name_clustering!$A$7,policy_name_clustering!$C$7,D10=policy_name_clustering!$A$8,policy_name_clustering!$C$8,D10=policy_name_clustering!$A$9,policy_name_clustering!$C$9,D10=policy_name_clustering!$A$10,policy_name_clustering!$C$10,D10=policy_name_clustering!$A$11,policy_name_clustering!$C$11,D10=policy_name_clustering!$A$12,policy_name_clustering!$C$12,D10="-","")} | G10: =solar_cum_cap!C11 -> 48.915 | H10: =estimated_capacity!C10 -> 601.77341 | I10: {=_xlfn.IFS(D10= ""," ",D10<> " ",F10*(G10/H10))} -> 0 | J10: {=_xlfn.IFS(D10= ""," ",D10<> " ",(H10-F10)*(G10/H10))} -> 48.915 | K10: {=IF(ISNUMBER(H10),_xlfn.IFS(D10= ""," ",D10<> " ",F10*(G10/H10)),"")} -> 0
A11: AUT | B11: 2010 | D11: - | E11: {=_xlfn.IFS(D11=policy_name_clustering!$A$2,policy_name_clustering!$C$2,D11=policy_name_clustering!$A$3,policy_name_clustering!$C$3,D11=policy_name_clustering!$A$4,policy_name_clustering!$C$4,D11=policy_name_clustering!$A$5,policy_name_clustering!$C$5,D11=policy_name_clustering!$A$6,policy_name_clustering!$C$6,D11=policy_name_clustering!$A$7,policy_name_clustering!$C$7,D11=policy_name_clustering!$A$8,policy_name_clustering!$C$8,D11=policy_name_clustering!$A$9,policy_name_clustering!$C$9,D11=policy_name_clustering!$A$10,policy_name_clustering!$C$10,D11=policy_name_clustering!$A$11,policy_name_clustering!$C$11,D11=policy_name_clustering!$A$12,policy_name_clustering!$C$12,D11="-","")} | G11: =solar_cum_cap!C12 -> 88.813 | H11: =estimated_capacity!C11 -> 745.20818 | I11: {=_xlfn.IFS(D11= ""," ",D11<> " ",F11*(G11/H11))} -> 0 | J11: {=_xlfn.IFS(D11= ""," ",D11<> " ",(H11-F11)*(G11/H11))} -> 88.813 | K11: {=IF(ISNUMBER(H11),_xlfn.IFS(D11= ""," ",D11<> " ",F11*(G11/H11)),"")} -> 0
A12: AUT | B12: 2011 | D12: - | E12: {=_xlfn.IFS(D12=policy_name_clustering!$A$2,policy_name_clustering!$C$2,D12=policy_name_clustering!$A$3,policy_name_clustering!$C$3,D12=policy_name_clustering!$A$4,policy_name_clustering!$C$4,D12=policy_name_clustering!$A$5,policy_name_clustering!$C$5,D12=policy_name_clustering!$A$6,policy_name_clustering!$C$6,D12=policy_name_clustering!$A$7,policy_name_clustering!$C$7,D12=policy_name_clustering!$A$8,policy_name_clustering!$C$8,D12=policy_name_clustering!$A$9,policy_name_clustering!$C$9,D12=policy_name_clustering!$A$10,policy_name_clustering!$C$10,D12=policy_name_clustering!$A$11,policy_name_clustering!$C$11,D12=policy_name_clustering!$A$12,policy_name_clustering!$C$12,D12="-","")} | G12: =solar_cum_cap!C13 -> 174.07 | H12: =estimated_capacity!C12 -> 942.06133 | I12: {=_xlfn.IFS(D12= ""," ",D12<> " ",F12*(G12/H12))} -> 0 | J12: {=_xlfn.IFS(D12= ""," ",D12<> " ",(H12-F12)*(G12/H12))} -> 174.07 | K12: {=IF(ISNUMBER(H12),_xlfn.IFS(D12= ""," ",D12<> " ",F12*(G12/H12)),"")} -> 0
A13: AUT | B13: 2012 | D13: - | E13: {=_xlfn.IFS(D13=policy_name_clustering!$A$2,policy_name_clustering!$C$2,D13=policy_name_clustering!$A$3,policy_name_clustering!$C$3,D13=policy_name_clustering!$A$4,policy_name_clustering!$C$4,D13=policy_name_clustering!$A$5,policy_name_clustering!$C$5,D13=policy_name_clustering!$A$6,policy_name_clustering!$C$6,D13=policy_name_clustering!$A$7,policy_name_clustering!$C$7,D13=policy_name_clustering!$A$8,policy_name_clustering!$C$8,D13=policy_name_clustering!$A$9,policy_name_clustering!$C$9,D13=policy_name_clustering!$A$10,policy_name_clustering!$C$10,D13=policy_name_clustering!$A$11,policy_name_clustering!$C$11,D13=policy_name_clustering!$A$12,policy_name_clustering!$C$12,D13="-","")} | G13: =solar_cum_cap!C14 -> 337.483 | H13: =estimated_capacity!C13 -> 1181.3722 | I13: {=_xlfn.IFS(D13= ""," ",D13<> " ",F13*(G13/H13))} -> 0 | J13: {=_xlfn.IFS(D13= ""," ",D13<> " ",(H13-F13)*(G13/H13))} -> 337.483 | K13: {=IF(ISNUMBER(H13),_xlfn.IFS(D13= ""," ",D13<> " ",F13*(G13/H13)),"")} -> 0
... A24: AUT | B24: 2023 | D24: - | E24: {=_xlfn.IFS(D24=policy_name_clustering!$A$2,policy_name_clustering!$C$2,D24=policy_name_clustering!$A$3,policy_name_clustering!$C$3,D24=policy_name_clustering!$A$4,policy_name_clustering!$C$4,D24=policy_name_clustering!$A$5,policy_name_clustering!$C$5,D24=policy_name_clustering!$A$6,policy_name_clustering!$C$6,D24=policy_name_clustering!$A$7,policy_name_clustering!$C$7,D24=policy_name_clustering!$A$8,policy_name_clustering!$C$8,D24=policy_name_clustering!$A$9,policy_name_clustering!$C$9,D24=policy_name_clustering!$A$10,policy_name_clustering!$C$10,D24=policy_name_clustering!$A$11,policy_name_clustering!$C$11,D24=policy_name_clustering!$A$12,policy_name_clustering!$C$12,D24="-","")} | G24: =solar_cum_cap!C25 -> 6394.811 | H24: =estimated_capacity!C24 -> 4802.3446 | I24: {=_xlfn.IFS(D24= ""," ",D24<> " ",F24*(G24/H24))} -> 0 | J24: {=_xlfn.IFS(D24= ""," ",D24<> " ",(H24-F24)*(G24/H24))} -> 6394.811 | K24: {=IF(ISNUMBER(H24),_xlfn.IFS(D24= ""," ",D24<> " ",F24*(G24/H24)),"")} -> 0
A25: BEL | B25: 2001 | D25: - | E25: {=_xlfn.IFS(D25=policy_name_clustering!$A$2,policy_name_clustering!$C$2,D25=policy_name_clustering!$A$3,policy_name_clustering!$C$3,D25=policy_name_clustering!$A$4,policy_name_clustering!$C$4,D25=policy_name_clustering!$A$5,policy_name_clustering!$C$5,D25=policy_name_clustering!$A$6,policy_name_clustering!$C$6,D25=policy_name_clustering!$A$7,policy_name_clustering!$C$7,D25=policy_name_clustering!$A$8,policy_name_clustering!$C$8,D25=policy_name_clustering!$A$9,policy_name_clustering!$C$9,D25=policy_name_clustering!$A$10,policy_name_clustering!$C$10,D25=policy_name_clustering!$A$11,policy_name_clustering!$C$11,D25=policy_name_clustering!$A$12,policy_name_clustering!$C$12,D25="-","")} | G25: =solar_cum_cap!C27 -> 0 | H25: =estimated_capacity!C25 -> 100.10894 | I25: {=_xlfn.IFS(D25= ""," ",D25<> " ",F25*(G25/H25))} -> 0 | J25: {=_xlfn.IFS(D25= ""," ",D25<> " ",(H25-F25)*(G25/H25))} -> 0 | K25: {=IF(ISNUMBER(H25),_xlfn.IFS(D25= ""," ",D25<> " ",F25*(G25/H25)),"")} -> 0
A26: BEL | B26: 2002 | D26: - | E26: {=_xlfn.IFS(D26=policy_name_clustering!$A$2,policy_name_clustering!$C$2,D26=policy_name_clustering!$A$3,policy_name_clustering!$C$3,D26=policy_name_clustering!$A$4,policy_name_clustering!$C$4,D26=policy_name_clustering!$A$5,policy_name_clustering!$C$5,D26=policy_name_clustering!$A$6,policy_name_clustering!$C$6,D26=policy_name_clustering!$A$7,policy_name_clustering!$C$7,D26=policy_name_clustering!$A$8,policy_name_clustering!$C$8,D26=policy_name_clustering!$A$9,policy_name_clustering!$C$9,D26=policy_name_clustering!$A$10,policy_name_clustering!$C$10,D26=policy_name_clustering!$A$11,policy_name_clustering!$C$11,D26=policy_name_clustering!$A$12,policy_name_clustering!$C$12,D26="-","")} | G26: =solar_cum_cap!C28 -> 0 | H26: =estimated_capacity!C26 -> 191.18881 | I26: {=_xlfn.IFS(D26= ""," ",D26<> " ",F26*(G26/H26))} -> 0 | J26: {=_xlfn.IFS(D26= ""," ",D26<> " ",(H26-F26)*(G26/H26))} -> 0 | K26: {=IF(ISNUMBER(H26),_xlfn.IFS(D26= ""," ",D26<> " ",F26*(G26/H26)),"")} -> 0
A27: BEL | B27: 2003 | D27: - | E27: {=_xlfn.IFS(D27=policy_name_clustering!$A$2,policy_name_clustering!$C$2,D27=policy_name_clustering!$A$3,policy_name_clustering!$C$3,D27=policy_name_clustering!$A$4,policy_name_clustering!$C$4,D27=policy_name_clustering!$A$5,policy_name_clustering!$C$5,D27=policy_name_clustering!$A$6,policy_name_clustering!$C$6,D27=policy_name_clustering!$A$7,policy_name_clustering!$C$7,D27=policy_name_clustering!$A$8,policy_name_clustering!$C$8,D27=policy_name_clustering!$A$9,policy_name_clustering!$C$9,D27=policy_name_clustering!$A$10,policy_name_clustering!$C$10,D27=policy_name_clustering!$A$11,policy_name_clustering!$C$11,D27=policy_name_clustering!$A$12,policy_name_clustering!$C$12,D27="-","")} | G27: =solar_cum_cap!C29 -> 0 | H27: =estimated_capacity!C27 -> 301.26271 | I27: {=_xlfn.IFS(D27= ""," ",D27<> " ",F27*(G27/H27))} -> 0 | J27: {=_xlfn.IFS(D27= ""," ",D27<> " ",(H27-F27)*(G27/H27))} -> 0 | K27: {=IF(ISNUMBER(H27),_xlfn.IFS(D27= ""," ",D27<> " ",F27*(G27/H27)),"")} -> 0
A28: BEL | B28: 2004 | D28: - | E28: {=_xlfn.IFS(D28=policy_name_clustering!$A$2,policy_name_clustering!$C$2,D28=policy_name_clustering!$A$3,policy_name_clustering!$C$3,D28=policy_name_clustering!$A$4,policy_name_clustering!$C$4,D28=policy_name_clustering!$A$5,policy_name_clustering!$C$5,D28=policy_name_clustering!$A$6,policy_name_clustering!$C$6,D28=policy_name_clustering!$A$7,policy_name_clustering!$C$7,D28=policy_name_clustering!$A$8,policy_name_clustering!$C$8,D28=policy_name_clustering!$A$9,policy_name_clustering!$C$9,D28=policy_name_clustering!$A$10,policy_name_clustering!$C$10,D28=policy_name_clustering!$A$11,policy_name_clustering!$C$11,D28=policy_name_clustering!$A$12,policy_name_clustering!$C$12,D28="-","")} | G28: =solar_cum_cap!C30 -> 0 | H28: =estimated_capacity!C28 -> 440.65569 | I28: {=_xlfn.IFS(D28= ""," ",D28<> " ",F28*(G28/H28))} -> 0 | J28: {=_xlfn.IFS(D28= ""," ",D28<> " ",(H28-F28)*(G28/H28))} -> 0 | K28: {=IF(ISNUMBER(H28),_xlfn.IFS(D28= ""," ",D28<> " ",F28*(G28/H28)),"")} -> 0
A29: BEL | B29: 2005 | D29: - | E29: {=_xlfn.IFS(D29=policy_name_clustering!$A$2,policy_name_clustering!$C$2,D29=policy_name_clustering!$A$3,policy_name_clustering!$C$3,D29=policy_name_clustering!$A$4,policy_name_clustering!$C$4,D29=policy_name_clustering!$A$5,policy_name_clustering!$C$5,D29=policy_name_clustering!$A$6,policy_name_clustering!$C$6,D29=policy_name_clustering!$A$7,policy_name_clustering!$C$7,D29=policy_name_clustering!$A$8,policy_name_clustering!$C$8,D29=policy_name_clustering!$A$9,policy_name_clustering!$C$9,D29=policy_name_clustering!$A$10,policy_name_clustering!$C$10,D29=policy_name_clustering!$A$11,policy_name_clustering!$C$11,D29=policy_name_clustering!$A$12,policy_name_clustering!$C$12,D29="-","")} | G29: =solar_cum_cap!C31 -> 0 | H29: =estimated_capacity!C29 -> 578.00966 | I29: {=_xlfn.IFS(D29= ""," ",D29<> " ",F29*(G29/H29))} -> 0 | J29: {=_xlfn.IFS(D29= ""," ",D29<> " ",(H29-F29)*(G29/H29))} -> 0 | K29: {=IF(ISNUMBER(H29),_xlfn.IFS(D29= ""," ",D29<> " ",F29*(G29/H29)),"")} -> 0
A30: BEL | B30: 2006 | D30: - | E30: {=_xlfn.IFS(D30=policy_name_clustering!$A$2,policy_name_clustering!$C$2,D30=policy_name_clustering!$A$3,policy_name_clustering!$C$3,D30=policy_name_clustering!$A$4,policy_name_clustering!$C$4,D30=policy_name_clustering!$A$5,policy_name_clustering!$C$5,D30=policy_name_clustering!$A$6,policy_name_clustering!$C$6,D30=policy_name_clustering!$A$7,policy_name_clustering!$C$7,D30=policy_name_clustering!$A$8,policy_name_clustering!$C$8,D30=policy_name_clustering!$A$9,policy_name_clustering!$C$9,D30=policy_name_clustering!$A$10,policy_name_clustering!$C$10,D30=policy_name_clustering!$A$11,policy_name_clustering!$C$11,D30=policy_name_clustering!$A$12,policy_name_clustering!$C$12,D30="-","")} | G30: =solar_cum_cap!C32 -> 0 | H30: =estimated_capacity!C30 -> 721.68252 | I30: {=_xlfn.IFS(D30= ""," ",D30<> " ",F30*(G30/H30))} -> 0 | J30: {=_xlfn.IFS(D30= ""," ",D30<> " ",(H30-F30)*(G30/H30))} -> 0 | K30: {=IF(ISNUMBER(H30),_xlfn.IFS(D30= ""," ",D30<> " ",F30*(G30/H30)),"")} -> 0
A31: BEL | B31: 2007 | D31: - | E31: {=_xlfn.IFS(D31=policy_name_clustering!$A$2,policy_name_clustering!$C$2,D31=policy_name_clustering!$A$3,policy_name_clustering!$C$3,D31=policy_name_clustering!$A$4,policy_name_clustering!$C$4,D31=policy_name_clustering!$A$5,policy_name_clustering!$C$5,D31=policy_name_clustering!$A$6,policy_name_clustering!$C$6,D31=policy_name_clustering!$A$7,policy_name_clustering!$C$7,D31=policy_name_clustering!$A$8,policy_name_clustering!$C$8,D31=policy_name_clustering!$A$9,policy_name_clustering!$C$9,D31=policy_name_clustering!$A$10,policy_name_clustering!$C$10,D31=policy_name_clustering!$A$11,policy_name_clustering!$C$11,D31=policy_name_clustering!$A$12,policy_name_clustering!$C$12,D31="-","")} | G31: =solar_cum_cap!C33 -> 0 | H31: =estimated_capacity!C31 -> 870.92112 | I31: {=_xlfn.IFS(D31= ""," ",D31<> " ",F31*(G31/H31))} -> 0 | J31: {=_xlfn.IFS(D31= ""," ",D31<> " ",(H31-F31)*(G31/H31))} -> 0 | K31: {=IF(ISNUMBER(H31),_xlfn.IFS(D31= ""," ",D31<> " ",F31*(G31/H31)),"")} -> 0
A32: BEL | B32: 2008 | D32: - | E32: {=_xlfn.IFS(D32=policy_name_clustering!$A$2,policy_name_clustering!$C$2,D32=policy_name_clustering!$A$3,policy_name_clustering!$C$3,D32=policy_name_clustering!$A$4,policy_name_clustering!$C$4,D32=policy_name_clustering!$A$5,policy_name_clustering!$C$5,D32=policy_name_clustering!$A$6,policy_name_clustering!$C$6,D32=policy_name_clustering!$A$7,policy_name_clustering!$C$7,D32=policy_name_clustering!$A$8,policy_name_clustering!$C$8,D32=policy_name_clustering!$A$9,policy_name_clustering!$C$9,D32=policy_name_clustering!$A$10,policy_name_clustering!$C$10,D32=policy_name_clustering!$A$11,policy_name_clustering!$C$11,D32=policy_name_clustering!$A$12,policy_name_clustering!$C$12,D32="-","")} | G32: =solar_cum_cap!C34 -> 0 | H32: =estimated_capacity!C32 -> 1040.3624 | I32: {=_xlfn.IFS(D32= ""," ",D32<> " ",F32*(G32/H32))} -> 0 | J32: {=_xlfn.IFS(D32= ""," ",D32<> " ",(H32-F32)*(G32/H32))} -> 0 | K32: {=IF(ISNUMBER(H32),_xlfn.IFS(D32= ""," ",D32<> " ",F32*(G32/H32)),"")} -> 0
A33: BEL | B33: 2009 | D33: - | E33: {=_xlfn.IFS(D33=policy_name_clustering!$A$2,policy_name_clustering!$C$2,D33=policy_name_clustering!$A$3,policy_name_clustering!$C$3,D33=policy_name_clustering!$A$4,policy_name_clustering!$C$4,D33=policy_name_clustering!$A$5,policy_name_clustering!$C$5,D33=policy_name_clustering!$A$6,policy_name_clustering!$C$6,D33=policy_name_clustering!$A$7,policy_name_clustering!$C$7,D33=policy_name_clustering!$A$8,policy_name_clustering!$C$8,D33=policy_name_clustering!$A$9,policy_name_clustering!$C$9,D33=policy_name_clustering!$A$10,policy_name_clustering!$C$10,D33=policy_name_clustering!$A$11,policy_name_clustering!$C$11,D33=policy_name_clustering!$A$12,policy_name_clustering!$C$12,D33="-","")} | G33: =solar_cum_cap!C35 -> 386 | H33: =estimated_capacity!C33 -> 1216.2788 | I33: {=_xlfn.IFS(D33= ""," ",D33<> " ",F33*(G33/H33))} -> 0 | J33: {=_xlfn.IFS(D33= ""," ",D33<> " ",(H33-F33)*(G33/H33))} -> 386 | K33: {=IF(ISNUMBER(H33),_xlfn.IFS(D33= ""," ",D33<> " ",F33*(G33/H33)),"")} -> 0
A34: BEL | B34: 2010 | D34: - | E34: {=_xlfn.IFS(D34=policy_name_clustering!$A$2,policy_name_clustering!$C$2,D34=policy_name_clustering!$A$3,policy_name_clustering!$C$3,D34=policy_name_clustering!$A$4,policy_name_clustering!$C$4,D34=policy_name_clustering!$A$5,policy_name_clustering!$C$5,D34=policy_name_clustering!$A$6,policy_name_clustering!$C$6,D34=policy_name_clustering!$A$7,policy_name_clustering!$C$7,D34=policy_name_clustering!$A$8,policy_name_clustering!$C$8,D34=policy_name_clustering!$A$9,policy_name_clustering!$C$9,D34=policy_name_clustering!$A$10,policy_name_clustering!$C$10,D34=policy_name_clustering!$A$11,policy_name_clustering!$C$11,D34=policy_name_clustering!$A$12,policy_name_clustering!$C$12,D34="-","")} | G34: =solar_cum_cap!C36 -> 840.2 | H34: =estimated_capacity!C34 -> 1452.2801 | I34: {=_xlfn.IFS(D34= ""," ",D34<> " ",F34*(G34/H34))} -> 0 | J34: {=_xlfn.IFS(D34= ""," ",D34<> " ",(H34-F34)*(G34/H34))} -> 840.2 | K34: {=IF(ISNUMBER(H34),_xlfn.IFS(D34= ""," ",D34<> " ",F34*(G34/H34)),"")} -> 0
A35: BEL | B35: 2011 | D35: - | E35: {=_xlfn.IFS(D35=policy_name_clustering!$A$2,policy_name_clustering!$C$2,D35=policy_name_clustering!$A$3,policy_name_clustering!$C$3,D35=policy_name_clustering!$A$4,policy_name_clustering!$C$4,D35=policy_name_clustering!$A$5,policy_name_clustering!$C$5,D35=policy_name_clustering!$A$6,policy_name_clustering!$C$6,D35=policy_name_clustering!$A$7,policy_name_clustering!$C$7,D35=policy_name_clustering!$A$8,policy_name_clustering!$C$8,D35=policy_name_clustering!$A$9,policy_name_clustering!$C$9,D35=policy_name_clustering!$A$10,policy_name_clustering!$C$10,D35=policy_name_clustering!$A$11,policy_name_clustering!$C$11,D35=policy_name_clustering!$A$12,policy_name_clustering!$C$12,D35="-","")} | G35: =solar_cum_cap!C37 -> 1864.9 | H35: =estimated_capacity!C35 -> 1774.0201 | I35: {=_xlfn.IFS(D35= ""," ",D35<> " ",F35*(G35/H35))} -> 0 | J35: {=_xlfn.IFS(D35= ""," ",D35<> " ",(H35-F35)*(G35/H35))} -> 1864.9 | K35: {=IF(ISNUMBER(H35),_xlfn.IFS(D35= ""," ",D35<> " ",F35*(G35/H35)),"")} -> 0
A36: BEL | B36: 2012 | D36: - | E36: {=_xlfn.IFS(D36=policy_name_clustering!$A$2,policy_name_clustering!$C$2,D36=policy_name_clustering!$A$3,policy_name_clustering!$C$3,D36=policy_name_clustering!$A$4,policy_name_clustering!$C$4,D36=policy_name_clustering!$A$5,policy_name_clustering!$C$5,D36=policy_name_clustering!$A$6,policy_name_clustering!$C$6,D36=policy_name_clustering!$A$7,policy_name_clustering!$C$7,D36=policy_name_clustering!$A$8,policy_name_clustering!$C$8,D36=policy_name_clustering!$A$9,policy_name_clustering!$C$9,D36=policy_name_clustering!$A$10,policy_name_clustering!$C$10,D36=policy_name_clustering!$A$11,policy_name_clustering!$C$11,D36=policy_name_clustering!$A$12,policy_name_clustering!$C$12,D36="-","")} | G36: =solar_cum_cap!C38 -> 2595.5 | H36: =estimated_capacity!C36 -> 2141.7769 | I36: {=_xlfn.IFS(D36= ""," ",D36<> " ",F36*(G36/H36))} -> 0 | J36: {=_xlfn.IFS(D36= ""," ",D36<> " ",(H36-F36)*(G36/H36))} -> 2595.5 | K36: {=IF(ISNUMBER(H36),_xlfn.IFS(D36= ""," ",D36<> " ",F36*(G36/H36)),"")} -> 0
... A47: BEL | B47: 2023 | D47: - | E47: {=_xlfn.IFS(D47=policy_name_clustering!$A$2,policy_name_clustering!$C$2,D47=policy_name_clustering!$A$3,policy_name_clustering!$C$3,D47=policy_name_clustering!$A$4,policy_name_clustering!$C$4,D47=policy_name_clustering!$A$5,policy_name_clustering!$C$5,D47=policy_name_clustering!$A$6,policy_name_clustering!$C$6,D47=policy_name_clustering!$A$7,policy_name_clustering!$C$7,D47=policy_name_clustering!$A$8,policy_name_clustering!$C$8,D47=policy_name_clustering!$A$9,policy_name_clustering!$C$9,D47=policy_name_clustering!$A$10,policy_name_clustering!$C$10,D47=policy_name_clustering!$A$11,policy_name_clustering!$C$11,D47=policy_name_clustering!$A$12,policy_name_clustering!$C$12,D47="-","")} | G47: =solar_cum_cap!C49 -> 8351.9 | H47: =estimated_capacity!C47 -> 7158.506 | I47: {=_xlfn.IFS(D47= ""," ",D47<> " ",F47*(G47/H47))} -> 0 | J47: {=_xlfn.IFS(D47= ""," ",D47<> " ",(H47-F47)*(G47/H47))} -> 8351.9 | K47: {=IF(ISNUMBER(H47),_xlfn.IFS(D47= ""," ",D47<> " ",F47*(G47/H47)),"")} -> 0
A48: BGR | B48: 2003 | D48: - | E48: {=_xlfn.IFS(D48=policy_name_clustering!$A$2,policy_name_clustering!$C$2,D48=policy_name_clustering!$A$3,policy_name_clustering!$C$3,D48=policy_name_clustering!$A$4,policy_name_clustering!$C$4,D48=policy_name_clustering!$A$5,policy_name_clustering!$C$5,D48=policy_name_clustering!$A$6,policy_name_clustering!$C$6,D48=policy_name_clustering!$A$7,policy_name_clustering!$C$7,D48=policy_name_clustering!$A$8,policy_name_clustering!$C$8,D48=policy_name_clustering!$A$9,policy_name_clustering!$C$9,D48=policy_name_clustering!$A$10,policy_name_clustering!$C$10,D48=policy_name_clustering!$A$11,policy_name_clustering!$C$11,D48=policy_name_clustering!$A$12,policy_name_clustering!$C$12,D48="-","")} | G48: =solar_cum_cap!C51 -> 0 | H48: =estimated_capacity!C48 -> -32.808115 | I48: {=_xlfn.IFS(D48= ""," ",D48<> " ",F48*(G48/H48))} -> 0 | J48: {=_xlfn.IFS(D48= ""," ",D48<> " ",(H48-F48)*(G48/H48))} -> 0 | K48: {=IF(ISNUMBER(H48),_xlfn.IFS(D48= ""," ",D48<> " ",F48*(G48/H48)),"")} -> 0
A49: BGR | B49: 2004 | D49: - | E49: {=_xlfn.IFS(D49=policy_name_clustering!$A$2,policy_name_clustering!$C$2,D49=policy_name_clustering!$A$3,policy_name_clustering!$C$3,D49=policy_name_clustering!$A$4,policy_name_clustering!$C$4,D49=policy_name_clustering!$A$5,policy_name_clustering!$C$5,D49=policy_name_clustering!$A$6,policy_name_clustering!$C$6,D49=policy_name_clustering!$A$7,policy_name_clustering!$C$7,D49=policy_name_clustering!$A$8,policy_name_clustering!$C$8,D49=policy_name_clustering!$A$9,policy_name_clustering!$C$9,D49=policy_name_clustering!$A$10,policy_name_clustering!$C$10,D49=policy_name_clustering!$A$11,policy_name_clustering!$C$11,D49=policy_name_clustering!$A$12,policy_name_clustering!$C$12,D49="-","")} | G49: =solar_cum_cap!C52 -> 0 | H49: =estimated_capacity!C49 -> -59.422986 | I49: {=_xlfn.IFS(D49= ""," ",D49<> " ",F49*(G49/H49))} -> 0 | J49: {=_xlfn.IFS(D49= ""," ",D49<> " ",(H49-F49)*(G49/H49))} -> 0 | K49: {=IF(ISNUMBER(H49),_xlfn.IFS(D49= ""," ",D49<> " ",F49*(G49/H49)),"")} -> 0
A50: BGR | B50: 2005 | D50: - | E50: {=_xlfn.IFS(D50=policy_name_clustering!$A$2,policy_name_clustering!$C$2,D50=policy_name_clustering!$A$3,policy_name_clustering!$C$3,D50=policy_name_clustering!$A$4,policy_name_clustering!$C$4,D50=policy_name_clustering!$A$5,policy_name_clustering!$C$5,D50=policy_name_clustering!$A$6,policy_name_clustering!$C$6,D50=policy_name_clustering!$A$7,policy_name_clustering!$C$7,D50=policy_name_clustering!$A$8,policy_name_clustering!$C$8,D50=policy_name_clustering!$A$9,policy_name_clustering!$C$9,D50=policy_name_clustering!$A$10,policy_name_clustering!$C$10,D50=policy_name_clustering!$A$11,policy_name_clustering!$C$11,D50=policy_name_clustering!$A$12,policy_name_clustering!$C$12,D50="-","")} | G50: =solar_cum_cap!C53 -> 0 | H50: =estimated_capacity!C50 -> -94.260044 | I50: {=_xlfn.IFS(D50= ""," ",D50<> " ",F50*(G50/H50))} -> 0 | J50: {=_xlfn.IFS(D50= ""," ",D50<> " ",(H50-F50)*(G50/H50))} -> 0 | K50: {=IF(ISNUMBER(H50),_xlfn.IFS(D50= ""," ",D50<> " ",F50*(G50/H50)),"")} -> 0
A51: BGR | B51: 2006 | D51: - | E51: {=_xlfn.IFS(D51=policy_name_clustering!$A$2,policy_name_clustering!$C$2,D51=policy_name_clustering!$A$3,policy_name_clustering!$C$3,D51=policy_name_clustering!$A$4,policy_name_clustering!$C$4,D51=policy_name_clustering!$A$5,policy_name_clustering!$C$5,D51=policy_name_clustering!$A$6,policy_name_clustering!$C$6,D51=policy_name_clustering!$A$7,policy_name_clustering!$C$7,D51=policy_name_clustering!$A$8,policy_name_clustering!$C$8,D51=policy_name_clustering!$A$9,policy_name_clustering!$C$9,D51=policy_name_clustering!$A$10,policy_name_clustering!$C$10,D51=policy_name_clustering!$A$11,policy_name_clustering!$C$11,D51=policy_name_clustering!$A$12,policy_name_clustering!$C$12,D51="-","")} | G51: =solar_cum_cap!C54 -> 0 | H51: =estimated_capacity!C51 -> -125.53581 | I51: {=_xlfn.IFS(D51= ""," ",D51<> " ",F51*(G51/H51))} -> 0 | J51: {=_xlfn.IFS(D51= ""," ",D51<> " ",(H51-F51)*(G51/H51))} -> 0 | K51: {=IF(ISNUMBER(H51),_xlfn.IFS(D51= ""," ",D51<> " ",F51*(G51/H51)),"")} -> 0
A52: BGR | B52: 2007 | D52: - | E52: {=_xlfn.IFS(D52=policy_name_clustering!$A$2,policy_name_clustering!$C$2,D52=policy_name_clustering!$A$3,policy_name_clustering!$C$3,D52=policy_name_clustering!$A$4,policy_name_clustering!$C$4,D52=policy_name_clustering!$A$5,policy_name_clustering!$C$5,D52=policy_name_clustering!$A$6,policy_name_clustering!$C$6,D52=policy_name_clustering!$A$7,policy_name_clustering!$C$7,D52=policy_name_clustering!$A$8,policy_name_clustering!$C$8,D52=policy_name_clustering!$A$9,policy_name_clustering!$C$9,D52=policy_name_clustering!$A$10,policy_name_clustering!$C$10,D52=policy_name_clustering!$A$11,policy_name_clustering!$C$11,D52=policy_name_clustering!$A$12,policy_name_clustering!$C$12,D52="-","")} | G52: =solar_cum_cap!C55 -> 0 | H52: =estimated_capacity!C52 -> -155.56036 | I52: {=_xlfn.IFS(D52= ""," ",D52<> " ",F52*(G52/H52))} -> 0 | J52: {=_xlfn.IFS(D52= ""," ",D52<> " ",(H52-F52)*(G52/H52))} -> 0 | K52: {=IF(ISNUMBER(H52),_xlfn.IFS(D52= ""," ",D52<> " ",F52*(G52/H52)),"")} -> 0
A53: BGR | B53: 2008 | D53: - | E53: {=_xlfn.IFS(D53=policy_name_clustering!$A$2,policy_name_clustering!$C$2,D53=policy_name_clustering!$A$3,policy_name_clustering!$C$3,D53=policy_name_clustering!$A$4,policy_name_clustering!$C$4,D53=policy_name_clustering!$A$5,policy_name_clustering!$C$5,D53=policy_name_clustering!$A$6,policy_name_clustering!$C$6,D53=policy_name_clustering!$A$7,policy_name_clustering!$C$7,D53=policy_name_clustering!$A$8,policy_name_clustering!$C$8,D53=policy_name_clustering!$A$9,policy_name_clustering!$C$9,D53=policy_name_clustering!$A$10,policy_name_clustering!$C$10,D53=policy_name_clustering!$A$11,policy_name_clustering!$C$11,D53=policy_name_clustering!$A$12,policy_name_clustering!$C$12,D53="-","")} | G53: =solar_cum_cap!C56 -> 0 | H53: =estimated_capacity!C53 -> -157.72615 | I53: {=_xlfn.IFS(D53= ""," ",D53<> " ",F53*(G53/H53))} -> 0 | J53: {=_xlfn.IFS(D53= ""," ",D53<> " ",(H53-F53)*(G53/H53))} -> 0 | K53: {=IF(ISNUMBER(H53),_xlfn.IFS(D53= ""," ",D53<> " ",F53*(G53/H53)),"")} -> 0
A54: BGR | B54: 2009 | D54: - | E54: {=_xlfn.IFS(D54=policy_name_clustering!$A$2,policy_name_clustering!$C$2,D54=policy_name_clustering!$A$3,policy_name_clustering!$C$3,D54=policy_name_clustering!$A$4,policy_name_clustering!$C$4,D54=policy_name_clustering!$A$5,policy_name_clustering!$C$5,D54=policy_name_clustering!$A$6,policy_name_clustering!$C$6,D54=policy_name_clustering!$A$7,policy_name_clustering!$C$7,D54=policy_name_clustering!$A$8,policy_name_clustering!$C$8,D54=policy_name_clustering!$A$9,policy_name_clustering!$C$9,D54=policy_name_clustering!$A$10,policy_name_clustering!$C$10,D54=policy_name_clustering!$A$11,policy_name_clustering!$C$11,D54=policy_name_clustering!$A$12,policy_name_clustering!$C$12,D54="-","")} | G54: =solar_cum_cap!C57 -> 2 | H54: =estimated_capacity!C54 -> -119.26938 | I54: {=_xlfn.IFS(D54= ""," ",D54<> " ",F54*(G54/H54))} -> 0 | J54: {=_xlfn.IFS(D54= ""," ",D54<> " ",(H54-F54)*(G54/H54))} -> 2 | K54: {=IF(ISNUMBER(H54),_xlfn.IFS(D54= ""," ",D54<> " ",F54*(G54/H54)),"")} -> 0
A55: BGR | B55: 2010 | D55: - | E55: {=_xlfn.IFS(D55=policy_name_clustering!$A$2,policy_name_clustering!$C$2,D55=policy_name_clustering!$A$3,policy_name_clustering!$C$3,D55=policy_name_clustering!$A$4,policy_name_clustering!$C$4,D55=policy_name_clustering!$A$5,policy_name_clustering!$C$5,D55=policy_name_clustering!$A$6,policy_name_clustering!$C$6,D55=policy_name_clustering!$A$7,policy_name_clustering!$C$7,D55=policy_name_clustering!$A$8,policy_name_clustering!$C$8,D55=policy_name_clustering!$A$9,policy_name_clustering!$C$9,D55=policy_name_clustering!$A$10,policy_name_clustering!$C$10,D55=policy_name_clustering!$A$11,policy_name_clustering!$C$11,D55=policy_name_clustering!$A$12,policy_name_clustering!$C$12,D55="-","")} | G55: =solar_cum_cap!C58 -> 25 | H55: =estimated_capacity!C55 -> -46.850379 | I55: {=_xlfn.IFS(D55= ""," ",D55<> " ",F55*(G55/H55))} -> 0 | J55: {=_xlfn.IFS(D55= ""," ",D55<> " ",(H55-F55)*(G55/H55))} -> 25 | K55: {=IF(ISNUMBER(H55),_xlfn.IFS(D55= ""," ",D55<> " ",F55*(G55/H55)),"")} -> 0
A56: BGR | B56: 2011 | D56: - | E56: {=_xlfn.IFS(D56=policy_name_clustering!$A$2,policy_name_clustering!$C$2,D56=policy_name_clustering!$A$3,policy_name_clustering!$C$3,D56=policy_name_clustering!$A$4,policy_name_clustering!$C$4,D56=policy_name_clustering!$A$5,policy_name_clustering!$C$5,D56=policy_name_clustering!$A$6,policy_name_clustering!$C$6,D56=policy_name_clustering!$A$7,policy_name_clustering!$C$7,D56=policy_name_clustering!$A$8,policy_name_clustering!$C$8,D56=policy_name_clustering!$A$9,policy_name_clustering!$C$9,D56=policy_name_clustering!$A$10,policy_name_clustering!$C$10,D56=policy_name_clustering!$A$11,policy_name_clustering!$C$11,D56=policy_name_clustering!$A$12,policy_name_clustering!$C$12,D56="-","")} | G56: =solar_cum_cap!C59 -> 154 | H56: =estimated_capacity!C56 -> 55.785768 | I56: {=_xlfn.IFS(D56= ""," ",D56<> " ",F56*(G56/H56))} -> 0 | J56: {=_xlfn.IFS(D56= ""," ",D56<> " ",(H56-F56)*(G56/H56))} -> 154 | K56: {=IF(ISNUMBER(H56),_xlfn.IFS(D56= ""," ",D56<> " ",F56*(G56/H56)),"")} -> 0
A57: BGR | B57: 2012 | D57: - | E57: {=_xlfn.IFS(D57=policy_name_clustering!$A$2,policy_name_clustering!$C$2,D57=policy_name_clustering!$A$3,policy_name_clustering!$C$3,D57=policy_name_clustering!$A$4,policy_name_clustering!$C$4,D57=policy_name_clustering!$A$5,policy_name_clustering!$C$5,D57=policy_name_clustering!$A$6,policy_name_clustering!$C$6,D57=policy_name_clustering!$A$7,policy_name_clustering!$C$7,D57=policy_name_clustering!$A$8,policy_name_clustering!$C$8,D57=policy_name_clustering!$A$9,policy_name_clustering!$C$9,D57=policy_name_clustering!$A$10,policy_name_clustering!$C$10,D57=policy_name_clustering!$A$11,policy_name_clustering!$C$11,D57=policy_name_clustering!$A$12,policy_name_clustering!$C$12,D57="-","")} | G57: =solar_cum_cap!C60 -> 921.987 | H57: =estimated_capacity!C57 -> 204.26346 | I57: {=_xlfn.IFS(D57= ""," ",D57<> " ",F57*(G57/H57))} -> 0 | J57: {=_xlfn.IFS(D57= ""," ",D57<> " ",(H57-F57)*(G57/H57))} -> 921.987 | K57: {=IF(ISNUMBER(H57),_xlfn.IFS(D57= ""," ",D57<> " ",F57*(G57/H57)),"")} -> 0
A58: BGR | B58: 2013 | D58: - | E58: {=_xlfn.IFS(D58=policy_name_clustering!$A$2,policy_name_clustering!$C$2,D58=policy_name_clustering!$A$3,policy_name_clustering!$C$3,D58=policy_name_clustering!$A$4,policy_name_clustering!$C$4,D58=policy_name_clustering!$A$5,policy_name_clustering!$C$5,D58=policy_name_clustering!$A$6,policy_name_clustering!$C$6,D58=policy_name_clustering!$A$7,policy_name_clustering!$C$7,D58=policy_name_clustering!$A$8,policy_name_clustering!$C$8,D58=policy_name_clustering!$A$9,policy_name_clustering!$C$9,D58=policy_name_clustering!$A$10,policy_name_clustering!$C$10,D58=policy_name_clustering!$A$11,policy_name_clustering!$C$11,D58=policy_name_clustering!$A$12,policy_name_clustering!$C$12,D58="-","")} | G58: =solar_cum_cap!C61 -> 1038.535 | H58: =estimated_capacity!C58 -> 388.39182 | I58: {=_xlfn.IFS(D58= ""," ",D58<> " ",F58*(G58/H58))} -> 0 | J58: {=_xlfn.IFS(D58= ""," ",D58<> " ",(H58-F58)*(G58/H58))} -> 1038.535 | K58: {=IF(ISNUMBER(H58),_xlfn.IFS(D58= ""," ",D58<> " ",F58*(G58/H58)),"")} -> 0
A59: BGR | B59: 2014 | D59: - | E59: {=_xlfn.IFS(D59=policy_name_clustering!$A$2,policy_name_clustering!$C$2,D59=policy_name_clustering!$A$3,policy_name_clustering!$C$3,D59=policy_name_clustering!$A$4,policy_name_clustering!$C$4,D59=policy_name_clustering!$A$5,policy_name_clustering!$C$5,D59=policy_name_clustering!$A$6,policy_name_clustering!$C$6,D59=policy_name_clustering!$A$7,policy_name_clustering!$C$7,D59=policy_name_clustering!$A$8,policy_name_clustering!$C$8,D59=policy_name_clustering!$A$9,policy_name_clustering!$C$9,D59=policy_name_clustering!$A$10,policy_name_clustering!$C$10,D59=policy_name_clustering!$A$11,policy_name_clustering!$C$11,D59=policy_name_clustering!$A$12,policy_name_clustering!$C$12,D59="-","")} | G59: =solar_cum_cap!C62 -> 1028.917 | H59: =estimated_capacity!C59 -> 609.73284 | I59: {=_xlfn.IFS(D59= ""," ",D59<> " ",F59*(G59/H59))} -> 0 | J59: {=_xlfn.IFS(D59= ""," ",D59<> " ",(H59-F59)*(G59/H59))} -> 1028.917 | K59: {=IF(ISNUMBER(H59),_xlfn.IFS(D59= ""," ",D59<> " ",F59*(G59/H59)),"")} -> 0
... A68: BGR | B68: 2023 | D68: - | E68: {=_xlfn.IFS(D68=policy_name_clustering!$A$2,policy_name_clustering!$C$2,D68=policy_name_clustering!$A$3,policy_name_clustering!$C$3,D68=policy_name_clustering!$A$4,policy_name_clustering!$C$4,D68=policy_name_clustering!$A$5,policy_name_clustering!$C$5,D68=policy_name_clustering!$A$6,policy_name_clustering!$C$6,D68=policy_name_clustering!$A$7,policy_name_clustering!$C$7,D68=policy_name_clustering!$A$8,policy_name_clustering!$C$8,D68=policy_name_clustering!$A$9,policy_name_clustering!$C$9,D68=policy_name_clustering!$A$10,policy_name_clustering!$C$10,D68=policy_name_clustering!$A$11,policy_name_clustering!$C$11,D68=policy_name_clustering!$A$12,policy_name_clustering!$C$12,D68="-","")} | G68: =solar_cum_cap!C71 -> 2908.127 | H68: =estimated_capacity!C68 -> 2507.3816 | I68: {=_xlfn.IFS(D68= ""," ",D68<> " ",F68*(G68/H68))} -> 0 | J68: {=_xlfn.IFS(D68= ""," ",D68<> " ",(H68-F68)*(G68/H68))} -> 2908.127 | K68: {=IF(ISNUMBER(H68),_xlfn.IFS(D68= ""," ",D68<> " ",F68*(G68/H68)),"")} -> 0
A69: CZE | B69: 2002 | D69: - | E69: {=_xlfn.IFS(D69=policy_name_clustering!$A$2,policy_name_clustering!$C$2,D69=policy_name_clustering!$A$3,policy_name_clustering!$C$3,D69=policy_name_clustering!$A$4,policy_name_clustering!$C$4,D69=policy_name_clustering!$A$5,policy_name_clustering!$C$5,D69=policy_name_clustering!$A$6,policy_name_clustering!$C$6,D69=policy_name_clustering!$A$7,policy_name_clustering!$C$7,D69=policy_name_clustering!$A$8,policy_name_clustering!$C$8,D69=policy_name_clustering!$A$9,policy_name_clustering!$C$9,D69=policy_name_clustering!$A$10,policy_name_clustering!$C$10,D69=policy_name_clustering!$A$11,policy_name_clustering!$C$11,D69=policy_name_clustering!$A$12,policy_name_clustering!$C$12,D69="-","")} | G69: =solar_cum_cap!C73 -> 0.155 | H69: =estimated_capacity!C69 -> 53.374632 | I69: {=_xlfn.IFS(D69= ""," ",D69<> " ",F69*(G69/H69))} -> 0 | J69: {=_xlfn.IFS(D69= ""," ",D69<> " ",(H69-F69)*(G69/H69))} -> 0.155 | K69: {=IF(ISNUMBER(H69),_xlfn.IFS(D69= ""," ",D69<> " ",F69*(G69/H69)),"")} -> 0
A70: CZE | B70: 2003 | D70: - | E70: {=_xlfn.IFS(D70=policy_name_clustering!$A$2,policy_name_clustering!$C$2,D70=policy_name_clustering!$A$3,policy_name_clustering!$C$3,D70=policy_name_clustering!$A$4,policy_name_clustering!$C$4,D70=policy_name_clustering!$A$5,policy_name_clustering!$C$5,D70=policy_name_clustering!$A$6,policy_name_clustering!$C$6,D70=policy_name_clustering!$A$7,policy_name_clustering!$C$7,D70=policy_name_clustering!$A$8,policy_name_clustering!$C$8,D70=policy_name_clustering!$A$9,policy_name_clustering!$C$9,D70=policy_name_clustering!$A$10,policy_name_clustering!$C$10,D70=policy_name_clustering!$A$11,policy_name_clustering!$C$11,D70=policy_name_clustering!$A$12,policy_name_clustering!$C$12,D70="-","")} | G70: =solar_cum_cap!C74 -> 0.289 | H70: =estimated_capacity!C70 -> 125.14833 | I70: {=_xlfn.IFS(D70= ""," ",D70<> " ",F70*(G70/H70))} -> 0 | J70: {=_xlfn.IFS(D70= ""," ",D70<> " ",(H70-F70)*(G70/H70))} -> 0.289 | K70: {=IF(ISNUMBER(H70),_xlfn.IFS(D70= ""," ",D70<> " ",F70*(G70/H70)),"")} -> 0
A71: CZE | B71: 2004 | D71: - | E71: {=_xlfn.IFS(D71=policy_name_clustering!$A$2,policy_name_clustering!$C$2,D71=policy_name_clustering!$A$3,policy_name_clustering!$C$3,D71=policy_name_clustering!$A$4,policy_name_clustering!$C$4,D71=policy_name_clustering!$A$5,policy_name_clustering!$C$5,D71=policy_name_clustering!$A$6,policy_name_clustering!$C$6,D71=policy_name_clustering!$A$7,policy_name_clustering!$C$7,D71=policy_name_clustering!$A$8,policy_name_clustering!$C$8,D71=policy_name_clustering!$A$9,policy_name_clustering!$C$9,D71=policy_name_clustering!$A$10,policy_name_clustering!$C$10,D71=policy_name_clustering!$A$11,policy_name_clustering!$C$11,D71=policy_name_clustering!$A$12,policy_name_clustering!$C$12,D71="-","")} | G71: =solar_cum_cap!C75 -> 0.413 | H71: =estimated_capacity!C71 -> 241.32567 | I71: {=_xlfn.IFS(D71= ""," ",D71<> " ",F71*(G71/H71))} -> 0 | J71: {=_xlfn.IFS(D71= ""," ",D71<> " ",(H71-F71)*(G71/H71))} -> 0.413 | K71: {=IF(ISNUMBER(H71),_xlfn.IFS(D71= ""," ",D71<> " ",F71*(G71/H71)),"")} -> 0
A72: CZE | B72: 2005 | D72: - | E72: {=_xlfn.IFS(D72=policy_name_clustering!$A$2,policy_name_clustering!$C$2,D72=policy_name_clustering!$A$3,policy_name_clustering!$C$3,D72=policy_name_clustering!$A$4,policy_name_clustering!$C$4,D72=policy_name_clustering!$A$5,policy_name_clustering!$C$5,D72=policy_name_clustering!$A$6,policy_name_clustering!$C$6,D72=policy_name_clustering!$A$7,policy_name_clustering!$C$7,D72=policy_name_clustering!$A$8,policy_name_clustering!$C$8,D72=policy_name_clustering!$A$9,policy_name_clustering!$C$9,D72=policy_name_clustering!$A$10,policy_name_clustering!$C$10,D72=policy_name_clustering!$A$11,policy_name_clustering!$C$11,D72=policy_name_clustering!$A$12,policy_name_clustering!$C$12,D72="-","")} | G72: =solar_cum_cap!C76 -> 0.586 | H72: =estimated_capacity!C72 -> 346.51777 | I72: {=_xlfn.IFS(D72= ""," ",D72<> " ",F72*(G72/H72))} -> 0 | J72: {=_xlfn.IFS(D72= ""," ",D72<> " ",(H72-F72)*(G72/H72))} -> 0.586 | K72: {=IF(ISNUMBER(H72),_xlfn.IFS(D72= ""," ",D72<> " ",F72*(G72/H72)),"")} -> 0
A73: CZE | B73: 2006 | D73: - | E73: {=_xlfn.IFS(D73=policy_name_clustering!$A$2,policy_name_clustering!$C$2,D73=policy_name_clustering!$A$3,policy_name_clustering!$C$3,D73=policy_name_clustering!$A$4,policy_name_clustering!$C$4,D73=policy_name_clustering!$A$5,policy_name_clustering!$C$5,D73=policy_name_clustering!$A$6,policy_name_clustering!$C$6,D73=policy_name_clustering!$A$7,policy_name_clustering!$C$7,D73=policy_name_clustering!$A$8,policy_name_clustering!$C$8,D73=policy_name_clustering!$A$9,policy_name_clustering!$C$9,D73=policy_name_clustering!$A$10,policy_name_clustering!$C$10,D73=policy_name_clustering!$A$11,policy_name_clustering!$C$11,D73=policy_name_clustering!$A$12,policy_name_clustering!$C$12,D73="-","")} | G73: =solar_cum_cap!C77 -> 0.841 | H73: =estimated_capacity!C73 -> 457.06874 | I73: {=_xlfn.IFS(D73= ""," ",D73<> " ",F73*(G73/H73))} -> 0 | J73: {=_xlfn.IFS(D73= ""," ",D73<> " ",(H73-F73)*(G73/H73))} -> 0.841 | K73: {=IF(ISNUMBER(H73),_xlfn.IFS(D73= ""," ",D73<> " ",F73*(G73/H73)),"")} -> 0
A74: CZE | B74: 2007 | D74: - | E74: {=_xlfn.IFS(D74=policy_name_clustering!$A$2,policy_name_clustering!$C$2,D74=policy_name_clustering!$A$3,policy_name_clustering!$C$3,D74=policy_name_clustering!$A$4,policy_name_clustering!$C$4,D74=policy_name_clustering!$A$5,policy_name_clustering!$C$5,D74=policy_name_clustering!$A$6,policy_name_clustering!$C$6,D74=policy_name_clustering!$A$7,policy_name_clustering!$C$7,D74=policy_name_clustering!$A$8,policy_name_clustering!$C$8,D74=policy_name_clustering!$A$9,policy_name_clustering!$C$9,D74=policy_name_clustering!$A$10,policy_name_clustering!$C$10,D74=policy_name_clustering!$A$11,policy_name_clustering!$C$11,D74=policy_name_clustering!$A$12,policy_name_clustering!$C$12,D74="-","")} | G74: =solar_cum_cap!C78 -> 3.961 | H74: =estimated_capacity!C74 -> 573.86536 | I74: {=_xlfn.IFS(D74= ""," ",D74<> " ",F74*(G74/H74))} -> 0 | J74: {=_xlfn.IFS(D74= ""," ",D74<> " ",(H74-F74)*(G74/H74))} -> 3.961 | K74: {=IF(ISNUMBER(H74),_xlfn.IFS(D74= ""," ",D74<> " ",F74*(G74/H74)),"")} -> 0
A75: CZE | B75: 2008 | D75: - | E75: {=_xlfn.IFS(D75=policy_name_clustering!$A$2,policy_name_clustering!$C$2,D75=policy_name_clustering!$A$3,policy_name_clustering!$C$3,D75=policy_name_clustering!$A$4,policy_name_clustering!$C$4,D75=policy_name_clustering!$A$5,policy_name_clustering!$C$5,D75=policy_name_clustering!$A$6,policy_name_clustering!$C$6,D75=policy_name_clustering!$A$7,policy_name_clustering!$C$7,D75=policy_name_clustering!$A$8,policy_name_clustering!$C$8,D75=policy_name_clustering!$A$9,policy_name_clustering!$C$9,D75=policy_name_clustering!$A$10,policy_name_clustering!$C$10,D75=policy_name_clustering!$A$11,policy_name_clustering!$C$11,D75=policy_name_clustering!$A$12,policy_name_clustering!$C$12,D75="-","")} | G75: =solar_cum_cap!C79 -> 39.5 | H75: =estimated_capacity!C75 -> 715.83861 | I75: {=_xlfn.IFS(D75= ""," ",D75<> " ",F75*(G75/H75))} -> 0 | J75: {=_xlfn.IFS(D75= ""," ",D75<> " ",(H75-F75)*(G75/H75))} -> 39.5 | K75: {=IF(ISNUMBER(H75),_xlfn.IFS(D75= ""," ",D75<> " ",F75*(G75/H75)),"")} -> 0
A76: CZE | B76: 2009 | D76: - | E76: {=_xlfn.IFS(D76=policy_name_clustering!$A$2,policy_name_clustering!$C$2,D76=policy_name_clustering!$A$3,policy_name_clustering!$C$3,D76=policy_name_clustering!$A$4,policy_name_clustering!$C$4,D76=policy_name_clustering!$A$5,policy_name_clustering!$C$5,D76=policy_name_clustering!$A$6,policy_name_clustering!$C$6,D76=policy_name_clustering!$A$7,policy_name_clustering!$C$7,D76=policy_name_clustering!$A$8,policy_name_clustering!$C$8,D76=policy_name_clustering!$A$9,policy_name_clustering!$C$9,D76=policy_name_clustering!$A$10,policy_name_clustering!$C$10,D76=policy_name_clustering!$A$11,policy_name_clustering!$C$11,D76=policy_name_clustering!$A$12,policy_name_clustering!$C$12,D76="-","")} | G76: =solar_cum_cap!C80 -> 464.6 | H76: =estimated_capacity!C76 -> 881.73395 | I76: {=_xlfn.IFS(D76= ""," ",D76<> " ",F76*(G76/H76))} -> 0 | J76: {=_xlfn.IFS(D76= ""," ",D76<> " ",(H76-F76)*(G76/H76))} -> 464.6 | K76: {=IF(ISNUMBER(H76),_xlfn.IFS(D76= ""," ",D76<> " ",F76*(G76/H76)),"")} -> 0
A77: CZE | B77: 2010 | D77: - | E77: {=_xlfn.IFS(D77=policy_name_clustering!$A$2,policy_name_clustering!$C$2,D77=policy_name_clustering!$A$3,policy_name_clustering!$C$3,D77=policy_name_clustering!$A$4,policy_name_clustering!$C$4,D77=policy_name_clustering!$A$5,policy_name_clustering!$C$5,D77=policy_name_clustering!$A$6,policy_name_clustering!$C$6,D77=policy_name_clustering!$A$7,policy_name_clustering!$C$7,D77=policy_name_clustering!$A$8,policy_name_clustering!$C$8,D77=policy_name_clustering!$A$9,policy_name_clustering!$C$9,D77=policy_name_clustering!$A$10,policy_name_clustering!$C$10,D77=policy_name_clustering!$A$11,policy_name_clustering!$C$11,D77=policy_name_clustering!$A$12,policy_name_clustering!$C$12,D77="-","")} | G77: =solar_cum_cap!C81 -> 1727 | H77: =estimated_capacity!C77 -> 1092.702 | I77: {=_xlfn.IFS(D77= ""," ",D77<> " ",F77*(G77/H77))} -> 0 | J77: {=_xlfn.IFS(D77= ""," ",D77<> " ",(H77-F77)*(G77/H77))} -> 1727 | K77: {=IF(ISNUMBER(H77),_xlfn.IFS(D77= ""," ",D77<> " ",F77*(G77/H77)),"")} -> 0
A78: CZE | B78: 2011 | D78: - | E78: {=_xlfn.IFS(D78=policy_name_clustering!$A$2,policy_name_clustering!$C$2,D78=policy_name_clustering!$A$3,policy_name_clustering!$C$3,D78=policy_name_clustering!$A$4,policy_name_clustering!$C$4,D78=policy_name_clustering!$A$5,policy_name_clustering!$C$5,D78=policy_name_clustering!$A$6,policy_name_clustering!$C$6,D78=policy_name_clustering!$A$7,policy_name_clustering!$C$7,D78=policy_name_clustering!$A$8,policy_name_clustering!$C$8,D78=policy_name_clustering!$A$9,policy_name_clustering!$C$9,D78=policy_name_clustering!$A$10,policy_name_clustering!$C$10,D78=policy_name_clustering!$A$11,policy_name_clustering!$C$11,D78=policy_name_clustering!$A$12,policy_name_clustering!$C$12,D78="-","")} | G78: =solar_cum_cap!C82 -> 1909.353 | H78: =estimated_capacity!C78 -> 1352.6187 | I78: {=_xlfn.IFS(D78= ""," ",D78<> " ",F78*(G78/H78))} -> 0 | J78: {=_xlfn.IFS(D78= ""," ",D78<> " ",(H78-F78)*(G78/H78))} -> 1909.353 | K78: {=IF(ISNUMBER(H78),_xlfn.IFS(D78= ""," ",D78<> " ",F78*(G78/H78)),"")} -> 0
A79: CZE | B79: 2012 | D79: - | E79: {=_xlfn.IFS(D79=policy_name_clustering!$A$2,policy_name_clustering!$C$2,D79=policy_name_clustering!$A$3,policy_name_clustering!$C$3,D79=policy_name_clustering!$A$4,policy_name_clustering!$C$4,D79=policy_name_clustering!$A$5,policy_name_clustering!$C$5,D79=policy_name_clustering!$A$6,policy_name_clustering!$C$6,D79=policy_name_clustering!$A$7,policy_name_clustering!$C$7,D79=policy_name_clustering!$A$8,policy_name_clustering!$C$8,D79=policy_name_clustering!$A$9,policy_name_clustering!$C$9,D79=policy_name_clustering!$A$10,policy_name_clustering!$C$10,D79=policy_name_clustering!$A$11,policy_name_clustering!$C$11,D79=policy_name_clustering!$A$12,policy_name_clustering!$C$12,D79="-","")} | G79: =solar_cum_cap!C83 -> 2014.161 | H79: =estimated_capacity!C79 -> 1368.1076 | I79: {=_xlfn.IFS(D79= ""," ",D79<> " ",F79*(G79/H79))} -> 0 | J79: {=_xlfn.IFS(D79= ""," ",D79<> " ",(H79-F79)*(G79/H79))} -> 2014.161 | K79: {=IF(ISNUMBER(H79),_xlfn.IFS(D79= ""," ",D79<> " ",F79*(G79/H79)),"")} -> 0
A80: CZE | B80: 2013 | D80: - | E80: {=_xlfn.IFS(D80=policy_name_clustering!$A$2,policy_name_clustering!$C$2,D80=policy_name_clustering!$A$3,policy_name_clustering!$C$3,D80=policy_name_clustering!$A$4,policy_name_clustering!$C$4,D80=policy_name_clustering!$A$5,policy_name_clustering!$C$5,D80=policy_name_clustering!$A$6,policy_name_clustering!$C$6,D80=policy_name_clustering!$A$7,policy_name_clustering!$C$7,D80=policy_name_clustering!$A$8,policy_name_clustering!$C$8,D80=policy_name_clustering!$A$9,policy_name_clustering!$C$9,D80=policy_name_clustering!$A$10,policy_name_clustering!$C$10,D80=policy_name_clustering!$A$11,policy_name_clustering!$C$11,D80=policy_name_clustering!$A$12,policy_name_clustering!$C$12,D80="-","")} | G80: =solar_cum_cap!C84 -> 2052.946 | H80: =estimated_capacity!C80 -> 1409.5697 | I80: {=_xlfn.IFS(D80= ""," ",D80<> " ",F80*(G80/H80))} -> 0 | J80: {=_xlfn.IFS(D80= ""," ",D80<> " ",(H80-F80)*(G80/H80))} -> 2052.946 | K80: {=IF(ISNUMBER(H80),_xlfn.IFS(D80= ""," ",D80<> " ",F80*(G80/H80)),"")} -> 0
... A90: CZE | B90: 2023 | D90: - | E90: {=_xlfn.IFS(D90=policy_name_clustering!$A$2,policy_name_clustering!$C$2,D90=policy_name_clustering!$A$3,policy_name_clustering!$C$3,D90=policy_name_clustering!$A$4,policy_name_clustering!$C$4,D90=policy_name_clustering!$A$5,policy_name_clustering!$C$5,D90=policy_name_clustering!$A$6,policy_name_clustering!$C$6,D90=policy_name_clustering!$A$7,policy_name_clustering!$C$7,D90=policy_name_clustering!$A$8,policy_name_clustering!$C$8,D90=policy_name_clustering!$A$9,policy_name_clustering!$C$9,D90=policy_name_clustering!$A$10,policy_name_clustering!$C$10,D90=policy_name_clustering!$A$11,policy_name_clustering!$C$11,D90=policy_name_clustering!$A$12,policy_name_clustering!$C$12,D90="-","")} | G90: =solar_cum_cap!C94 -> 3250.961 | H90: =estimated_capacity!C90 -> 2582.7092 | I90: {=_xlfn.IFS(D90= ""," ",D90<> " ",F90*(G90/H90))} -> 0 | J90: {=_xlfn.IFS(D90= ""," ",D90<> " ",(H90-F90)*(G90/H90))} -> 3250.961 | K90: {=IF(ISNUMBER(H90),_xlfn.IFS(D90= ""," ",D90<> " ",F90*(G90/H90)),"")} -> 0
A91: DEU | B91: 2001 | D91: - | E91: {=_xlfn.IFS(D91=policy_name_clustering!$A$2,policy_name_clustering!$C$2,D91=policy_name_clustering!$A$3,policy_name_clustering!$C$3,D91=policy_name_clustering!$A$4,policy_name_clustering!$C$4,D91=policy_name_clustering!$A$5,policy_name_clustering!$C$5,D91=policy_name_clustering!$A$6,policy_name_clustering!$C$6,D91=policy_name_clustering!$A$7,policy_name_clustering!$C$7,D91=policy_name_clustering!$A$8,policy_name_clustering!$C$8,D91=policy_name_clustering!$A$9,policy_name_clustering!$C$9,D91=policy_name_clustering!$A$10,policy_name_clustering!$C$10,D91=policy_name_clustering!$A$11,policy_name_clustering!$C$11,D91=policy_name_clustering!$A$12,policy_name_clustering!$C$12,D91="-","")} | G91: =solar_cum_cap!C96 -> 195 | H91: =estimated_capacity!C91 -> 149.75305 | I91: {=_xlfn.IFS(D91= ""," ",D91<> " ",F91*(G91/H91))} -> 0 | J91: {=_xlfn.IFS(D91= ""," ",D91<> " ",(H91-F91)*(G91/H91))} -> 195 | K91: {=IF(ISNUMBER(H91),_xlfn.IFS(D91= ""," ",D91<> " ",F91*(G91/H91)),"")} -> 0
A92: DEU | B92: 2002 | D92: - | E92: {=_xlfn.IFS(D92=policy_name_clustering!$A$2,policy_name_clustering!$C$2,D92=policy_name_clustering!$A$3,policy_name_clustering!$C$3,D92=policy_name_clustering!$A$4,policy_name_clustering!$C$4,D92=policy_name_clustering!$A$5,policy_name_clustering!$C$5,D92=policy_name_clustering!$A$6,policy_name_clustering!$C$6,D92=policy_name_clustering!$A$7,policy_name_clustering!$C$7,D92=policy_name_clustering!$A$8,policy_name_clustering!$C$8,D92=policy_name_clustering!$A$9,policy_name_clustering!$C$9,D92=policy_name_clustering!$A$10,policy_name_clustering!$C$10,D92=policy_name_clustering!$A$11,policy_name_clustering!$C$11,D92=policy_name_clustering!$A$12,policy_name_clustering!$C$12,D92="-","")} | G92: =solar_cum_cap!C97 -> 260 | H92: =estimated_capacity!C92 -> 290.81986 | I92: {=_xlfn.IFS(D92= ""," ",D92<> " ",F92*(G92/H92))} -> 0 | J92: {=_xlfn.IFS(D92= ""," ",D92<> " ",(H92-F92)*(G92/H92))} -> 260 | K92: {=IF(ISNUMBER(H92),_xlfn.IFS(D92= ""," ",D92<> " ",F92*(G92/H92)),"")} -> 0
A93: DEU | B93: 2003 | D93: - | E93: {=_xlfn.IFS(D93=policy_name_clustering!$A$2,policy_name_clustering!$C$2,D93=policy_name_clustering!$A$3,policy_name_clustering!$C$3,D93=policy_name_clustering!$A$4,policy_name_clustering!$C$4,D93=policy_name_clustering!$A$5,policy_name_clustering!$C$5,D93=policy_name_clustering!$A$6,policy_name_clustering!$C$6,D93=policy_name_clustering!$A$7,policy_name_clustering!$C$7,D93=policy_name_clustering!$A$8,policy_name_clustering!$C$8,D93=policy_name_clustering!$A$9,policy_name_clustering!$C$9,D93=policy_name_clustering!$A$10,policy_name_clustering!$C$10,D93=policy_name_clustering!$A$11,policy_name_clustering!$C$11,D93=policy_name_clustering!$A$12,policy_name_clustering!$C$12,D93="-","")} | G93: =solar_cum_cap!C98 -> 435 | H93: =estimated_capacity!C93 -> 454.56694 | I93: {=_xlfn.IFS(D93= ""," ",D93<> " ",F93*(G93/H93))} -> 0 | J93: {=_xlfn.IFS(D93= ""," ",D93<> " ",(H93-F93)*(G93/H93))} -> 435 | K93: {=IF(ISNUMBER(H93),_xlfn.IFS(D93= ""," ",D93<> " ",F93*(G93/H93)),"")} -> 0
A94: DEU | B94: 2004 | C94: FiT intro - 2000 | D94: FiT | E94: {=_xlfn.IFS(D94=policy_name_clustering!$A$2,policy_name_clustering!$C$2,D94=policy_name_clustering!$A$3,policy_name_clustering!$C$3,D94=policy_name_clustering!$A$4,policy_name_clustering!$C$4,D94=policy_name_clustering!$A$5,policy_name_clustering!$C$5,D94=policy_name_clustering!$A$6,policy_name_clustering!$C$6,D94=policy_name_clustering!$A$7,policy_name_clustering!$C$7,D94=policy_name_clustering!$A$8,policy_name_clustering!$C$8,D94=policy_name_clustering!$A$9,policy_name_clustering!$C$9,D94=policy_name_clustering!$A$10,policy_name_clustering!$C$10,D94=policy_name_clustering!$A$11,policy_name_clustering!$C$11,D94=policy_name_clustering!$A$12,policy_name_clustering!$C$12,D94="-","")} -> FiT/FiP-based | F94: =policy_contributions_cum!F2 -> 214.54302 | G94: =solar_cum_cap!C99 -> 1105 | H94: =estimated_capacity!C94 -> 861.52714 | I94: {=_xlfn.IFS(D94= ""," ",D94<> " ",F94*(G94/H94))} -> 275.17419 | J94: {=_xlfn.IFS(D94= ""," ",D94<> " ",(H94-F94)*(G94/H94))} -> 829.82581 | K94: {=IF(ISNUMBER(H94),_xlfn.IFS(D94= ""," ",D94<> " ",F94*(G94/H94)),"")} -> 275.17419
A95: DEU | B95: 2005 | C95: FiT intro - 2000 | D95: FiT | E95: {=_xlfn.IFS(D95=policy_name_clustering!$A$2,policy_name_clustering!$C$2,D95=policy_name_clustering!$A$3,policy_name_clustering!$C$3,D95=policy_name_clustering!$A$4,policy_name_clustering!$C$4,D95=policy_name_clustering!$A$5,policy_name_clustering!$C$5,D95=policy_name_clustering!$A$6,policy_name_clustering!$C$6,D95=policy_name_clustering!$A$7,policy_name_clustering!$C$7,D95=policy_name_clustering!$A$8,policy_name_clustering!$C$8,D95=policy_name_clustering!$A$9,policy_name_clustering!$C$9,D95=policy_name_clustering!$A$10,policy_name_clustering!$C$10,D95=policy_name_clustering!$A$11,policy_name_clustering!$C$11,D95=policy_name_clustering!$A$12,policy_name_clustering!$C$12,D95="-","")} -> FiT/FiP-based | F95: =policy_contributions_cum!F3 -> 737.37471 | G95: =solar_cum_cap!C100 -> 2056 | H95: =estimated_capacity!C95 -> 1580.022 | I95: {=_xlfn.IFS(D95= ""," ",D95<> " ",F95*(G95/H95))} -> 959.50715 | J95: {=_xlfn.IFS(D95= ""," ",D95<> " ",(H95-F95)*(G95/H95))} -> 1096.4929 | K95: {=IF(ISNUMBER(H95),_xlfn.IFS(D95= ""," ",D95<> " ",F95*(G95/H95)),"")} -> 959.50715
A96: DEU | B96: 2006 | C96: FiT intro - 2000 | D96: FiT | E96: {=_xlfn.IFS(D96=policy_name_clustering!$A$2,policy_name_clustering!$C$2,D96=policy_name_clustering!$A$3,policy_name_clustering!$C$3,D96=policy_name_clustering!$A$4,policy_name_clustering!$C$4,D96=policy_name_clustering!$A$5,policy_name_clustering!$C$5,D96=policy_name_clustering!$A$6,policy_name_clustering!$C$6,D96=policy_name_clustering!$A$7,policy_name_clustering!$C$7,D96=policy_name_clustering!$A$8,policy_name_clustering!$C$8,D96=policy_name_clustering!$A$9,policy_name_clustering!$C$9,D96=policy_name_clustering!$A$10,policy_name_clustering!$C$10,D96=policy_name_clustering!$A$11,policy_name_clustering!$C$11,D96=policy_name_clustering!$A$12,policy_name_clustering!$C$12,D96="-","")} -> FiT/FiP-based | F96: =policy_contributions_cum!F4 -> 1712.3256 | G96: =solar_cum_cap!C101 -> 2899 | H96: =estimated_capacity!C96 -> 2759.0891 | I96: {=_xlfn.IFS(D96= ""," ",D96<> " ",F96*(G96/H96))} -> 1799.156 | J96: {=_xlfn.IFS(D96= ""," ",D96<> " ",(H96-F96)*(G96/H96))} -> 1099.844 | K96: {=IF(ISNUMBER(H96),_xlfn.IFS(D96= ""," ",D96<> " ",F96*(G96/H96)),"")} -> 1799.156
A97: DEU | B97: 2007 | C97: FiT intro - 2000 | D97: FiT | E97: {=_xlfn.IFS(D97=policy_name_clustering!$A$2,policy_name_clustering!$C$2,D97=policy_name_clustering!$A$3,policy_name_clustering!$C$3,D97=policy_name_clustering!$A$4,policy_name_clustering!$C$4,D97=policy_name_clustering!$A$5,policy_name_clustering!$C$5,D97=policy_name_clustering!$A$6,policy_name_clustering!$C$6,D97=policy_name_clustering!$A$7,policy_name_clustering!$C$7,D97=policy_name_clustering!$A$8,policy_name_clustering!$C$8,D97=policy_name_clustering!$A$9,policy_name_clustering!$C$9,D97=policy_name_clustering!$A$10,policy_name_clustering!$C$10,D97=policy_name_clustering!$A$11,policy_name_clustering!$C$11,D97=policy_name_clustering!$A$12,policy_name_clustering!$C$12,D97="-","")} -> FiT/FiP-based | F97: =policy_contributions_cum!F5 -> 3327.996 | G97: =solar_cum_cap!C102 -> 4170 | H97: =estimated_capacity!C97 -> 4582.2138 | I97: {=_xlfn.IFS(D97= ""," ",D97<> " ",F97*(G97/H97))} -> 3028.611 | J97: {=_xlfn.IFS(D97= ""," ",D97<> " ",(H97-F97)*(G97/H97))} -> 1141.389 | K97: {=IF(ISNUMBER(H97),_xlfn.IFS(D97= ""," ",D97<> " ",F97*(G97/H97)),"")} -> 3028.611
A98: DEU | B98: 2008 | C98: FiT intro - 2000 | D98: FiT | E98: {=_xlfn.IFS(D98=policy_name_clustering!$A$2,policy_name_clustering!$C$2,D98=policy_name_clustering!$A$3,policy_name_clustering!$C$3,D98=policy_name_clustering!$A$4,policy_name_clustering!$C$4,D98=policy_name_clustering!$A$5,policy_name_clustering!$C$5,D98=policy_name_clustering!$A$6,policy_name_clustering!$C$6,D98=policy_name_clustering!$A$7,policy_name_clustering!$C$7,D98=policy_name_clustering!$A$8,policy_name_clustering!$C$8,D98=policy_name_clustering!$A$9,policy_name_clustering!$C$9,D98=policy_name_clustering!$A$10,policy_name_clustering!$C$10,D98=policy_name_clustering!$A$11,policy_name_clustering!$C$11,D98=policy_name_clustering!$A$12,policy_name_clustering!$C$12,D98="-","")} -> FiT/FiP-based | F98: =policy_contributions_cum!F6 -> 5913.2348 | G98: =solar_cum_cap!C103 -> 6120 | H98: =estimated_capacity!C98 -> 7388.9905 | I98: {=_xlfn.IFS(D98= ""," ",D98<> " ",F98*(G98/H98))} -> 4897.6917 | J98: {=_xlfn.IFS(D98= ""," ",D98<> " ",(H98-F98)*(G98/H98))} -> 1222.3083 | K98: {=IF(ISNUMBER(H98),_xlfn.IFS(D98= ""," ",D98<> " ",F98*(G98/H98)),"")} -> 4897.6917
A99: DEU | B99: 2009 | C99: FiT intro - 2000 | D99: FiT | E99: {=_xlfn.IFS(D99=policy_name_clustering!$A$2,policy_name_clustering!$C$2,D99=policy_name_clustering!$A$3,policy_name_clustering!$C$3,D99=policy_name_clustering!$A$4,policy_name_clustering!$C$4,D99=policy_name_clustering!$A$5,policy_name_clustering!$C$5,D99=policy_name_clustering!$A$6,policy_name_clustering!$C$6,D99=policy_name_clustering!$A$7,policy_name_clustering!$C$7,D99=policy_name_clustering!$A$8,policy_name_clustering!$C$8,D99=policy_name_clustering!$A$9,policy_name_clustering!$C$9,D99=policy_name_clustering!$A$10,policy_name_clustering!$C$10,D99=policy_name_clustering!$A$11,policy_name_clustering!$C$11,D99=policy_name_clustering!$A$12,policy_name_clustering!$C$12,D99="-","")} -> FiT/FiP-based | F99: =policy_contributions_cum!F7 -> 9762.8464 | G99: =solar_cum_cap!C104 -> 10566 | H99: =estimated_capacity!C99 -> 11452.947 | I99: {=_xlfn.IFS(D99= ""," ",D99<> " ",F99*(G99/H99))} -> 9006.7853 | J99: {=_xlfn.IFS(D99= ""," ",D99<> " ",(H99-F99)*(G99/H99))} -> 1559.2147 | K99: {=IF(ISNUMBER(H99),_xlfn.IFS(D99= ""," ",D99<> " ",F99*(G99/H99)),"")} -> 9006.7853
A100: DEU | B100: 2010 | C100: FiT intro - 2000, FiT level reduced | D100: FiT | E100: {=_xlfn.IFS(D100=policy_name_clustering!$A$2,policy_name_clustering!$C$2,D100=policy_name_clustering!$A$3,policy_name_clustering!$C$3,D100=policy_name_clustering!$A$4,policy_name_clustering!$C$4,D100=policy_name_clustering!$A$5,policy_name_clustering!$C$5,D100=policy_name_clustering!$A$6,policy_name_clustering!$C$6,D100=policy_name_clustering!$A$7,policy_name_clustering!$C$7,D100=policy_name_clustering!$A$8,policy_name_clustering!$C$8,D100=policy_name_clustering!$A$9,policy_name_clustering!$C$9,D100=policy_name_clustering!$A$10,policy_name_clustering!$C$10,D100=policy_name_clustering!$A$11,policy_name_clustering!$C$11,D100=policy_name_clustering!$A$12,policy_name_clustering!$C$12,D100="-","")} -> FiT/FiP-based | F100: =policy_contributions_cum!F8 -> 16096.481 | G100: =solar_cum_cap!C105 -> 18006 | H100: =estimated_capacity!C100 -> 18060.353 | I100: {=_xlfn.IFS(D100= ""," ",D100<> " ",F100*(G100/H100))} -> 16048.038 | J100: {=_xlfn.IFS(D100= ""," ",D100<> " ",(H100-F100)*(G100/H100))} -> 1957.9622 | K100: {=IF(ISNUMBER(H100),_xlfn.IFS(D100= ""," ",D100<> " ",F100*(G100/H100)),"")} -> 16048.038
A101: DEU | B101: 2011 | C101: FiT intro - 2000, FiP intro | D101: FiT | E101: {=_xlfn.IFS(D101=policy_name_clustering!$A$2,policy_name_clustering!$C$2,D101=policy_name_clustering!$A$3,policy_name_clustering!$C$3,D101=policy_name_clustering!$A$4,policy_name_clustering!$C$4,D101=policy_name_clustering!$A$5,policy_name_clustering!$C$5,D101=policy_name_clustering!$A$6,policy_name_clustering!$C$6,D101=policy_name_clustering!$A$7,policy_name_clustering!$C$7,D101=policy_name_clustering!$A$8,policy_name_clustering!$C$8,D101=policy_name_clustering!$A$9,policy_name_clustering!$C$9,D101=policy_name_clustering!$A$10,policy_name_clustering!$C$10,D101=policy_name_clustering!$A$11,policy_name_clustering!$C$11,D101=policy_name_clustering!$A$12,policy_name_clustering!$C$12,D101="-","")} -> FiT/FiP-based | F101: =policy_contributions_cum!F9 -> 26307.838 | G101: =solar_cum_cap!C106 -> 25916 | H101: =estimated_capacity!C101 -> 28606.683 | I101: {=_xlfn.IFS(D101= ""," ",D101<> " ",F101*(G101/H101))} -> 23833.379 | J101: {=_xlfn.IFS(D101= ""," ",D101<> " ",(H101-F101)*(G101/H101))} -> 2082.621 | K101: {=IF(ISNUMBER(H101),_xlfn.IFS(D101= ""," ",D101<> " ",F101*(G101/H101)),"")} -> 23833.379
A102: DEU | B102: 2012 | C102: negative break here:FiT degression changed - 2012, soft loan intro | D102: FiT | E102: {=_xlfn.IFS(D102=policy_name_clustering!$A$2,policy_name_clustering!$C$2,D102=policy_name_clustering!$A$3,policy_name_clustering!$C$3,D102=policy_name_clustering!$A$4,policy_name_clustering!$C$4,D102=policy_name_clustering!$A$5,policy_name_clustering!$C$5,D102=policy_name_clustering!$A$6,policy_name_clustering!$C$6,D102=policy_name_clustering!$A$7,policy_name_clustering!$C$7,D102=policy_name_clustering!$A$8,policy_name_clustering!$C$8,D102=policy_name_clustering!$A$9,policy_name_clustering!$C$9,D102=policy_name_clustering!$A$10,policy_name_clustering!$C$10,D102=policy_name_clustering!$A$11,policy_name_clustering!$C$11,D102=policy_name_clustering!$A$12,policy_name_clustering!$C$12,D102="-","")} -> FiT/FiP-based | F102: =policy_contributions_cum!F10 -> 31759.778 | G102: =solar_cum_cap!C107 -> 34077 | H102: =estimated_capacity!C102 -> 33982.226 | I102: {=_xlfn.IFS(D102= ""," ",D102<> " ",F102*(G102/H102))} -> 31848.354 | J102: {=_xlfn.IFS(D102= ""," ",D102<> " ",(H102-F102)*(G102/H102))} -> 2228.6463 | K102: {=IF(ISNUMBER(H102),_xlfn.IFS(D102= ""," ",D102<> " ",F102*(G102/H102)),"")} -> 31848.354
A103: DEU | B103: 2013 | C103: FiT degression changed, cap intro, soft loan intro | D103: FiT | E103: {=_xlfn.IFS(D103=policy_name_clustering!$A$2,policy_name_clustering!$C$2,D103=policy_name_clustering!$A$3,policy_name_clustering!$C$3,D103=policy_name_clustering!$A$4,policy_name_clustering!$C$4,D103=policy_name_clustering!$A$5,policy_name_clustering!$C$5,D103=policy_name_clustering!$A$6,policy_name_clustering!$C$6,D103=policy_name_clustering!$A$7,policy_name_clustering!$C$7,D103=policy_name_clustering!$A$8,policy_name_clustering!$C$8,D103=policy_name_clustering!$A$9,policy_name_clustering!$C$9,D103=policy_name_clustering!$A$10,policy_name_clustering!$C$10,D103=policy_name_clustering!$A$11,policy_name_clustering!$C$11,D103=policy_name_clustering!$A$12,policy_name_clustering!$C$12,D103="-","")} -> FiT/FiP-based | F103: =policy_contributions_cum!F11 -> 34966.553 | G103: =solar_cum_cap!C108 -> 36710 | H103: =estimated_capacity!C103 -> 36970.529 | I103: {=_xlfn.IFS(D103= ""," ",D103<> " ",F103*(G103/H103))} -> 34720.145 | J103: {=_xlfn.IFS(D103= ""," ",D103<> " ",(H103-F103)*(G103/H103))} -> 1989.8546 | K103: {=IF(ISNUMBER(H103),_xlfn.IFS(D103= ""," ",D103<> " ",F103*(G103/H103)),"")} -> 34720.145
A104: DEU | B104: 2014 | C104: soft loan interest rate increase | D104: FiT | E104: {=_xlfn.IFS(D104=policy_name_clustering!$A$2,policy_name_clustering!$C$2,D104=policy_name_clustering!$A$3,policy_name_clustering!$C$3,D104=policy_name_clustering!$A$4,policy_name_clustering!$C$4,D104=policy_name_clustering!$A$5,policy_name_clustering!$C$5,D104=policy_name_clustering!$A$6,policy_name_clustering!$C$6,D104=policy_name_clustering!$A$7,policy_name_clustering!$C$7,D104=policy_name_clustering!$A$8,policy_name_clustering!$C$8,D104=policy_name_clustering!$A$9,policy_name_clustering!$C$9,D104=policy_name_clustering!$A$10,policy_name_clustering!$C$10,D104=policy_name_clustering!$A$11,policy_name_clustering!$C$11,D104=policy_name_clustering!$A$12,policy_name_clustering!$C$12,D104="-","")} -> FiT/FiP-based | F104: =policy_contributions_cum!F12 -> 36642.055 | G104: =solar_cum_cap!C109 -> 37900 | H104: =estimated_capacity!C104 -> 38365.196 | I104: {=_xlfn.IFS(D104= ""," ",D104<> " ",F104*(G104/H104))} -> 36197.753 | J104: {=_xlfn.IFS(D104= ""," ",D104<> " ",(H104-F104)*(G104/H104))} -> 1702.2472 | K104: {=IF(ISNUMBER(H104),_xlfn.IFS(D104= ""," ",D104<> " ",F104*(G104/H104)),"")} -> 36197.753
A105: DEU | B105: 2015 | C105: tender intro, FiP degression increased, new positive break here | D105: FiT | E105: {=_xlfn.IFS(D105=policy_name_clustering!$A$2,policy_name_clustering!$C$2,D105=policy_name_clustering!$A$3,policy_name_clustering!$C$3,D105=policy_name_clustering!$A$4,policy_name_clustering!$C$4,D105=policy_name_clustering!$A$5,policy_name_clustering!$C$5,D105=policy_name_clustering!$A$6,policy_name_clustering!$C$6,D105=policy_name_clustering!$A$7,policy_name_clustering!$C$7,D105=policy_name_clustering!$A$8,policy_name_clustering!$C$8,D105=policy_name_clustering!$A$9,policy_name_clustering!$C$9,D105=policy_name_clustering!$A$10,policy_name_clustering!$C$10,D105=policy_name_clustering!$A$11,policy_name_clustering!$C$11,D105=policy_name_clustering!$A$12,policy_name_clustering!$C$12,D105="-","")} -> FiT/FiP-based | F105: =F104 -> 36642.055 | I105: =I104 -> 36197.753 | K105: {=IF(ISNUMBER(H105),_xlfn.IFS(D105= ""," ",D105<> " ",F105*(G105/H105)),"")}
A106: DEU | B106: 2016 | C106: FiP cancelled (except for PV rooftop) | D106: FiT | E106: {=_xlfn.IFS(D106=policy_name_clustering!$A$2,policy_name_clustering!$C$2,D106=policy_name_clustering!$A$3,policy_name_clustering!$C$3,D106=policy_name_clustering!$A$4,policy_name_clustering!$C$4,D106=policy_name_clustering!$A$5,policy_name_clustering!$C$5,D106=policy_name_clustering!$A$6,policy_name_clustering!$C$6,D106=policy_name_clustering!$A$7,policy_name_clustering!$C$7,D106=policy_name_clustering!$A$8,policy_name_clustering!$C$8,D106=policy_name_clustering!$A$9,policy_name_clustering!$C$9,D106=policy_name_clustering!$A$10,policy_name_clustering!$C$10,D106=policy_name_clustering!$A$11,policy_name_clustering!$C$11,D106=policy_name_clustering!$A$12,policy_name_clustering!$C$12,D106="-","")} -> FiT/FiP-based | F106: =F105 -> 36642.055 | I106: =I105 -> 36197.753 | K106: {=IF(ISNUMBER(H106),_xlfn.IFS(D106= ""," ",D106<> " ",F106*(G106/H106)),"")}
A107: DEU | B107: 2017 | C107: FiT cancelled, soft loan cap increased, FiP (PV rooftop) cap removed | D107: FiT | E107: {=_xlfn.IFS(D107=policy_name_clustering!$A$2,policy_name_clustering!$C$2,D107=policy_name_clustering!$A$3,policy_name_clustering!$C$3,D107=policy_name_clustering!$A$4,policy_name_clustering!$C$4,D107=policy_name_clustering!$A$5,policy_name_clustering!$C$5,D107=policy_name_clustering!$A$6,policy_name_clustering!$C$6,D107=policy_name_clustering!$A$7,policy_name_clustering!$C$7,D107=policy_name_clustering!$A$8,policy_name_clustering!$C$8,D107=policy_name_clustering!$A$9,policy_name_clustering!$C$9,D107=policy_name_clustering!$A$10,policy_name_clustering!$C$10,D107=policy_name_clustering!$A$11,policy_name_clustering!$C$11,D107=policy_name_clustering!$A$12,policy_name_clustering!$C$12,D107="-","")} -> FiT/FiP-based | F107: =F106 -> 36642.055 | I107: =I106 -> 36197.753 | K107: {=IF(ISNUMBER(H107),_xlfn.IFS(D107= ""," ",D107<> " ",F107*(G107/H107)),"")}
A108: DEU | B108: 2018 | C108: soft loan cap increased, FiP cancelled | D108: FiT | E108: {=_xlfn.IFS(D108=policy_name_clustering!$A$2,policy_name_clustering!$C$2,D108=policy_name_clustering!$A$3,policy_name_clustering!$C$3,D108=policy_name_clustering!$A$4,policy_name_clustering!$C$4,D108=policy_name_clustering!$A$5,policy_name_clustering!$C$5,D108=policy_name_clustering!$A$6,policy_name_clustering!$C$6,D108=policy_name_clustering!$A$7,policy_name_clustering!$C$7,D108=policy_name_clustering!$A$8,policy_name_clustering!$C$8,D108=policy_name_clustering!$A$9,policy_name_clustering!$C$9,D108=policy_name_clustering!$A$10,policy_name_clustering!$C$10,D108=policy_name_clustering!$A$11,policy_name_clustering!$C$11,D108=policy_name_clustering!$A$12,policy_name_clustering!$C$12,D108="-","")} -> FiT/FiP-based | F108: =F107 -> 36642.055 | I108: =I107 -> 36197.753 | K108: {=IF(ISNUMBER(H108),_xlfn.IFS(D108= ""," ",D108<> " ",F108*(G108/H108)),"")}
A109: DEU | B109: 2019 | D109: FiT | E109: {=_xlfn.IFS(D109=policy_name_clustering!$A$2,policy_name_clustering!$C$2,D109=policy_name_clustering!$A$3,policy_name_clustering!$C$3,D109=policy_name_clustering!$A$4,policy_name_clustering!$C$4,D109=policy_name_clustering!$A$5,policy_name_clustering!$C$5,D109=policy_name_clustering!$A$6,policy_name_clustering!$C$6,D109=policy_name_clustering!$A$7,policy_name_clustering!$C$7,D109=policy_name_clustering!$A$8,policy_name_clustering!$C$8,D109=policy_name_clustering!$A$9,policy_name_clustering!$C$9,D109=policy_name_clustering!$A$10,policy_name_clustering!$C$10,D109=policy_name_clustering!$A$11,policy_name_clustering!$C$11,D109=policy_name_clustering!$A$12,policy_name_clustering!$C$12,D109="-","")} -> FiT/FiP-based | F109: =F108 -> 36642.055 | I109: =I108 -> 36197.753 | K109: {=IF(ISNUMBER(H109),_xlfn.IFS(D109= ""," ",D109<> " ",F109*(G109/H109)),"")}
A110: DEU | B110: 2020 | D110: FiT | E110: {=_xlfn.IFS(D110=policy_name_clustering!$A$2,policy_name_clustering!$C$2,D110=policy_name_clustering!$A$3,policy_name_clustering!$C$3,D110=policy_name_clustering!$A$4,policy_name_clustering!$C$4,D110=policy_name_clustering!$A$5,policy_name_clustering!$C$5,D110=policy_name_clustering!$A$6,policy_name_clustering!$C$6,D110=policy_name_clustering!$A$7,policy_name_clustering!$C$7,D110=policy_name_clustering!$A$8,policy_name_clustering!$C$8,D110=policy_name_clustering!$A$9,policy_name_clustering!$C$9,D110=policy_name_clustering!$A$10,policy_name_clustering!$C$10,D110=policy_name_clustering!$A$11,policy_name_clustering!$C$11,D110=policy_name_clustering!$A$12,policy_name_clustering!$C$12,D110="-","")} -> FiT/FiP-based | F110: =F109 -> 36642.055 | I110: =I109 -> 36197.753 | K110: {=IF(ISNUMBER(H110),_xlfn.IFS(D110= ""," ",D110<> " ",F110*(G110/H110)),"")}
A111: DEU | B111: 2021 | D111: FiT | E111: {=_xlfn.IFS(D111=policy_name_clustering!$A$2,policy_name_clustering!$C$2,D111=policy_name_clustering!$A$3,policy_name_clustering!$C$3,D111=policy_name_clustering!$A$4,policy_name_clustering!$C$4,D111=policy_name_clustering!$A$5,policy_name_clustering!$C$5,D111=policy_name_clustering!$A$6,policy_name_clustering!$C$6,D111=policy_name_clustering!$A$7,policy_name_clustering!$C$7,D111=policy_name_clustering!$A$8,policy_name_clustering!$C$8,D111=policy_name_clustering!$A$9,policy_name_clustering!$C$9,D111=policy_name_clustering!$A$10,policy_name_clustering!$C$10,D111=policy_name_clustering!$A$11,policy_name_clustering!$C$11,D111=policy_name_clustering!$A$12,policy_name_clustering!$C$12,D111="-","")} -> FiT/FiP-based | F111: =F110 -> 36642.055 | I111: =I110 -> 36197.753 | K111: {=IF(ISNUMBER(H111),_xlfn.IFS(D111= ""," ",D111<> " ",F111*(G111/H111)),"")}
A112: DEU | B112: 2022 | D112: FiT | E112: {=_xlfn.IFS(D112=policy_name_clustering!$A$2,policy_name_clustering!$C$2,D112=policy_name_clustering!$A$3,policy_name_clustering!$C$3,D112=policy_name_clustering!$A$4,policy_name_clustering!$C$4,D112=policy_name_clustering!$A$5,policy_name_clustering!$C$5,D112=policy_name_clustering!$A$6,policy_name_clustering!$C$6,D112=policy_name_clustering!$A$7,policy_name_clustering!$C$7,D112=policy_name_clustering!$A$8,policy_name_clustering!$C$8,D112=policy_name_clustering!$A$9,policy_name_clustering!$C$9,D112=policy_name_clustering!$A$10,policy_name_clustering!$C$10,D112=policy_name_clustering!$A$11,policy_name_clustering!$C$11,D112=policy_name_clustering!$A$12,policy_name_clustering!$C$12,D112="-","")} -> FiT/FiP-based | F112: =F111 -> 36642.055 | I112: =I111 -> 36197.753 | K112: {=IF(ISNUMBER(H112),_xlfn.IFS(D112= ""," ",D112<> " ",F112*(G112/H112)),"")}
A113: DEU | B113: 2023 | D113: FiT | E113: {=_xlfn.IFS(D113=policy_name_clustering!$A$2,policy_name_clustering!$C$2,D113=policy_name_clustering!$A$3,policy_name_clustering!$C$3,D113=policy_name_clustering!$A$4,policy_name_clustering!$C$4,D113=policy_name_clustering!$A$5,policy_name_clustering!$C$5,D113=policy_name_clustering!$A$6,policy_name_clustering!$C$6,D113=policy_name_clustering!$A$7,policy_name_clustering!$C$7,D113=policy_name_clustering!$A$8,policy_name_clustering!$C$8,D113=policy_name_clustering!$A$9,policy_name_clustering!$C$9,D113=policy_name_clustering!$A$10,policy_name_clustering!$C$10,D113=policy_name_clustering!$A$11,policy_name_clustering!$C$11,D113=policy_name_clustering!$A$12,policy_name_clustering!$C$12,D113="-","")} -> FiT/FiP-based | F113: =F112 -> 36642.055 | I113: =I112 -> 36197.753 | K113: {=IF(ISNUMBER(H113),_xlfn.IFS(D113= ""," ",D113<> " ",F113*(G113/H113)),"")}
A114: DEU | B114: 2015 | C114: soft loan intro 2012,2013, FiP intro 2011, tender intro 2015 (auction wih FiT) , FiT degression changed, cap intro | D114: Soft loan, FiP, Tender | E114: {=_xlfn.IFS(D114=policy_name_clustering!$A$2,policy_name_clustering!$C$2,D114=policy_name_clustering!$A$3,policy_name_clustering!$C$3,D114=policy_name_clustering!$A$4,policy_name_clustering!$C$4,D114=policy_name_clustering!$A$5,policy_name_clustering!$C$5,D114=policy_name_clustering!$A$6,policy_name_clustering!$C$6,D114=policy_name_clustering!$A$7,policy_name_clustering!$C$7,D114=policy_name_clustering!$A$8,policy_name_clustering!$C$8,D114=policy_name_clustering!$A$9,policy_name_clustering!$C$9,D114=policy_name_clustering!$A$10,policy_name_clustering!$C$10,D114=policy_name_clustering!$A$11,policy_name_clustering!$C$11,D114=policy_name_clustering!$A$12,policy_name_clustering!$C$12,D114="-","")} -> Policy mix | F114: =policy_contributions_cum!F22 -> 1026.4168 | G114: =solar_cum_cap!C110 -> 39224 | H114: =estimated_capacity!C105 -> 39863.611 | I114: {=_xlfn.IFS(D114= ""," ",D114<> " ",F114*(G114/H114))} -> 1009.948 | J114: {=_xlfn.IFS(D114= ""," ",D114<> " ",(H114-F114)*(G114/H114)-$I$104)} -> 2016.2993 | K114: {=IF(ISNUMBER(H114),_xlfn.IFS(D114= ""," ",D114<> " ",F114*(G114/H114)),"")} -> 1009.948
A115: DEU | B115: 2016 | C115: soft loan intro 2012,2013, FiP intro 2011, tender intro 2015 , FiP cancelled (except for PV rooftop) | D115: Soft loan, FiP, Tender | E115: {=_xlfn.IFS(D115=policy_name_clustering!$A$2,policy_name_clustering!$C$2,D115=policy_name_clustering!$A$3,policy_name_clustering!$C$3,D115=policy_name_clustering!$A$4,policy_name_clustering!$C$4,D115=policy_name_clustering!$A$5,policy_name_clustering!$C$5,D115=policy_name_clustering!$A$6,policy_name_clustering!$C$6,D115=policy_name_clustering!$A$7,policy_name_clustering!$C$7,D115=policy_name_clustering!$A$8,policy_name_clustering!$C$8,D115=policy_name_clustering!$A$9,policy_name_clustering!$C$9,D115=policy_name_clustering!$A$10,policy_name_clustering!$C$10,D115=policy_name_clustering!$A$11,policy_name_clustering!$C$11,D115=policy_name_clustering!$A$12,policy_name_clustering!$C$12,D115="-","")} -> Policy mix | F115: =policy_contributions_cum!F23 -> 2658.4376 | G115: =solar_cum_cap!C111 -> 40679 | H115: =estimated_capacity!C106 -> 41558.827 | I115: {=_xlfn.IFS(D115= ""," ",D115<> " ",F115*(G115/H115))} -> 2602.1568 | J115: {=_xlfn.IFS(D115= ""," ",D115<> " ",(H115-F115)*(G115/H115)-$I$104)} -> 1879.0905 | K115: {=IF(ISNUMBER(H115),_xlfn.IFS(D115= ""," ",D115<> " ",F115*(G115/H115)),"")} -> 2602.1568
A116: DEU | B116: 2017 | C116: soft loan intro 2012,2013, FiP intro 2011, tender intro 2015, FiT cancelled, soft loan cap increased, FiP (PV rooftop) cap removed | D116: Soft loan, FiP, Tender | E116: {=_xlfn.IFS(D116=policy_name_clustering!$A$2,policy_name_clustering!$C$2,D116=policy_name_clustering!$A$3,policy_name_clustering!$C$3,D116=policy_name_clustering!$A$4,policy_name_clustering!$C$4,D116=policy_name_clustering!$A$5,policy_name_clustering!$C$5,D116=policy_name_clustering!$A$6,policy_name_clustering!$C$6,D116=policy_name_clustering!$A$7,policy_name_clustering!$C$7,D116=policy_name_clustering!$A$8,policy_name_clustering!$C$8,D116=policy_name_clustering!$A$9,policy_name_clustering!$C$9,D116=policy_name_clustering!$A$10,policy_name_clustering!$C$10,D116=policy_name_clustering!$A$11,policy_name_clustering!$C$11,D116=policy_name_clustering!$A$12,policy_name_clustering!$C$12,D116="-","")} -> Policy mix | F116: =policy_contributions_cum!F24 -> 5002.262 | G116: =solar_cum_cap!C112 -> 42293 | H116: =estimated_capacity!C107 -> 43795.489 | I116: {=_xlfn.IFS(D116= ""," ",D116<> " ",F116*(G116/H116))} -> 4830.6497 | J116: {=_xlfn.IFS(D116= ""," ",D116<> " ",(H116-F116)*(G116/H116)-$I$104)} -> 1264.5975 | K116: {=IF(ISNUMBER(H116),_xlfn.IFS(D116= ""," ",D116<> " ",F116*(G116/H116)),"")} -> 4830.6497
A117: DEU | B117: 2018 | C117: soft loan intro 2012,2013, FiP intro 2011, tender intro 2015, soft loan cap increased, FiP cancelled | D117: Soft loan, FiP, Tender | E117: {=_xlfn.IFS(D117=policy_name_clustering!$A$2,policy_name_clustering!$C$2,D117=policy_name_clustering!$A$3,policy_name_clustering!$C$3,D117=policy_name_clustering!$A$4,policy_name_clustering!$C$4,D117=policy_name_clustering!$A$5,policy_name_clustering!$C$5,D117=policy_name_clustering!$A$6,policy_name_clustering!$C$6,D117=policy_name_clustering!$A$7,policy_name_clustering!$C$7,D117=policy_name_clustering!$A$8,policy_name_clustering!$C$8,D117=policy_name_clustering!$A$9,policy_name_clustering!$C$9,D117=policy_name_clustering!$A$10,policy_name_clustering!$C$10,D117=policy_name_clustering!$A$11,policy_name_clustering!$C$11,D117=policy_name_clustering!$A$12,policy_name_clustering!$C$12,D117="-","")} -> Policy mix | F117: =policy_contributions_cum!F25 -> 8064.8228 | G117: =solar_cum_cap!C113 -> 45158 | H117: =estimated_capacity!C108 -> 46654.646 | I117: {=_xlfn.IFS(D117= ""," ",D117<> " ",F117*(G117/H117))} -> 7806.1094 | J117: {=_xlfn.IFS(D117= ""," ",D117<> " ",(H117-F117)*(G117/H117)-$I$104)} -> 1154.1378 | K117: {=IF(ISNUMBER(H117),_xlfn.IFS(D117= ""," ",D117<> " ",F117*(G117/H117)),"")} -> 7806.1094
A118: DEU | B118: 2019 | C118: soft loan intro 2012,2013, FiP intro 2011, tender intro 2015 | D118: Soft loan, FiP, Tender | E118: {=_xlfn.IFS(D118=policy_name_clustering!$A$2,policy_name_clustering!$C$2,D118=policy_name_clustering!$A$3,policy_name_clustering!$C$3,D118=policy_name_clustering!$A$4,policy_name_clustering!$C$4,D118=policy_name_clustering!$A$5,policy_name_clustering!$C$5,D118=policy_name_clustering!$A$6,policy_name_clustering!$C$6,D118=policy_name_clustering!$A$7,policy_name_clustering!$C$7,D118=policy_name_clustering!$A$8,policy_name_clustering!$C$8,D118=policy_name_clustering!$A$9,policy_name_clustering!$C$9,D118=policy_name_clustering!$A$10,policy_name_clustering!$C$10,D118=policy_name_clustering!$A$11,policy_name_clustering!$C$11,D118=policy_name_clustering!$A$12,policy_name_clustering!$C$12,D118="-","")} -> Policy mix | F118: =policy_contributions_cum!F26 -> 11242.385 | G118: =solar_cum_cap!C114 -> 48914 | H118: =estimated_capacity!C109 -> 49565.609 | I118: {=_xlfn.IFS(D118= ""," ",D118<> " ",F118*(G118/H118))} -> 11094.588 | J118: {=_xlfn.IFS(D118= ""," ",D118<> " ",(H118-F118)*(G118/H118)-$I$104)} -> 1621.6594 | K118: {=IF(ISNUMBER(H118),_xlfn.IFS(D118= ""," ",D118<> " ",F118*(G118/H118)),"")} -> 11094.588
A119: DEU | B119: 2020 | C119: soft loan intro 2012,2013, FiP intro 2011, tender intro 2015 | D119: Soft loan, FiP, Tender | E119: {=_xlfn.IFS(D119=policy_name_clustering!$A$2,policy_name_clustering!$C$2,D119=policy_name_clustering!$A$3,policy_name_clustering!$C$3,D119=policy_name_clustering!$A$4,policy_name_clustering!$C$4,D119=policy_name_clustering!$A$5,policy_name_clustering!$C$5,D119=policy_name_clustering!$A$6,policy_name_clustering!$C$6,D119=policy_name_clustering!$A$7,policy_name_clustering!$C$7,D119=policy_name_clustering!$A$8,policy_name_clustering!$C$8,D119=policy_name_clustering!$A$9,policy_name_clustering!$C$9,D119=policy_name_clustering!$A$10,policy_name_clustering!$C$10,D119=policy_name_clustering!$A$11,policy_name_clustering!$C$11,D119=policy_name_clustering!$A$12,policy_name_clustering!$C$12,D119="-","")} -> Policy mix | F119: =F118 -> 11242.385 | I119: =I118 -> 11094.588 | K119: {=IF(ISNUMBER(H119),_xlfn.IFS(D119= ""," ",D119<> " ",F119*(G119/H119)),"")}
A120: DEU | B120: 2021 | D120: Soft loan, FiP, Tender | E120: {=_xlfn.IFS(D120=policy_name_clustering!$A$2,policy_name_clustering!$C$2,D120=policy_name_clustering!$A$3,policy_name_clustering!$C$3,D120=policy_name_clustering!$A$4,policy_name_clustering!$C$4,D120=policy_name_clustering!$A$5,policy_name_clustering!$C$5,D120=policy_name_clustering!$A$6,policy_name_clustering!$C$6,D120=policy_name_clustering!$A$7,policy_name_clustering!$C$7,D120=policy_name_clustering!$A$8,policy_name_clustering!$C$8,D120=policy_name_clustering!$A$9,policy_name_clustering!$C$9,D120=policy_name_clustering!$A$10,policy_name_clustering!$C$10,D120=policy_name_clustering!$A$11,policy_name_clustering!$C$11,D120=policy_name_clustering!$A$12,policy_name_clustering!$C$12,D120="-","")} -> Policy mix | F120: =F119 -> 11242.385 | I120: =I119 -> 11094.588 | K120: {=IF(ISNUMBER(H120),_xlfn.IFS(D120= ""," ",D120<> " ",F120*(G120/H120)),"")}
A121: DEU | B121: 2022 | D121: Soft loan, FiP, Tender | E121: {=_xlfn.IFS(D121=policy_name_clustering!$A$2,policy_name_clustering!$C$2,D121=policy_name_clustering!$A$3,policy_name_clustering!$C$3,D121=policy_name_clustering!$A$4,policy_name_clustering!$C$4,D121=policy_name_clustering!$A$5,policy_name_clustering!$C$5,D121=policy_name_clustering!$A$6,policy_name_clustering!$C$6,D121=policy_name_clustering!$A$7,policy_name_clustering!$C$7,D121=policy_name_clustering!$A$8,policy_name_clustering!$C$8,D121=policy_name_clustering!$A$9,policy_name_clustering!$C$9,D121=policy_name_clustering!$A$10,policy_name_clustering!$C$10,D121=policy_name_clustering!$A$11,policy_name_clustering!$C$11,D121=policy_name_clustering!$A$12,policy_name_clustering!$C$12,D121="-","")} -> Policy mix | F121: =F120 -> 11242.385 | I121: =I120 -> 11094.588 | K121: {=IF(ISNUMBER(H121),_xlfn.IFS(D121= ""," ",D121<> " ",F121*(G121/H121)),"")}
A122: DEU | B122: 2023 | D122: Soft loan, FiP, Tender | E122: {=_xlfn.IFS(D122=policy_name_clustering!$A$2,policy_name_clustering!$C$2,D122=policy_name_clustering!$A$3,policy_name_clustering!$C$3,D122=policy_name_clustering!$A$4,policy_name_clustering!$C$4,D122=policy_name_clustering!$A$5,policy_name_clustering!$C$5,D122=policy_name_clustering!$A$6,policy_name_clustering!$C$6,D122=policy_name_clustering!$A$7,policy_name_clustering!$C$7,D122=policy_name_clustering!$A$8,policy_name_clustering!$C$8,D122=policy_name_clustering!$A$9,policy_name_clustering!$C$9,D122=policy_name_clustering!$A$10,policy_name_clustering!$C$10,D122=policy_name_clustering!$A$11,policy_name_clustering!$C$11,D122=policy_name_clustering!$A$12,policy_name_clustering!$C$12,D122="-","")} -> Policy mix | F122: =F121 -> 11242.385 | I122: =I121 -> 11094.588 | K122: {=IF(ISNUMBER(H122),_xlfn.IFS(D122= ""," ",D122<> " ",F122*(G122/H122)),"")}
A123: DEU | B123: 2020 | C123: soft loan intro 2012,2013, FiP intro 2011, tender intro 2015 | D123: Soft loan, Tender | E123: {=_xlfn.IFS(D123=policy_name_clustering!$A$2,policy_name_clustering!$C$2,D123=policy_name_clustering!$A$3,policy_name_clustering!$C$3,D123=policy_name_clustering!$A$4,policy_name_clustering!$C$4,D123=policy_name_clustering!$A$5,policy_name_clustering!$C$5,D123=policy_name_clustering!$A$6,policy_name_clustering!$C$6,D123=policy_name_clustering!$A$7,policy_name_clustering!$C$7,D123=policy_name_clustering!$A$8,policy_name_clustering!$C$8,D123=policy_name_clustering!$A$9,policy_name_clustering!$C$9,D123=policy_name_clustering!$A$10,policy_name_clustering!$C$10,D123=policy_name_clustering!$A$11,policy_name_clustering!$C$11,D123=policy_name_clustering!$A$12,policy_name_clustering!$C$12,D123="-","")} -> Policy mix | F123: =policy_contributions_cum!F27 -> 14611.166 | G123: =solar_cum_cap!C115 -> 53671 | H123: =estimated_capacity!C110 -> 52640.637 | I123: {=_xlfn.IFS(D123= ""," ",D123<> " ",F123*(G123/H123)-$I$118)} -> 3802.5703 | J123: {=_xlfn.IFS(D123= ""," ",D123<> " ",(H123-F123)*(G123/H123)-$I$104)} -> 2576.0891 | K123: {=IF(ISNUMBER(H123),_xlfn.IFS(D123= ""," ",D123<> " ",F123*(G123/H123)),"")} -> 14897.158
A124: DEU | B124: 2021 | C124: soft loan intro 2012,2013, tender intro 2015 | D124: Soft loan, Tender | E124: {=_xlfn.IFS(D124=policy_name_clustering!$A$2,policy_name_clustering!$C$2,D124=policy_name_clustering!$A$3,policy_name_clustering!$C$3,D124=policy_name_clustering!$A$4,policy_name_clustering!$C$4,D124=policy_name_clustering!$A$5,policy_name_clustering!$C$5,D124=policy_name_clustering!$A$6,policy_name_clustering!$C$6,D124=policy_name_clustering!$A$7,policy_name_clustering!$C$7,D124=policy_name_clustering!$A$8,policy_name_clustering!$C$8,D124=policy_name_clustering!$A$9,policy_name_clustering!$C$9,D124=policy_name_clustering!$A$10,policy_name_clustering!$C$10,D124=policy_name_clustering!$A$11,policy_name_clustering!$C$11,D124=policy_name_clustering!$A$12,policy_name_clustering!$C$12,D124="-","")} -> Policy mix | F124: =policy_contributions_cum!F28 -> 18736.503 | G124: =solar_cum_cap!C116 -> 60038 | H124: =estimated_capacity!C111 -> 56461.499 | I124: {=_xlfn.IFS(D124= ""," ",D124<> " ",F124*(G124/H124)-$I$118)} -> 8828.7618 | J124: {=_xlfn.IFS(D124= ""," ",D124<> " ",(H124-F124)*(G124/H124)-$I$104)} -> 3916.8976 | K124: {=IF(ISNUMBER(H124),_xlfn.IFS(D124= ""," ",D124<> " ",F124*(G124/H124)),"")} -> 19923.35
A125: DEU | B125: 2022 | C125: soft loan intro 2012,2013, tender intro 2015 | D125: Soft loan, Tender | E125: {=_xlfn.IFS(D125=policy_name_clustering!$A$2,policy_name_clustering!$C$2,D125=policy_name_clustering!$A$3,policy_name_clustering!$C$3,D125=policy_name_clustering!$A$4,policy_name_clustering!$C$4,D125=policy_name_clustering!$A$5,policy_name_clustering!$C$5,D125=policy_name_clustering!$A$6,policy_name_clustering!$C$6,D125=policy_name_clustering!$A$7,policy_name_clustering!$C$7,D125=policy_name_clustering!$A$8,policy_name_clustering!$C$8,D125=policy_name_clustering!$A$9,policy_name_clustering!$C$9,D125=policy_name_clustering!$A$10,policy_name_clustering!$C$10,D125=policy_name_clustering!$A$11,policy_name_clustering!$C$11,D125=policy_name_clustering!$A$12,policy_name_clustering!$C$12,D125="-","")} -> Policy mix | F125: =policy_contributions_cum!F29 -> 25249.151 | G125: =solar_cum_cap!C117 -> 61188 | H125: =estimated_capacity!C112 -> 62665.86 | I125: {=_xlfn.IFS(D125= ""," ",D125<> " ",F125*(G125/H125)-$I$118)} -> 13559.108 | J125: {=_xlfn.IFS(D125= ""," ",D125<> " ",(H125-F125)*(G125/H125)-$I$104)} -> 336.55145 | K125: {=IF(ISNUMBER(H125),_xlfn.IFS(D125= ""," ",D125<> " ",F125*(G125/H125)),"")} -> 24653.696
A126: DEU | B126: 2023 | C126: soft loan intro 2012,2013, tender intro 2015 | D126: Soft loan, Tender | E126: {=_xlfn.IFS(D126=policy_name_clustering!$A$2,policy_name_clustering!$C$2,D126=policy_name_clustering!$A$3,policy_name_clustering!$C$3,D126=policy_name_clustering!$A$4,policy_name_clustering!$C$4,D126=policy_name_clustering!$A$5,policy_name_clustering!$C$5,D126=policy_name_clustering!$A$6,policy_name_clustering!$C$6,D126=policy_name_clustering!$A$7,policy_name_clustering!$C$7,D126=policy_name_clustering!$A$8,policy_name_clustering!$C$8,D126=policy_name_clustering!$A$9,policy_name_clustering!$C$9,D126=policy_name_clustering!$A$10,policy_name_clustering!$C$10,D126=policy_name_clustering!$A$11,policy_name_clustering!$C$11,D126=policy_name_clustering!$A$12,policy_name_clustering!$C$12,D126="-","")} -> Policy mix | F126: =policy_contributions_cum!F30 -> 34038.527 | G126: =solar_cum_cap!C118 -> 74882 | H126: =estimated_capacity!C113 -> 71143.52 | I126: {=_xlfn.IFS(D126= ""," ",D126<> " ",F126*(G126/H126)-$I$118)} -> 24732.61 | J126: {=_xlfn.IFS(D126= ""," ",D126<> " ",(H126-F126)*(G126/H126)-$I$104)} -> 2857.0496 | K126: {=IF(ISNUMBER(H126),_xlfn.IFS(D126= ""," ",D126<> " ",F126*(G126/H126)),"")} -> 35827.198
A127: DNK | B127: 2001 | D127: - | E127: {=_xlfn.IFS(D127=policy_name_clustering!$A$2,policy_name_clustering!$C$2,D127=policy_name_clustering!$A$3,policy_name_clustering!$C$3,D127=policy_name_clustering!$A$4,policy_name_clustering!$C$4,D127=policy_name_clustering!$A$5,policy_name_clustering!$C$5,D127=policy_name_clustering!$A$6,policy_name_clustering!$C$6,D127=policy_name_clustering!$A$7,policy_name_clustering!$C$7,D127=policy_name_clustering!$A$8,policy_name_clustering!$C$8,D127=policy_name_clustering!$A$9,policy_name_clustering!$C$9,D127=policy_name_clustering!$A$10,policy_name_clustering!$C$10,D127=policy_name_clustering!$A$11,policy_name_clustering!$C$11,D127=policy_name_clustering!$A$12,policy_name_clustering!$C$12,D127="-","")} | G127: =solar_cum_cap!C120 -> 1 | H127: =estimated_capacity!C114 -> -1.4924322 | I127: {=_xlfn.IFS(D127= ""," ",D127<> " ",F127*(G127/H127))} -> 0 | J127: {=_xlfn.IFS(D127= ""," ",D127<> " ",(H127-F127)*(G127/H127))} -> 1 | K127: {=IF(ISNUMBER(H127),_xlfn.IFS(D127= ""," ",D127<> " ",F127*(G127/H127)),"")} -> 0
A128: DNK | B128: 2002 | D128: - | E128: {=_xlfn.IFS(D128=policy_name_clustering!$A$2,policy_name_clustering!$C$2,D128=policy_name_clustering!$A$3,policy_name_clustering!$C$3,D128=policy_name_clustering!$A$4,policy_name_clustering!$C$4,D128=policy_name_clustering!$A$5,policy_name_clustering!$C$5,D128=policy_name_clustering!$A$6,policy_name_clustering!$C$6,D128=policy_name_clustering!$A$7,policy_name_clustering!$C$7,D128=policy_name_clustering!$A$8,policy_name_clustering!$C$8,D128=policy_name_clustering!$A$9,policy_name_clustering!$C$9,D128=policy_name_clustering!$A$10,policy_name_clustering!$C$10,D128=policy_name_clustering!$A$11,policy_name_clustering!$C$11,D128=policy_name_clustering!$A$12,policy_name_clustering!$C$12,D128="-","")} | G128: =solar_cum_cap!C121 -> 2 | H128: =estimated_capacity!C115 -> -8.6521617 | I128: {=_xlfn.IFS(D128= ""," ",D128<> " ",F128*(G128/H128))} -> 0 | J128: {=_xlfn.IFS(D128= ""," ",D128<> " ",(H128-F128)*(G128/H128))} -> 2 | K128: {=IF(ISNUMBER(H128),_xlfn.IFS(D128= ""," ",D128<> " ",F128*(G128/H128)),"")} -> 0
A129: DNK | B129: 2003 | D129: - | E129: {=_xlfn.IFS(D129=policy_name_clustering!$A$2,policy_name_clustering!$C$2,D129=policy_name_clustering!$A$3,policy_name_clustering!$C$3,D129=policy_name_clustering!$A$4,policy_name_clustering!$C$4,D129=policy_name_clustering!$A$5,policy_name_clustering!$C$5,D129=policy_name_clustering!$A$6,policy_name_clustering!$C$6,D129=policy_name_clustering!$A$7,policy_name_clustering!$C$7,D129=policy_name_clustering!$A$8,policy_name_clustering!$C$8,D129=policy_name_clustering!$A$9,policy_name_clustering!$C$9,D129=policy_name_clustering!$A$10,policy_name_clustering!$C$10,D129=policy_name_clustering!$A$11,policy_name_clustering!$C$11,D129=policy_name_clustering!$A$12,policy_name_clustering!$C$12,D129="-","")} | G129: =solar_cum_cap!C122 -> 2 | H129: =estimated_capacity!C116 -> -1.3677831 | I129: {=_xlfn.IFS(D129= ""," ",D129<> " ",F129*(G129/H129))} -> 0 | J129: {=_xlfn.IFS(D129= ""," ",D129<> " ",(H129-F129)*(G129/H129))} -> 2 | K129: {=IF(ISNUMBER(H129),_xlfn.IFS(D129= ""," ",D129<> " ",F129*(G129/H129)),"")} -> 0
A130: DNK | B130: 2004 | D130: - | E130: {=_xlfn.IFS(D130=policy_name_clustering!$A$2,policy_name_clustering!$C$2,D130=policy_name_clustering!$A$3,policy_name_clustering!$C$3,D130=policy_name_clustering!$A$4,policy_name_clustering!$C$4,D130=policy_name_clustering!$A$5,policy_name_clustering!$C$5,D130=policy_name_clustering!$A$6,policy_name_clustering!$C$6,D130=policy_name_clustering!$A$7,policy_name_clustering!$C$7,D130=policy_name_clustering!$A$8,policy_name_clustering!$C$8,D130=policy_name_clustering!$A$9,policy_name_clustering!$C$9,D130=policy_name_clustering!$A$10,policy_name_clustering!$C$10,D130=policy_name_clustering!$A$11,policy_name_clustering!$C$11,D130=policy_name_clustering!$A$12,policy_name_clustering!$C$12,D130="-","")} | G130: =solar_cum_cap!C123 -> 2 | H130: =estimated_capacity!C117 -> 27.862989 | I130: {=_xlfn.IFS(D130= ""," ",D130<> " ",F130*(G130/H130))} -> 0 | J130: {=_xlfn.IFS(D130= ""," ",D130<> " ",(H130-F130)*(G130/H130))} -> 2 | K130: {=IF(ISNUMBER(H130),_xlfn.IFS(D130= ""," ",D130<> " ",F130*(G130/H130)),"")} -> 0
A131: DNK | B131: 2005 | D131: - | E131: {=_xlfn.IFS(D131=policy_name_clustering!$A$2,policy_name_clustering!$C$2,D131=policy_name_clustering!$A$3,policy_name_clustering!$C$3,D131=policy_name_clustering!$A$4,policy_name_clustering!$C$4,D131=policy_name_clustering!$A$5,policy_name_clustering!$C$5,D131=policy_name_clustering!$A$6,policy_name_clustering!$C$6,D131=policy_name_clustering!$A$7,policy_name_clustering!$C$7,D131=policy_name_clustering!$A$8,policy_name_clustering!$C$8,D131=policy_name_clustering!$A$9,policy_name_clustering!$C$9,D131=policy_name_clustering!$A$10,policy_name_clustering!$C$10,D131=policy_name_clustering!$A$11,policy_name_clustering!$C$11,D131=policy_name_clustering!$A$12,policy_name_clustering!$C$12,D131="-","")} | G131: =solar_cum_cap!C124 -> 3 | H131: =estimated_capacity!C118 -> 53.657718 | I131: {=_xlfn.IFS(D131= ""," ",D131<> " ",F131*(G131/H131))} -> 0 | J131: {=_xlfn.IFS(D131= ""," ",D131<> " ",(H131-F131)*(G131/H131))} -> 3 | K131: {=IF(ISNUMBER(H131),_xlfn.IFS(D131= ""," ",D131<> " ",F131*(G131/H131)),"")} -> 0
A132: DNK | B132: 2006 | D132: - | E132: {=_xlfn.IFS(D132=policy_name_clustering!$A$2,policy_name_clustering!$C$2,D132=policy_name_clustering!$A$3,policy_name_clustering!$C$3,D132=policy_name_clustering!$A$4,policy_name_clustering!$C$4,D132=policy_name_clustering!$A$5,policy_name_clustering!$C$5,D132=policy_name_clustering!$A$6,policy_name_clustering!$C$6,D132=policy_name_clustering!$A$7,policy_name_clustering!$C$7,D132=policy_name_clustering!$A$8,policy_name_clustering!$C$8,D132=policy_name_clustering!$A$9,policy_name_clustering!$C$9,D132=policy_name_clustering!$A$10,policy_name_clustering!$C$10,D132=policy_name_clustering!$A$11,policy_name_clustering!$C$11,D132=policy_name_clustering!$A$12,policy_name_clustering!$C$12,D132="-","")} | G132: =solar_cum_cap!C125 -> 3 | H132: =estimated_capacity!C119 -> 84.947933 | I132: {=_xlfn.IFS(D132= ""," ",D132<> " ",F132*(G132/H132))} -> 0 | J132: {=_xlfn.IFS(D132= ""," ",D132<> " ",(H132-F132)*(G132/H132))} -> 3 | K132: {=IF(ISNUMBER(H132),_xlfn.IFS(D132= ""," ",D132<> " ",F132*(G132/H132)),"")} -> 0
A133: DNK | B133: 2007 | D133: - | E133: {=_xlfn.IFS(D133=policy_name_clustering!$A$2,policy_name_clustering!$C$2,D133=policy_name_clustering!$A$3,policy_name_clustering!$C$3,D133=policy_name_clustering!$A$4,policy_name_clustering!$C$4,D133=policy_name_clustering!$A$5,policy_name_clustering!$C$5,D133=policy_name_clustering!$A$6,policy_name_clustering!$C$6,D133=policy_name_clustering!$A$7,policy_name_clustering!$C$7,D133=policy_name_clustering!$A$8,policy_name_clustering!$C$8,D133=policy_name_clustering!$A$9,policy_name_clustering!$C$9,D133=policy_name_clustering!$A$10,policy_name_clustering!$C$10,D133=policy_name_clustering!$A$11,policy_name_clustering!$C$11,D133=policy_name_clustering!$A$12,policy_name_clustering!$C$12,D133="-","")} | G133: =solar_cum_cap!C126 -> 3 | H133: =estimated_capacity!C120 -> 119.36399 | I133: {=_xlfn.IFS(D133= ""," ",D133<> " ",F133*(G133/H133))} -> 0 | J133: {=_xlfn.IFS(D133= ""," ",D133<> " ",(H133-F133)*(G133/H133))} -> 3 | K133: {=IF(ISNUMBER(H133),_xlfn.IFS(D133= ""," ",D133<> " ",F133*(G133/H133)),"")} -> 0
A134: DNK | B134: 2008 | D134: - | E134: {=_xlfn.IFS(D134=policy_name_clustering!$A$2,policy_name_clustering!$C$2,D134=policy_name_clustering!$A$3,policy_name_clustering!$C$3,D134=policy_name_clustering!$A$4,policy_name_clustering!$C$4,D134=policy_name_clustering!$A$5,policy_name_clustering!$C$5,D134=policy_name_clustering!$A$6,policy_name_clustering!$C$6,D134=policy_name_clustering!$A$7,policy_name_clustering!$C$7,D134=policy_name_clustering!$A$8,policy_name_clustering!$C$8,D134=policy_name_clustering!$A$9,policy_name_clustering!$C$9,D134=policy_name_clustering!$A$10,policy_name_clustering!$C$10,D134=policy_name_clustering!$A$11,policy_name_clustering!$C$11,D134=policy_name_clustering!$A$12,policy_name_clustering!$C$12,D134="-","")} | G134: =solar_cum_cap!C127 -> 3 | H134: =estimated_capacity!C121 -> 166.54433 | I134: {=_xlfn.IFS(D134= ""," ",D134<> " ",F134*(G134/H134))} -> 0 | J134: {=_xlfn.IFS(D134= ""," ",D134<> " ",(H134-F134)*(G134/H134))} -> 3 | K134: {=IF(ISNUMBER(H134),_xlfn.IFS(D134= ""," ",D134<> " ",F134*(G134/H134)),"")} -> 0
A135: DNK | B135: 2009 | D135: - | E135: {=_xlfn.IFS(D135=policy_name_clustering!$A$2,policy_name_clustering!$C$2,D135=policy_name_clustering!$A$3,policy_name_clustering!$C$3,D135=policy_name_clustering!$A$4,policy_name_clustering!$C$4,D135=policy_name_clustering!$A$5,policy_name_clustering!$C$5,D135=policy_name_clustering!$A$6,policy_name_clustering!$C$6,D135=policy_name_clustering!$A$7,policy_name_clustering!$C$7,D135=policy_name_clustering!$A$8,policy_name_clustering!$C$8,D135=policy_name_clustering!$A$9,policy_name_clustering!$C$9,D135=policy_name_clustering!$A$10,policy_name_clustering!$C$10,D135=policy_name_clustering!$A$11,policy_name_clustering!$C$11,D135=policy_name_clustering!$A$12,policy_name_clustering!$C$12,D135="-","")} | G135: =solar_cum_cap!C128 -> 5 | H135: =estimated_capacity!C122 -> 212.36096 | I135: {=_xlfn.IFS(D135= ""," ",D135<> " ",F135*(G135/H135))} -> 0 | J135: {=_xlfn.IFS(D135= ""," ",D135<> " ",(H135-F135)*(G135/H135))} -> 5 | K135: {=IF(ISNUMBER(H135),_xlfn.IFS(D135= ""," ",D135<> " ",F135*(G135/H135)),"")} -> 0
A136: DNK | B136: 2010 | D136: - | E136: {=_xlfn.IFS(D136=policy_name_clustering!$A$2,policy_name_clustering!$C$2,D136=policy_name_clustering!$A$3,policy_name_clustering!$C$3,D136=policy_name_clustering!$A$4,policy_name_clustering!$C$4,D136=policy_name_clustering!$A$5,policy_name_clustering!$C$5,D136=policy_name_clustering!$A$6,policy_name_clustering!$C$6,D136=policy_name_clustering!$A$7,policy_name_clustering!$C$7,D136=policy_name_clustering!$A$8,policy_name_clustering!$C$8,D136=policy_name_clustering!$A$9,policy_name_clustering!$C$9,D136=policy_name_clustering!$A$10,policy_name_clustering!$C$10,D136=policy_name_clustering!$A$11,policy_name_clustering!$C$11,D136=policy_name_clustering!$A$12,policy_name_clustering!$C$12,D136="-","")} | G136: =solar_cum_cap!C129 -> 7 | H136: =estimated_capacity!C123 -> 292.54863 | I136: {=_xlfn.IFS(D136= ""," ",D136<> " ",F136*(G136/H136))} -> 0 | J136: {=_xlfn.IFS(D136= ""," ",D136<> " ",(H136-F136)*(G136/H136))} -> 7 | K136: {=IF(ISNUMBER(H136),_xlfn.IFS(D136= ""," ",D136<> " ",F136*(G136/H136)),"")} -> 0
A137: DNK | B137: 2011 | D137: - | E137: {=_xlfn.IFS(D137=policy_name_clustering!$A$2,policy_name_clustering!$C$2,D137=policy_name_clustering!$A$3,policy_name_clustering!$C$3,D137=policy_name_clustering!$A$4,policy_name_clustering!$C$4,D137=policy_name_clustering!$A$5,policy_name_clustering!$C$5,D137=policy_name_clustering!$A$6,policy_name_clustering!$C$6,D137=policy_name_clustering!$A$7,policy_name_clustering!$C$7,D137=policy_name_clustering!$A$8,policy_name_clustering!$C$8,D137=policy_name_clustering!$A$9,policy_name_clustering!$C$9,D137=policy_name_clustering!$A$10,policy_name_clustering!$C$10,D137=policy_name_clustering!$A$11,policy_name_clustering!$C$11,D137=policy_name_clustering!$A$12,policy_name_clustering!$C$12,D137="-","")} | G137: =solar_cum_cap!C130 -> 17 | H137: =estimated_capacity!C124 -> 407.92447 | I137: {=_xlfn.IFS(D137= ""," ",D137<> " ",F137*(G137/H137))} -> 0 | J137: {=_xlfn.IFS(D137= ""," ",D137<> " ",(H137-F137)*(G137/H137))} -> 17 | K137: {=IF(ISNUMBER(H137),_xlfn.IFS(D137= ""," ",D137<> " ",F137*(G137/H137)),"")} -> 0
...

Sheet cumulative_effects
A1: policy instrument | B1: error-adjusted Cumulative policy instrument effect in GW
A2: FiT | B2: =SUMIFS(effect_quant_by_period!$I$2:$I$506,effect_quant_by_period!$D$2:$D$506,A2,effect_quant_by_period!$B$2:$B$506,estimated_capacity!$L$1)/1000 -> 67.74148
A3: FiT level increased | B3: =SUMIFS(effect_quant_by_period!$I$2:$I$506,effect_quant_by_period!$D$2:$D$506,A3,effect_quant_by_period!$B$2:$B$506,estimated_capacity!$L$1)/1000 -> 3.771609
A4: FiT level increased, FiP level increased | B4: =SUMIFS(effect_quant_by_period!$I$2:$I$506,effect_quant_by_period!$D$2:$D$506,A4,effect_quant_by_period!$B$2:$B$506,estimated_capacity!$L$1)/1000 -> 4.7516627
A5: FiP, TGC aim increase | B5: =SUMIFS(effect_quant_by_period!$I$2:$I$506,effect_quant_by_period!$D$2:$D$506,A5,effect_quant_by_period!$B$2:$B$506,estimated_capacity!$L$1)/1000 -> 18.390535
A6: tax incentive increase | B6: =SUMIFS(effect_quant_by_period!$I$2:$I$506,effect_quant_by_period!$D$2:$D$506,A6,effect_quant_by_period!$B$2:$B$506,estimated_capacity!$L$1)/1000 -> 13.122246
A7: FiT prolonged, Tax incentive prolonged, Tender | B7: =SUMIFS(effect_quant_by_period!$I$2:$I$506,effect_quant_by_period!$D$2:$D$506,A7,effect_quant_by_period!$B$2:$B$506,estimated_capacity!$L$1)/1000 -> 13.691958
A8: Tender | B8: =SUMIFS(effect_quant_by_period!$I$2:$I$506,effect_quant_by_period!$D$2:$D$506,A8,effect_quant_by_period!$B$2:$B$506,estimated_capacity!$L$1)/1000 -> 41.880652
A9: Soft loan, Tender | B9: =SUMIFS(effect_quant_by_period!$I$2:$I$506,effect_quant_by_period!$D$2:$D$506,A9,effect_quant_by_period!$B$2:$B$506,estimated_capacity!$L$1)/1000 -> 24.73261
A10: Tender, FiP | B10: =SUMIFS(effect_quant_by_period!$I$2:$I$506,effect_quant_by_period!$D$2:$D$506,A10,effect_quant_by_period!$B$2:$B$506,estimated_capacity!$L$1)/1000 -> 6.720556
A11: Soft loan, FiP, Tender | B11: =SUMIFS(effect_quant_by_period!$I$2:$I$506,effect_quant_by_period!$D$2:$D$506,A11,effect_quant_by_period!$B$2:$B$506,estimated_capacity!$L$1)/1000 -> 11.094588
A12: Total policy effect | B12: =SUM(B2:B11) -> 205.8979
A13: Non-policy factors | B13: =SUMIFS(effect_quant_by_period!$J$2:$J$498,effect_quant_by_period!$B$2:$B$498,estimated_capacity!$L$1)/1000 -> 50.124984 | C13: =(estimated_capacity!G2)-B12-B13 -> -8.2150493 | D13: difference as model estimated cumulative capacity is not error adjusted!
A14: Policy effect share | B14: =B12/SUM(B12:B13) -> 0.80421678
A18: policy instrument | B18: error-adjusted Cumulative policy instrument effect in GW
A19: FiT/FiP-based | B19: =SUM(B2:B4) -> 76.264752
A20: Tax-based | B20: =SUM(B6) -> 13.122246
A21: Tender-based | B21: =SUM(B8) -> 41.880652
A22: Policy mix | B22: =SUM(B7,B9,B11,B5) -> 67.90969
A23: Other single instrument | B23: =SUM(B10) -> 6.720556
A24: Total policy effect | B24: =B12 -> 205.8979
A25: Non-policy factors | B25: =B13 -> 50.124984

Sheet policy_contributions_cum
A1: id | B1: time | C1: policy | D1: effect_mw | E1: benchmark_mw | F1: cumulative_effect_mw
A2: DEU | B2: 2004 | C2: effect_tisDEU.2004 | D2: 214.54302 | E2: 406.9602 | F2: 214.54302
A3: DEU | B3: 2005 | C3: effect_tisDEU.2004 | D3: 522.83169 | E3: 718.49486 | F3: 737.37471
A4: DEU | B4: 2006 | C4: effect_tisDEU.2004 | D4: 974.95085 | E4: 1179.0671 | F4: 1712.3256
A5: DEU | B5: 2007 | C5: effect_tisDEU.2004 | D5: 1615.6704 | E5: 1823.1247 | F5: 3327.996
A6: DEU | B6: 2008 | C6: effect_tisDEU.2004 | D6: 2585.2388 | E6: 2806.7767 | F6: 5913.2348
A7: DEU | B7: 2009 | C7: effect_tisDEU.2004 | D7: 3849.6116 | E7: 4063.9566 | F7: 9762.8464
A8: DEU | B8: 2010 | C8: effect_tisDEU.2004 | D8: 6333.6344 | E8: 6607.4063 | F8: 16096.481
A9: DEU | B9: 2011 | C9: effect_tisDEU.2004 | D9: 10211.357 | E9: 10546.33 | F9: 26307.838
A10: DEU | B10: 2012 | C10: effect_tisDEU.2004 | D10: 5451.9404 | E10: 5375.5431 | F10: 31759.778
A11: DEU | B11: 2013 | C11: effect_tisDEU.2004 | D11: 3206.7747 | E11: 2988.3031 | F11: 34966.553
A12: DEU | B12: 2014 | C12: effect_tisDEU.2004 | D12: 1675.5024 | E12: 1394.667 | F12: 36642.055
A13: DEU | B13: 2015 | C13: effect_tisDEU.2004 | D13: 1788.3217 | E13: 1498.415 | F13: 38430.377
... A142: POL | B142: 2023 | C142: effect_tisPOL.2018 | D142: 7227.9413 | E142: 7649.0141 | F142: 16025.468

Sheet solar_cum_cap
A1: year | B1: country | C1: solar.cap | E1: Eur_cum_cap_solar_GW | G1: end sample year | H1: 2023
A2: 2000 | B2: AUT | C2: 5 | E2: =SUMIF($A$2:$A$466,$H$1,$C$2:$C$466)/1000 -> 256.02288
A3: 2001 | B3: AUT | C3: 7
A4: 2002 | B4: AUT | C4: 9
A5: 2003 | B5: AUT | C5: 23
A6: 2004 | B6: AUT | C6: 27
A7: 2005 | B7: AUT | C7: 21.018
A8: 2006 | B8: AUT | C8: 22.387
A9: 2007 | B9: AUT | C9: 24.238
A10: 2008 | B10: AUT | C10: 30.12
A11: 2009 | B11: AUT | C11: 48.915
A12: 2010 | B12: AUT | C12: 88.813
A13: 2011 | B13: AUT | C13: 174.07
A14: 2012 | B14: AUT | C14: 337.483
... A466: 2023 | B466: SWE | C466: 3993

Sheet estimated_capacity
A1: id | B1: time | C1: estimated_cumulative_solar_cap_MW | G1: Eur_estimated_cum_cap_GW | K1: end sample year | L1: 2023
A2: AUT | B2: 2001 | C2: 37.662573 | G2: =SUMIF(B2:B446,$L$1,C2:C446)/1000 -> 247.80783
A3: AUT | B3: 2002 | C3: 67.605946
A4: AUT | B4: 2003 | C4: 111.45853
A5: AUT | B5: 2004 | C5: 179.5902
A6: AUT | B6: 2005 | C6: 248.19562
A7: AUT | B7: 2006 | C7: 322.68046
A8: AUT | B8: 2007 | C8: 402.12565
A9: AUT | B9: 2008 | C9: 499.52628
A10: AUT | B10: 2009 | C10: 601.77341
A11: AUT | B11: 2010 | C11: 745.20818
A12: AUT | B12: 2011 | C12: 942.06133
A13: AUT | B13: 2012 | C13: 1181.3722
A14: AUT | B14: 2013 | C14: 1478.0097
... A446: SWE | B446: 2023 | C446: 3227.1494

Sheet policy_name_clustering
A1: full name | B1: dominant instrument | C1: cluster name
A2: FiT | B2: FiT | C2: FiT/FiP-based
A3: FiT level increased | B3: FiT | C3: FiT/FiP-based
A4: FiT prolonged, Tax incentive prolonged, Tender | B4: FiT | C4: Policy mix
A5: FiT level increased, FiP level increased | B5: FiT | C5: FiT/FiP-based
A6: FiP, TGC aim increase | B6: FiP | C6: Policy mix
A7: Tax incentive increase | B7: Tax incentive | C7: Tax-based
A8: Tender | B8: Tender | C8: Tender-based
A9: Soft loan, Tender | B9: Tender | C9: Policy mix
A10: Tender, FiP | B10: Tender | C10: Other single instrument
A11: Soft loan, FiP, Tender | B11: Tender | C11: Policy mix
A12: Tender, FiT level increased, Tax incentive prolonged | B12: Tender | C12: Policy mix
